Workbook
Name Affiche_Semaine: #REF!
Name Affiche_Semaine: #REF!
Name Affiche_Semaine: #REF!
Name Affiche_Semaine: #REF!
Name Affiche_Semaine: #REF!
Name Affiche_Semaine: #REF!
Name Affiche_Semaine: #REF!
Name Affiche_Semaine: #REF!
Name Affiche_Semaine: #REF!
Name Affiche_Semaine: #REF!
Name Affiche_Semaine: #REF!
Name Affiche_Semaine: #REF!
Name Affiche_Semaine: #REF!
Name asd: #REF!
Name asd: #REF!
Name asd: #REF!
Name asd: #REF!
Name asd: #REF!
Name asd: #REF!
Name asd: #REF!
Name asd: #REF!
Name asd: #REF!
Name asd: #REF!
Name asd: #REF!
Name asd: #REF!
Name bis: #REF!
Name bis: #REF!
Name bis: #REF!
Name bis: #REF!
Name bis: #REF!
Name bis: #REF!
Name bis: #REF!
Name bis: #REF!
Name bis: #REF!
Name bis: #REF!
Name bis: #REF!
Name bis: #REF!
Name BN: #REF!
Name BN: #REF!
Name BN: #REF!
Name BN: #REF!
Name BN: #REF!
Name BN: #REF!
Name BN: #REF!
Name BN: #REF!
Name BN: #REF!
Name CjmDuProjet: #REF!
Name CjmDuProjet: #REF!
Name CjmDuProjet: #REF!
Name CjmDuProjet: #REF!
Name CjmDuProjet: #REF!
Name CjmDuProjet: #REF!
Name CjmDuProjet: #REF!
Name CjmDuProjet: #REF!
Name CjmDuProjet: #REF!
Name CjmDuProjet: #REF!
Name CjmDuProjet: #REF!
Name CjmDuProjet: #REF!
Name CjmDuProjet: #REF!
Name Direction: #REF!

Sheet Fiche Doc
B1: FICHE DE REVUE PROJET | E1: Référence: F-AFF-13
E2: Version: 03
E3: Date: Novembre 2024
A5: Dashboard
A7: Rédigé par | B7: Vérifié par | D7: Approuvé par
A8: Abdelkarim AMARA | B8: Nadia BOUKEF | D8: Ahmed SAHLI
A9: Directeur AMOA- Réseaux HD | B9: Responsable Management Qualité | D9: Directeur Général Adjoint
A11: Date | B11: Version | C11: Motif de mise à jour
A12: 45505 | B12: 1 | C12: Création du document
A13: 45608 | B13: 2 | C13: Ajout du sheet Statistique et séparation des KPI figures du dashboard
A14: 45597 | B14: 3 | C14: Optimisation du fichier

Sheet Fiche identification
A1: Identification / Decription du projet | D1: Dashboard
A2: Project | B2: A24001 - PFS_AIE
A3: Contract ID | B3: 003/C/MINEPAT/CTS/PFS-AIE/UGP/CCCM-SPI/CSPM
A4: Client | B4: Projet Filets Sociaux Adaptatifs et Inclusion Economique
A5: Project name | B5: Mise à jour technologique et mise à niveau du SIG-I pour integrer les besoins du projet Filets Sociaux adaptatifs et d'Inclusion Economique
A6: Project Description | B6: Mise à jour technologique et mise à niveau du SIG-I pour integrer les besoins du projet Filets Sociaux adaptatifs et d'Inclusion Economique
A7: Bailleur de fonds | B7: Banque Mondiale (IDA)
A8: Modèle business (Seul/En groupement) | B8: Seul
A9: Type d'engagement Type (T&M / FP) | B9: FP
A10: Project manager | B10: Ahmed Amine Amiri
A11: Date de démarrage | B11: 45328
A12: Date de fin prévue | B12: 46058
A13: Durée du contrat Duration (En jours) | B13: 731
A15: Statut contractuel et financier initial (DI)
A16: Devise Projet | B16: FCFA
A17: Budget initial TO (incluant licences & soutraitances) | B17: 248992444
A18: Budget Licences & soutraitance (Initial) | B18: 0
A19: Avenant (O/N) | B19: Non
A20: Montant Avenant | B20: 0
A21: Total avenants | B21: 0
A22: Budget total (avenants inclus) | B22: 248992444
A23: Budget initial TO (incluant licences & soutraitances) en TND | B23: 1269861.5
A24: Budget Projet Rémunération en TND | B24: =#REF! -> #REF!
A25: Total avenants en TND | B25: 0
A26: Budget total (avenants inclus) en TND | B26: 1269861.5
A27: PPR (Provision Pour Risques) en TND | B27: =B26*5% -> 63493.073
A28: PPP (Provision Pour Pénalités) en TND | B28: 0
A29: Coût Total en TND (DI) | B29: =#REF! -> #REF!
A30: Marge nette vendue % | B30: =B31/B26 -> #VALUE!
A31: Marge nette vendue en TND | B31: l
A32: Workload vendu avenants inclus en JH | B32: 1717
A33: Workload initial en JH | B33: 1717
A34: Workload avenants en JH | B34: 0
A35: Workload Garantie en JH | B35: 75

Sheet TCC
A1: Dashboard
A5: Ressource | B5: TCC 2024 | C5: TCC (inclus FG) | D5: TCC 2025 | E5: TCC 2025 (inclus FG)
A6: Ahmed HAMADI | B6: 1813.3333 | C6: =(B6*1.7)/22 -> 140.12121 | D6: 1813.3333 | E6: =(D6*1.7)/20 -> 154.13333
A7: ASMA BELGHUITH | B7: 3310.909 | C7: =(B7*1.7)/22 -> 255.84297 | D7: 3310.909 | E7: =(D7*1.7)/20 -> 281.42726
A8: AYMEN ABID | B8: 3007.2955 | C8: =(B8*1.7)/22 -> 232.38193 | D8: 3399.7742 | E8: =(D8*1.7)/20 -> 288.9808
A9: DORSAF BABAY | B9: 7851.5715 | C9: =(B9*1.7)/22 -> 606.71234 | D9: 8379.2124 | E9: =(D9*1.7)/20 -> 712.23306
A10: FATEN ZNAIDI | B10: 6275.241 | C10: =(B10*1.7)/22 -> 484.90499 | D10: 7121.4332 | E10: =(D10*1.7)/20 -> 605.32182
A11: HASSEN BEN HMIDA | B11: 5112.3322 | C11: =(B11*1.7)/22 -> 395.04385 | D11: 5487.5059 | E11: =(D11*1.7)/20 -> 466.43801
A12: ISLEM BEN SAID | B12: 2000 | C12: =(B12*1.7)/22 -> 154.54545 | D12: 3774.1471 | E12: =(D12*1.7)/20 -> 320.8025
A13: MOATEZ ZNAIDI | B13: 1895 | C13: =(B13*1.7)/22 -> 146.43182 | D13: 3500.2622 | E13: =(D13*1.7)/20 -> 297.52229
A14: NIDHAL MAROUANI | B14: 2968.061 | C14: =(B14*1.7)/22 -> 229.35017 | D14: 4044.2673 | E14: =(D14*1.7)/20 -> 343.76272
A15: RAMI LOULOU | B15: 12540.872 | C15: =(B15*1.7)/22 -> 969.06737 | D15: 11275.647 | E15: =(D15*1.7)/20 -> 958.42999
A16: WAFA BOUSETTA | B16: 2063.53 | C16: =(B16*1.7)/22 -> 159.45459 | D16: 2180.2678 | E16: =(D16*1.7)/20 -> 185.32276
A17: AHMED AMINE AMIRI | B17: 9265.5224 | C17: =(B17*1.7)/22 -> 715.97218 | D17: 10177.751 | E17: =(D17*1.7)/20 -> 865.10884
... A23: Safouene BEN GALI | B23: 3776.3745 | C23: =(B23*1.7)/22 -> 291.81075 | D23: 3776.3745 | E23: =(D23*1.7)/20 -> 320.99183
A24: Total | B24: =SUM(B6:B23) -> 84507.322 | C24: =SUM(C6:C23) -> 6530.1113 | D24: =SUM(D6:D23) -> 89709.09 | E24: =SUM(E6:E23) -> 7625.2727
A29: Autres Frais | B29: Coût d'achat (DT) | C29: Coût de vente (DI/contrat) en DT | E29: Taux de change
A30: Frais de mission (Perdiem) | B30: =80*G24 -> 0 | C30: 0 | E30: 1 | F30: 3.4883
A31: Frais de mission (Billet) | C31: 0
A32: Autres | C32: 0

Sheet Missions
L1: 80
A2: N° | B2: PHASE | C2: Poste | D2: Ressource | E2: Date prévisionnel | F2: Date Début | G2: Date Fin | H2: Nom Bénéficiaire | I2: Billet | J2: Timbre | K2: Séjour | L2: Perdiem € | M2: Taux de change | N2: Perdiem DT | O2: Coût /Mission
A3: 1 | B3: Sprint 11 | C3: Chef de mission | D3: Ahmed BERRED | E3: 45293 | F3: 45303 | G3: 45303 | H3: Ahmed BERRED | I3: 3755.5 | J3: 60 | K3: 7 | L3: 80 | M3: 3.3728 | N3: =K3*L3*M3 -> 1888.768 | O3: =N3+J3+I3 -> 5704.268
A4: 2 | B4: Sprint 11 | C4: BA | D4: Faten Znaidi | E4: 45628 | F4: 45303 | G4: 45303 | H4: Faten Znaidi | I4: 3755.5 | J4: 60 | K4: 7 | L4: 80 | M4: 3.3728 | N4: =K4*L4*M4 -> 1888.768 | O4: =N4+J4+I4 -> 5704.268
A5: 3
A6: 4
A7: 5
A8: 6
A9: 7
A10: 8
A11: 9
A12: 10
A13: 11
M14: TOTAL | N14: =SUM(N3:N13) -> 3777.536 | O14: =SUM(O3:O13) -> 11408.536
K15: 49 | L15: 19298228 | M15: 0.0051 | O15: =M15*L15 -> 98420.963
I19: Facture 2025-05 du 03/02/2025
C20: 1073250 | D20: 1 | E20: =C20*D20 -> 1073250 | H20: Voyage/ Billet | I20: =1073250*#REF! -> #REF! | J20: =I20*3 -> #REF!
C21: 100170 | D21: 7 | E21: =C21*D21 -> 701190 | H21: Perdiem | I21: =151448*#REF! -> #REF! | J21: =I21*21 -> #REF!
C22: 11925 | D22: 7 | E22: =C22*D22 -> 83475 | H22: Transport | I22: =71550*#REF! -> #REF! | J22: =I22*7 -> #REF!
C23: 39353 | D23: 7 | E23: =C23*D23 -> 275471 | H23: Total consommé | J23: =SUM(J20:J22) -> #REF!
C24: 71550 | D24: 7 | E24: =C24*D24 -> 500850 | H24: RAC | J24: =O15-J23 -> #REF!
E27: =SUM(E20:E24) -> 2634236 | F27: =E27*0.0051 -> 13434.604
E29: 1033200 | F29: =E29/7 -> 147600

Sheet Avancement_Facturation
A2: Dashboard
C3: Total contrat HT (DT) | D3: ='Fiche identification'!B26 -> 1269861.5
A4: Mois en cours | C4: Total contrat HT (FCFA) | D4: ='Fiche identification'!B22 -> 248992444
B6: 45323 | C6: 45352 | D6: 45383 | E6: 45413 | F6: 45444 | G6: 45474 | H6: 45505 | I6: 45536 | J6: 45566 | K6: 45597 | L6: 45627 | M6: 45658 | N6: 45689 | O6: 45717 | P6: 45748 | Q6: 45778 | R6: 45809 | S6: 45839 | T6: 45870 | U6: 45901 | V6: 45931 | W6: 45962 | X6: 45992 | Y6: 46023 | Z6: 46054
A7: Num échéance | C7: 1 | F7: 2 | H7: 3 | J7: 4 | L7: 5 | N7: 6 | T7: 7 | Z7: 8
A8: Description | C8: Facture Sprint 1 | F8: Facture Sprint 2+3+4 | H8: Facture Sprint 5+6 | J8: Facture Sprint 7+8 | L8: Facture Sprint 9+10 | N8: Facture Sprint 11+12 | T8: MNT 18 premiers mois | Z8: MNT 6 derniers mois
A9: % | C9: 0.1 | F9: 0.16 | H9: 0.16 | J9: 0.16 | L9: 0.16 | T9: 0.05 | Z9: 0.05
A10: Evènement
A11: Devise | C11: FCFA | F11: FCFA | H11: FCFA | J11: FCFA | L11: FCFA | N11: FCFA | T11: FCFA | Z11: FCFA
A12: Montant | C12: =$D$4*C9 -> 24899244 | F12: =$D$4*F9 -> 39838791 | H12: =$D$4*H9 -> 39838791 | J12: =$D$4*J9 -> 39838791 | L12: =$D$4*L9 -> 39838791 | N12: =$D$4*N9 -> 0 | T12: =$D$4*T9 -> 12449622 | Z12: =$D$4*Z9 -> 12449622
A13: Montant en TND | C13: =$D$3*C9 -> 126986.15 | F13: =$D$3*F9 -> 203177.83 | H13: =$D$3*H9 -> 203177.83 | J13: =$D$3*J9 -> 203177.83 | L13: =$D$3*L9 -> 203177.83 | N13: =$D$3*N9 -> 0 | T13: =$D$3*T9 -> 63493.073 | Z13: =$D$3*Z9 -> 63493.073
A14: Reste à facturer en TND | C14: =$D$3-C13 -> 1142875.3 | F14: =C14-F13 -> 939697.48 | H14: =F14-H13 -> 736519.65 | J14: =H14-J13 -> 533341.82 | L14: =J14-L13 -> 330163.98 | N14: =L14-N13 -> 330163.98 | T14: =N14-T13 -> 266670.91 | Z14: =T14-Z13 -> 203177.83
A15: Cumul facturation | C15: =C13 -> 126986.15 | D15: =C15+D13 -> 126986.15 | E15: =D15+E13 -> 126986.15 | F15: =E15+F13 -> 330163.98 | G15: =F15+G13 -> 330163.98 | H15: =G15+H13 -> 533341.82 | I15: =H15+I13 -> 533341.82 | J15: =I15+J13 -> 736519.65 | K15: =J15+K13 -> 736519.65 | ... S15: =R15+S13 -> 939697.48 | T15: =T13+S15 -> 1003190.6 | U15: =U13+T15 -> 1003190.6 | V15: =V13+U15 -> 1003190.6 | W15: =W13+V15 -> 1003190.6 | X15: =X13+W15 -> 1003190.6 | Y15: =Y13+X15 -> 1003190.6 | Z15: =Z13+Y15 -> 1066683.6
A16: Cumul facturation % | C16: =C13/$D$3+B16 -> 0.1 | D16: =D13/$D$3+C16 -> 0.1 | E16: =E13/$D$3+D16 -> 0.1 | F16: =F13/$D$3+E16 -> 0.26 | G16: =G13/$D$3+F16 -> 0.26 | H16: =H13/$D$3+G16 -> 0.42 | I16: =I13/$D$3+H16 -> 0.42 | J16: =J13/$D$3+I16 -> 0.58 | ... Z16: =Z13/$D$3+Y16 -> 0.84
A17: Reste à facturer % | C17: =1-C16 -> 0.9 | D17: =1-D16 -> 0.9 | E17: =1-E16 -> 0.9 | F17: =1-F16 -> 0.74 | G17: =1-G16 -> 0.74 | H17: =1-H16 -> 0.58 | I17: =1-I16 -> 0.58 | J17: =1-J16 -> 0.42 | ... Z17: =1-Z16 -> 0.16
A18: Date initiale | C18: 45357 | F18: 45449 | H18: 45510 | J18: 45571 | L18: 45632 | N18: 45694 | T18: 45875 | Z18: 46059
A19: Date prévisionnelle | C19: 45357 | F19: 45449 | H19: 45565 | J19: 45590 | L19: 45644 | N19: 45704 | T19: 45875 | Z19: 46059
A20: Date réelle | C20: 45365 | F20: 45496 | H20: 30/9/2024 | J20: 45593
A21: Statut | C21: Facturé | F21: Facturé | H21: Facturé | J21: Facturé
A22: Réglé (si facturé) O/N | C22: Oui | F22: Non | H22: Non | J22: Non
A23: Montant payé (Si réglé) | C23: 22969421
A24: Cumul payé | C24: =C23+B24 -> 22969421 | D24: =D23+C24 -> 22969421 | E24: =E23+D24 -> 22969421 | F24: =F23+E24 -> 22969421 | G24: =G23+F24 -> 22969421 | H24: =H23+G24 -> 22969421 | I24: =I23+H24 -> 22969421 | J24: =J23+I24 -> 22969421 | ... Z24: =Z23+Y24 -> 22969421
A25: Commentaires | C25: Payé le 21/08/2024

Sheet Recap Facturation (2)
A2: Dashboard | H2: Total contrat HT (DT) | I2: ='Fiche identification'!B26 -> 1269861.5 | J2: =J4*#REF! -> #REF!
H3: Total Rémunération (HT) | I3: 1171440.5
A4: Mois en cours | B4: =Dashboard!C22 -> 45997 | H4: Total contrat HT (FCFA) | I4: ='Fiche identification'!B22 -> 248992444 | J4: 222803390
B6: N° échéance | C6: Description | D6: % | E6: Devise | F6: Montant | G6: Date initiale | H6: Montant en TND | I6: Reste à facturer en TND | J6: Cumul facturation | K6: Cumul facturation % | L6: Reste à facturer % | M6: Date prévisionnelle | N6: Date réelle | O6: Statut | P6: Réglé (si facturé) O/N | Q6: Montant payé (Si réglé) | R6: Cumul payé | S6: Commentaires | T6: Commentaires2
A7: 45358 | B7: 1 | C7: Facture Sprint 1 | D7: 0.1 | E7: FCFA | F7: 22280339 | G7: =DATE(2024,3,6)+10 -> 45367 | H7: =F7*#REF! -> #REF! | I7: =$J$2-H7 -> #REF! | J7: =H7 -> #REF! | K7: =J7/$I$3 -> #REF! | L7: =100%-K7 -> #REF! | M7: =DATE(2024,3,6)+10 -> 45367 | N7: 45365 | O7: Facturé | P7: Oui | Q7: 22969421 | R7: 22969421 | S7: Payé le 21/08/2024
A8: 45450 | B8: 2 | C8: Facture Sprint 2+3+4 | D8: 0.16 | E8: FCFA | F8: 35767792 | G8: =DATE(2024,6,6)+10 -> 45459 | H8: =F8*#REF! -> #REF! | I8: =I7-H8 -> #REF! | J8: =H7+H8 -> #REF! | K8: =J8/$I$3 -> #REF! | L8: =100%-K8 -> #REF! | M8: =DATE(2024,6,6)+10 -> 45459 | N8: 45496 | O8: Facturé | P8: Non | R8: 22969421
A9: 45511 | B9: 3 | C9: Facture Sprint 5+6 | D9: 0.16 | E9: FCFA | F9: 35791642 | G9: =DATE(2024,8,6)+10 -> 45520 | H9: =F9*#REF! -> #REF! | I9: =I8-H9 -> #REF! | J9: =H7+H8+H9 -> #REF! | K9: =J9/$I$3 -> #REF! | L9: =100%-K9 -> #REF! | M9: =DATE(2024,9,20)+10 -> 45565 | N9: 30/9/2024 | O9: Facturé | P9: Non | R9: 22969421
A10: 45572 | B10: 4 | C10: Facture Sprint 7+8 | D10: 0.16 | E10: FCFA | F10: 35791642 | G10: =DATE(2024,10,6)+10 -> 45581 | H10: =F10*#REF! -> #REF! | I10: =I9-H10 -> #REF! | J10: =H7+H8+H9+H10 -> #REF! | K10: =J10/$I$3 -> #REF! | L10: =100%-K10 -> #REF! | M10: =DATE(2024,10,25) -> 45590 | N10: 45593 | O10: Facturé | P10: Non | R10: 22969421
A11: 45633 | B11: 5 | C11: Facture Sprint 9+10 | D11: 0.16 | E11: FCFA | F11: 35791642 | G11: =DATE(2024,12,6)+10 -> 45642 | H11: =F11*#REF! -> #REF! | I11: =I10-H11 -> #REF! | J11: =SUM(H7:H11) -> #REF! | K11: =J11/$I$3 -> #REF! | L11: =100%-K11 -> #REF! | M11: 45657 | N11: 45657 | O11: Facturé | P11: Non | R11: 22969421
A12: 45695 | B12: 6 | C12: Facture Sprint 11+12 | D12: 0.16 | E12: FCFA | F12: =J4*D12 -> 35648542 | G12: =DATE(2025,2,6)+10 -> 45704 | H12: =Tableau5[[#This Row],[Montant]]*#REF! -> #REF! | I12: =I11-H12 -> #REF! | J12: =SUM(H7:H12) -> #REF! | K12: =J12/$I$3 -> #REF! | L12: =100%-K12 -> #REF! | M12: 45704 | R12: 22969421
A13: 45876 | B13: 7 | C13: MNT 18 premiers mois | D13: 0.05 | E13: FCFA | F13: =J4*Tableau5[[#This Row],[%]] -> 11140170 | G13: =DATE(2025,8,6)+10 -> 45885 | H13: =Tableau5[[#This Row],[Montant]]*#REF! -> #REF! | I13: =I12-H13 -> #REF! | J13: =SUM(H7:H13) -> #REF! | K13: =J13/$I$3 -> #REF! | L13: =100%-K13 -> #REF! | M13: =DATE(2025,8,6)+10 -> 45885 | R13: 22969421
A14: 46060 | B14: 8 | C14: MNT 6 derniers mois | D14: 0.05 | E14: FCFA | F14: =J4*Tableau5[[#This Row],[%]] -> 11140170 | G14: =DATE(2026,2,6)+10 -> 46069 | H14: =Tableau5[[#This Row],[Montant]]*#REF! -> #REF! | I14: =I13-H14 -> #REF! | J14: =SUM(H7:H14) -> #REF! | K14: =J14/$I$3 -> #REF! | L14: =100%-K14 -> #REF! | M14: =DATE(2026,2,6)+10 -> 46069 | R14: 22969421

Sheet Coût Prévisionnel
A2: Dashboard
A4: Mois en cours
A6: Plan de charge | B6: 45323 | C6: 45352 | D6: 45383 | E6: 45413 | F6: 45444 | G6: 45474 | H6: 45505 | I6: 45536 | J6: 45566 | K6: 45597 | L6: 45627 | M6: 45658 | N6: 45689 | O6: 45717 | P6: 45748 | Q6: 45778 | R6: 45809 | S6: 45839 | T6: 45870 | U6: 45901 | V6: 45931 | W6: 45962 | X6: 45992 | Y6: 46023 | Z6: 46054
A7: Ahmed Hamadi | F7: 20 | G7: 20 | H7: 19 | I7: 20 | J7: 20 | K7: 0 | L7: 0 | M7: 0
A8: Asma Belghith | D8: 10 | F8: 10 | G8: 20 | H8: 15 | I8: 20 | J8: 20 | K8: 0 | L8: 0 | M8: 0
A9: Aymen Abid | E9: 20 | F9: 20 | G9: 20 | H9: 18 | I9: 18 | J9: 18 | K9: 10 | L9: 5 | M9: 0
A10: Dorsaf Babay | G10: 10 | H10: 10 | I10: 10 | J10: 10 | K10: 20 | L10: 10
A11: Faten Zenaidi | B11: 20 | C11: 20 | D11: 20 | E11: 20 | F11: 20 | G11: 20 | H11: 10 | I11: 10 | J11: 10 | K11: 15 | L11: 10 | M11: 15
A12: Hassen Ben Hamida | B12: 20 | C12: 20 | D12: 20 | E12: 20 | F12: 20 | G12: 20 | H12: 20 | I12: 20 | J12: 20 | K12: 15 | L12: 15 | M12: 5 | N12: 5 | O12: 1 | P12: 1 | Q12: 1 | R12: 1 | S12: 1 | T12: 1 | U12: 1 | V12: 1 | W12: 1 | X12: 1 | Y12: 1 | Z12: 1
A13: Islem Bensaid | G13: 20 | H13: 20 | I13: 20 | J13: 20 | K13: 15 | L13: 15 | M13: 5 | O13: 1 | P13: 1 | Q13: 1 | R13: 1 | S13: 1 | T13: 1 | U13: 1 | V13: 1 | W13: 1 | X13: 1 | Y13: 1 | Z13: 1
A14: Moataz Zenaidi | B14: 20 | C14: 20 | D14: 20 | E14: 20 | F14: 20 | G14: 20 | H14: 15 | I14: 20 | J14: 20 | K14: 15 | L14: 10 | M14: 20 | N14: 5 | O14: 1 | P14: 1 | Q14: 1 | R14: 1 | S14: 1 | T14: 1 | U14: 1 | V14: 1 | W14: 1 | X14: 1 | Y14: 1 | Z14: 1
A15: Nidhal Marouani | B15: 20 | C15: 20 | D15: 20 | E15: 20 | F15: 20 | G15: 20 | H15: 18 | I15: 20 | J15: 20 | K15: 20 | L15: 15 | M15: 10 | N15: 5 | O15: 1 | P15: 1 | Q15: 1 | R15: 1 | S15: 1 | T15: 1 | U15: 1 | V15: 1 | W15: 1 | X15: 1 | Y15: 1 | Z15: 1
A16: Rami Loulou | G16: 5 | H16: 5 | I16: 10 | J16: 10 | K16: 10 | L16: 10 | M16: 0 | O16: 1 | P16: 1 | Q16: 1 | R16: 1 | S16: 1 | T16: 1 | U16: 1 | V16: 1 | W16: 1 | X16: 1 | Y16: 1 | Z16: 1
A17: Slim Amiri | G17: 10
A18: Wafa Boussetta | B18: 15 | C18: 15 | D18: 15 | E18: 15 | F18: 15 | G18: 15 | H18: 10 | I18: 10 | J18: 10 | K18: 15 | L18: 10 | M18: 10
A19: Ahmed Amine AMIRI | B19: 20 | C19: 20 | D19: 20 | E19: 20 | F19: 20 | G19: 20 | H19: 20 | I19: 10 | J19: 15 | K19: 10 | L19: 10 | M19: 5 | N19: 5 | O19: 1 | P19: 1 | Q19: 1 | R19: 1 | S19: 1 | T19: 1 | U19: 1 | V19: 1 | W19: 1 | X19: 1 | Y19: 1 | Z19: 1
A20: Frais de mission (Perdiem) | W20: 28
A21: Frais de mission (Billet) | W21: 4
A22: Autres Frais
A23: Total | B23: =SUM(B7:B19) -> 115 | C23: =SUM(C7:C19) -> 115 | D23: =SUM(D7:D19) -> 125 | E23: =SUM(E7:E19) -> 135 | F23: =SUM(F7:F19) -> 165 | G23: =SUM(G7:G19) -> 220 | H23: =SUM(H7:H19) -> 180 | I23: =SUM(I7:I19) -> 188 | ... L23: =SUM(L7:L19) -> 110 | M23: 101 | N23: =SUM(N7:N19) -> 20 | O23: =SUM(O7:O19) -> 6 | P23: =SUM(P7:P19) -> 6 | Q23: =SUM(Q7:Q19) -> 6 | R23: =SUM(R7:R19) -> 6 | S23: =SUM(S7:S19) -> 6 | T23: =SUM(T7:T19) -> 6 | U23: =SUM(U7:U19) -> 6 | ... Z23: =SUM(Z7:Z19) -> 6
A24: Estimation To Complet (ETC) | B24: =SUM(B23:$Z$23)-B23 -> 1769 | C24: =SUM(C23:$Z$23)-C23 -> 1654 | D24: =SUM(D23:$Z$23)-D23 -> 1529 | E24: =SUM(E23:$Z$23)-E23 -> 1394 | F24: =SUM(F23:$Z$23)-F23 -> 1229 | G24: =SUM(G23:$Z$23)-G23 -> 1009 | H24: =SUM(H23:$Z$23)-H23 -> 829 | I24: =SUM(I23:$Z$23)-I23 -> 641 | ... Z24: =SUM(Z23:$Z$23)-Z23 -> 0
A25: Coût Prévisionnel
A26: Ahmed Hamadi | B26: =B7*TCC!$C6 -> 0 | C26: =C7*TCC!$C6 -> 0 | D26: =D7*TCC!$C6 -> 0 | E26: =E7*TCC!$C6 -> 0 | F26: =F7*TCC!$C6 -> 2802.4242 | G26: =G7*TCC!$C6 -> 2802.4242 | H26: =H7*TCC!$C6 -> 2662.303 | I26: =I7*TCC!$C6 -> 2802.4242 | ... L26: =L7*TCC!$C6 -> 0 | M26: =M7*TCC!$E6 -> 0 | N26: =N7*TCC!$E6 -> 0 | O26: =O7*TCC!$E6 -> 0 | P26: =P7*TCC!$E6 -> 0 | Q26: =Q7*TCC!$E6 -> 0 | R26: =R7*TCC!$E6 -> 0 | S26: =S7*TCC!$E6 -> 0 | T26: =T7*TCC!$E6 -> 0 | ... Z26: =Z7*TCC!$E6 -> 0
A27: Asma Belghith | B27: =B8*TCC!$C7 -> 0 | C27: =C8*TCC!$C7 -> 0 | D27: =D8*TCC!$C7 -> 2558.4297 | E27: =E8*TCC!$C7 -> 0 | F27: =F8*TCC!$C7 -> 2558.4297 | G27: =G8*TCC!$C7 -> 5116.8594 | H27: =H8*TCC!$C7 -> 3837.6445 | I27: =I8*TCC!$C7 -> 5116.8594 | ... L27: =L8*TCC!$C7 -> 0 | M27: =M8*TCC!$E7 -> 0 | N27: =N8*TCC!$E7 -> 0 | O27: =O8*TCC!$E7 -> 0 | P27: =P8*TCC!$E7 -> 0 | Q27: =Q8*TCC!$E7 -> 0 | R27: =R8*TCC!$E7 -> 0 | S27: =S8*TCC!$E7 -> 0 | T27: =T8*TCC!$E7 -> 0 | ... Z27: =Z8*TCC!$E7 -> 0
A28: Aymen Abid | B28: =B9*TCC!$C8 -> 0 | C28: =C9*TCC!$C8 -> 0 | D28: =D9*TCC!$C8 -> 0 | E28: =E9*TCC!$C8 -> 4647.6385 | F28: =F9*TCC!$C8 -> 4647.6385 | G28: =G9*TCC!$C8 -> 4647.6385 | H28: =H9*TCC!$C8 -> 4182.8747 | I28: =I9*TCC!$C8 -> 4182.8747 | ... L28: =L9*TCC!$C8 -> 1161.9096 | M28: =M9*TCC!$E8 -> 0 | N28: =N9*TCC!$E8 -> 0 | O28: =O9*TCC!$E8 -> 0 | P28: =P9*TCC!$E8 -> 0 | Q28: =Q9*TCC!$E8 -> 0 | R28: =R9*TCC!$E8 -> 0 | S28: =S9*TCC!$E8 -> 0 | T28: =T9*TCC!$E8 -> 0 | ... Z28: =Z9*TCC!$E8 -> 0
A29: Dorsaf Babay | B29: =B10*TCC!$C9 -> 0 | C29: =C10*TCC!$C9 -> 0 | D29: =D10*TCC!$C9 -> 0 | E29: =E10*TCC!$C9 -> 0 | F29: =F10*TCC!$C9 -> 0 | G29: =G10*TCC!$C9 -> 6067.1234 | H29: =H10*TCC!$C9 -> 6067.1234 | I29: =I10*TCC!$C9 -> 6067.1234 | ... L29: =L10*TCC!$C9 -> 6067.1234 | M29: =M10*TCC!$E9 -> 0 | N29: =N10*TCC!$E9 -> 0 | O29: =O10*TCC!$E9 -> 0 | P29: =P10*TCC!$E9 -> 0 | Q29: =Q10*TCC!$E9 -> 0 | R29: =R10*TCC!$E9 -> 0 | S29: =S10*TCC!$E9 -> 0 | T29: =T10*TCC!$E9 -> 0 | ... Z29: =Z10*TCC!$E9 -> 0
A30: Faten Zenaidi | B30: =B11*TCC!$C10 -> 9698.0997 | C30: =C11*TCC!$C10 -> 9698.0997 | D30: =D11*TCC!$C10 -> 9698.0997 | E30: =E11*TCC!$C10 -> 9698.0997 | F30: =F11*TCC!$C10 -> 9698.0997 | G30: =G11*TCC!$C10 -> 9698.0997 | H30: =H11*TCC!$C10 -> 4849.0499 | I30: =I11*TCC!$C10 -> 4849.0499 | ... L30: =L11*TCC!$C10 -> 4849.0499 | M30: =M11*TCC!$E10 -> 9079.8274 | N30: =N11*TCC!$E10 -> 0 | O30: =O11*TCC!$E10 -> 0 | P30: =P11*TCC!$E10 -> 0 | Q30: =Q11*TCC!$E10 -> 0 | R30: =R11*TCC!$E10 -> 0 | S30: =S11*TCC!$E10 -> 0 | T30: =T11*TCC!$E10 -> 0 | ... Z30: =Z11*TCC!$E10 -> 0
A31: Hassen Ben Hamida | B31: =B12*TCC!$C11 -> 7900.8771 | C31: =C12*TCC!$C11 -> 7900.8771 | D31: =D12*TCC!$C11 -> 7900.8771 | E31: =E12*TCC!$C11 -> 7900.8771 | F31: =F12*TCC!$C11 -> 7900.8771 | G31: =G12*TCC!$C11 -> 7900.8771 | H31: =H12*TCC!$C11 -> 7900.8771 | I31: =I12*TCC!$C11 -> 7900.8771 | ... L31: =L12*TCC!$C11 -> 5925.6578 | M31: =M12*TCC!$E11 -> 2332.19 | N31: =N12*TCC!$E11 -> 2332.19 | O31: =O12*TCC!$E11 -> 466.43801 | P31: =P12*TCC!$E11 -> 466.43801 | Q31: =Q12*TCC!$E11 -> 466.43801 | R31: =R12*TCC!$E11 -> 466.43801 | S31: =S12*TCC!$E11 -> 466.43801 | T31: =T12*TCC!$E11 -> 466.43801 | ... Z31: =Z12*TCC!$E11 -> 466.43801
A32: Islem Bensaid | B32: =B13*TCC!$C12 -> 0 | C32: =C13*TCC!$C12 -> 0 | D32: =D13*TCC!$C12 -> 0 | E32: =E13*TCC!$C12 -> 0 | F32: =F13*TCC!$C12 -> 0 | G32: =G13*TCC!$C12 -> 3090.9091 | H32: =H13*TCC!$C12 -> 3090.9091 | I32: =I13*TCC!$C12 -> 3090.9091 | ... L32: =L13*TCC!$C12 -> 2318.1818 | M32: =M13*TCC!$E12 -> 1604.0125 | N32: =N13*TCC!$E12 -> 0 | O32: =O13*TCC!$E12 -> 320.8025 | P32: =P13*TCC!$E12 -> 320.8025 | Q32: =Q13*TCC!$E12 -> 320.8025 | R32: =R13*TCC!$E12 -> 320.8025 | S32: =S13*TCC!$E12 -> 320.8025 | T32: =T13*TCC!$E12 -> 320.8025 | ... Z32: =Z13*TCC!$E12 -> 320.8025
A33: Moataz Zenaidi | B33: =B14*TCC!$C13 -> 2928.6364 | C33: =C14*TCC!$C13 -> 2928.6364 | D33: =D14*TCC!$C13 -> 2928.6364 | E33: =E14*TCC!$C13 -> 2928.6364 | F33: =F14*TCC!$C13 -> 2928.6364 | G33: =G14*TCC!$C13 -> 2928.6364 | H33: =H14*TCC!$C13 -> 2196.4773 | I33: =I14*TCC!$C13 -> 2928.6364 | ... L33: =L14*TCC!$C13 -> 1464.3182 | M33: =M14*TCC!$E13 -> 5950.4458 | N33: =N14*TCC!$E13 -> 1487.6115 | O33: =O14*TCC!$E13 -> 297.52229 | P33: =P14*TCC!$E13 -> 297.52229 | Q33: =Q14*TCC!$E13 -> 297.52229 | R33: =R14*TCC!$E13 -> 297.52229 | S33: =S14*TCC!$E13 -> 297.52229 | T33: =T14*TCC!$E13 -> 297.52229 | ... Z33: =Z14*TCC!$E13 -> 297.52229
A34: Nidhal Marouani | B34: =B15*TCC!$C14 -> 4587.0034 | C34: =C15*TCC!$C14 -> 4587.0034 | D34: =D15*TCC!$C14 -> 4587.0034 | E34: =E15*TCC!$C14 -> 4587.0034 | F34: =F15*TCC!$C14 -> 4587.0034 | G34: =G15*TCC!$C14 -> 4587.0034 | H34: =H15*TCC!$C14 -> 4128.303 | I34: =I15*TCC!$C14 -> 4587.0034 | ... L34: =L15*TCC!$C14 -> 3440.2525 | M34: =M15*TCC!$E14 -> 3437.6272 | N34: =N15*TCC!$E14 -> 1718.8136 | O34: =O15*TCC!$E14 -> 343.76272 | P34: =P15*TCC!$E14 -> 343.76272 | Q34: =Q15*TCC!$E14 -> 343.76272 | R34: =R15*TCC!$E14 -> 343.76272 | S34: =S15*TCC!$E14 -> 343.76272 | T34: =T15*TCC!$E14 -> 343.76272 | ... Z34: =Z15*TCC!$E14 -> 343.76272
A35: Rami Loulou | B35: =B16*TCC!$C15 -> 0 | C35: =C16*TCC!$C15 -> 0 | D35: =D16*TCC!$C15 -> 0 | E35: =E16*TCC!$C15 -> 0 | F35: =F16*TCC!$C15 -> 0 | G35: =G16*TCC!$C15 -> 4845.3368 | H35: =H16*TCC!$C15 -> 4845.3368 | I35: =I16*TCC!$C15 -> 9690.6737 | ... L35: =L16*TCC!$C15 -> 9690.6737 | M35: =M16*TCC!$E15 -> 0 | N35: =N16*TCC!$E15 -> 0 | O35: =O16*TCC!$E15 -> 958.42999 | P35: =P16*TCC!$E15 -> 958.42999 | Q35: =Q16*TCC!$E15 -> 958.42999 | R35: =R16*TCC!$E15 -> 958.42999 | S35: =S16*TCC!$E15 -> 958.42999 | T35: =T16*TCC!$E15 -> 958.42999 | ... Z35: =Z16*TCC!$E15 -> 958.42999
A36: Slim Amiri | B36: =B17*TCC!$C16 -> 0 | C36: =C17*TCC!$C16 -> 0 | D36: =D17*TCC!$C16 -> 0 | E36: =E17*TCC!$C16 -> 0 | F36: =F17*TCC!$C16 -> 0 | G36: =G17*TCC!$C16 -> 1594.5459 | H36: =H17*TCC!$C16 -> 0 | I36: =I17*TCC!$C16 -> 0 | ... L36: =L17*TCC!$C16 -> 0 | M36: =M17*TCC!$E16 -> 0 | N36: =N17*TCC!$E16 -> 0 | O36: =O17*TCC!$E16 -> 0 | P36: =P17*TCC!$E16 -> 0 | Q36: =Q17*TCC!$E16 -> 0 | R36: =R17*TCC!$E16 -> 0 | S36: =S17*TCC!$E16 -> 0 | T36: =T17*TCC!$E16 -> 0 | ... Z36: =Z17*TCC!$E16 -> 0
A37: Wafa Boussetta | B37: =B18*TCC!$C17 -> 10739.583 | C37: =C18*TCC!$C17 -> 10739.583 | D37: =D18*TCC!$C17 -> 10739.583 | E37: =E18*TCC!$C17 -> 10739.583 | F37: =F18*TCC!$C17 -> 10739.583 | G37: =G18*TCC!$C17 -> 10739.583 | H37: =H18*TCC!$C17 -> 7159.7218 | I37: =I18*TCC!$C17 -> 7159.7218 | ... L37: =L18*TCC!$C17 -> 7159.7218 | M37: =M18*TCC!$E17 -> 8651.0884 | N37: =N18*TCC!$E17 -> 0 | O37: =O18*TCC!$E17 -> 0 | P37: =P18*TCC!$E17 -> 0 | Q37: =Q18*TCC!$E17 -> 0 | R37: =R18*TCC!$E17 -> 0 | S37: =S18*TCC!$E17 -> 0 | T37: =T18*TCC!$E17 -> 0 | ... Z37: =Z18*TCC!$E17 -> 0
A38: Ahmed Amine AMIRI | B38: =B19*TCC!$C18 -> 3574.2134 | C38: =C19*TCC!$C18 -> 3574.2134 | D38: =D19*TCC!$C18 -> 3574.2134 | E38: =E19*TCC!$C18 -> 3574.2134 | F38: =F19*TCC!$C18 -> 3574.2134 | G38: =G19*TCC!$C18 -> 3574.2134 | H38: =H19*TCC!$C18 -> 3574.2134 | I38: =I19*TCC!$C18 -> 1787.1067 | ... L38: =L19*TCC!$C18 -> 1787.1067 | M38: =M19*TCC!$E18 -> 982.90869 | N38: =N19*TCC!$E18 -> 982.90869 | O38: =O19*TCC!$E18 -> 196.58174 | P38: =P19*TCC!$E18 -> 196.58174 | Q38: =Q19*TCC!$E18 -> 196.58174 | R38: =R19*TCC!$E18 -> 196.58174 | S38: =S19*TCC!$E18 -> 196.58174 | T38: =T19*TCC!$E18 -> 196.58174 | ... Z38: =Z19*TCC!$E18 -> 196.58174
A39: Frais de mission (Perdiem) | H39: =H20*#REF! -> #REF! | I39: =I20*#REF! -> #REF! | J39: =J20*#REF! -> #REF! | K39: =K20*#REF! -> #REF! | L39: =L20*#REF! -> #REF! | M39: =M20*#REF! -> #REF! | N39: =N20*#REF! -> #REF! | O39: =O20*#REF! -> #REF! | ... Z39: =Z20*#REF! -> #REF!
A40: Frais de mission (Billet) | H40: =H21*#REF! -> #REF! | I40: =I21*#REF! -> #REF! | J40: =J21*#REF! -> #REF! | K40: =K21*#REF! -> #REF! | L40: =L21*#REF! -> #REF! | M40: =M21*#REF! -> #REF! | N40: =N21*#REF! -> #REF! | O40: =O21*#REF! -> #REF! | ... Z40: =Z21*#REF! -> #REF!
A41: Autres Frais
A42: Total | B42: =SUM(B26:B41) -> 39428.413 | C42: =SUM(C26:C41) -> 39428.413 | D42: =SUM(D26:D41) -> 41986.842 | E42: =SUM(E26:E41) -> 44076.051 | F42: =SUM(F26:F41) -> 49436.905 | G42: =SUM(G26:G41) -> 67593.25 | H42: =SUM(H26:H41) -> #REF! | I42: =SUM(I26:I41) -> #REF! | ... Z42: =SUM(Z26:Z41) -> #REF!
A43: Cumul | B43: =SUM(B$42:$Z42)-B42 -> #REF! | C43: =SUM(C$42:$Z42)-C42 -> #REF! | D43: =SUM(D$42:$Z42)-D42 -> #REF! | E43: =SUM(E$42:$Z42)-E42 -> #REF! | F43: =SUM(F$42:$Z42)-F42 -> #REF! | G43: =SUM(G$42:$Z42)-G42 -> #REF! | H43: =SUM(H$42:$Z42)-H42 -> #REF! | I43: =SUM(I$42:$Z42)-I42 -> #REF! | ... Z43: =SUM(Z$42:$Z42)-Z42 -> #REF!

Sheet Coût réel Actualisé
A2: Dashboard
A4: Mois en cours | B4: =Dashboard!C22 -> 45997
A6: Imputation Actuel | B6: 45328 | C6: 45357 | D6: 45388 | E6: 45418 | F6: 45449 | G6: 45479 | H6: 45510 | I6: 45541 | J6: 45571 | K6: 45602 | L6: 45632 | M6: 45663 | N6: 45689 | O6: 45717 | P6: 45748 | Q6: 45778 | R6: 45809 | S6: 45839 | T6: 45870 | U6: 45901 | V6: 45931 | W6: 45962 | X6: 45992 | Y6: 46023 | Z6: 46054
A7: Ahmed HAMADI | B7: 0 | C7: 0 | D7: 20 | E7: 20 | F7: 20 | G7: 18 | H7: 17 | I7: 18 | J7: 12 | K7: 0 | L7: 0 | M7: 0 | N7: 0
A8: ASMA BELGHUITH | B8: 0 | C8: 0 | D8: 0 | E8: 0 | F8: 9 | G8: 12.5 | H8: 13 | I8: 15.6875 | J8: 0 | K8: 0 | L8: 0 | M8: 0 | N8: 0
A9: AYMEN ABID | B9: 0 | C9: 6 | D9: 6 | E9: 16 | F9: 13 | G9: 16 | H9: 19 | I9: 13.5 | J9: 7.5 | K9: 15 | L9: 5.5 | M9: 0 | N9: 0 | O9: 0 | P9: 0.5 | Q9: 0 | R9: =25/8 -> 3.125 | S9: =2/8 -> 0.25 | T9: 0 | X9: =4/8 -> 0.5
A10: DORSAF BABAY | B10: 0 | C10: 0 | D10: 0 | E10: 0 | F10: 0 | G10: 11 | H10: 10 | I10: 10 | J10: 13.875 | K10: 10 | L10: 19 | M10: 9 | N10: 6 | O10: 0 | P10: 0 | Q10: 0 | R10: 0 | S10: 0 | T10: 0
A11: FATEN ZNAIDI | B11: 18 | C11: 19 | D11: 20 | E11: 18 | F11: 15 | G11: 14 | H11: 14.75 | I11: 18 | J11: 14.625 | K11: 19.125 | L11: 17.75 | M11: 16 | N11: 11.375 | O11: 4.5 | P11: 0.125 | Q11: 0 | R11: 0 | S11: 0 | T11: =2/8 -> 0.25
A12: HASSEN BEN HMIDA | B12: 18 | C12: 18 | D12: 22 | E12: 18 | F12: 19 | G12: 22 | H12: 17.75 | I12: 20.5 | J12: 19.25 | K12: 20 | L12: 19.75 | M12: 10 | N12: 5 | O12: =3/8 -> 0.375 | P12: =28/8 -> 3.5 | Q12: 0 | R12: =2/8 -> 0.25 | S12: 0.5 | T12: =26/8 -> 3.25 | U12: =18/8 -> 2.25 | V12: =24/8 -> 3 | W12: =8/8 -> 1
A13: ISLEM BEN SAID | B13: 0 | C13: 0 | D13: 0 | E13: 7 | F13: 2 | G13: 22 | H13: 13.5 | I13: 21 | J13: 18.875 | K13: 20.25 | L13: 18 | M13: 7.625 | N13: 1.5 | O13: =21/8 -> 2.625 | P13: =1/8 -> 0.125 | Q13: 1 | R13: 0 | S13: =11/8 -> 1.375 | T13: 0 | V13: =1/8 -> 0.125 | W13: =10/8 -> 1.25
A14: MOATEZ ZNAIDI | B14: 20 | C14: 17 | D14: 21 | E14: 20 | F14: 20 | G14: 22 | H14: 12.75 | I14: 20.625 | J14: 20.75 | K14: 20.5 | L14: 7.5 | M14: 11.5 | N14: 10.5 | O14: =34/8 -> 4.25 | P14: 0.5 | Q14: 0.5 | R14: 0 | S14: 0 | T14: 0
A15: NIDHAL MAROUANI | B15: 18 | C15: 19 | D15: 23 | E15: 20 | F15: 20 | G15: 22 | H15: 19 | I15: 17 | J15: 20 | K15: 19 | L15: 20 | M15: 11 | N15: 4 | O15: 0 | P15: 0 | Q15: 0 | R15: 0 | S15: 0 | T15: 0
A16: RAMI LOULOU | B16: 0 | C16: 0 | D16: 0 | E16: 2 | F16: 6 | G16: 12 | H16: 5.5 | I16: 13.5 | J16: 10.8125 | K16: 12.25 | L16: 14.5 | M16: 1.5 | N16: 0.625 | O16: 3 | P16: =26/8 -> 3.25 | Q16: =2/8 -> 0.25 | R16: =10/8 -> 1.25 | S16: 0.5 | W16: =1/8 -> 0.125
A17: WAFA BOUSETTA | B17: 11 | C17: 15 | D17: 15 | E17: 10 | F17: 15 | G17: 15 | H17: 15.5 | I17: 15.5 | J17: 12 | K17: 12 | L17: 17.5 | M17: 18.5 | N17: 5 | O17: 0 | P17: 0 | Q17: 0 | R17: 0
A18: AHMED AMINE AMIRI | B18: 19 | C18: 17 | D18: 16 | E18: 10 | F18: 17 | G18: 21 | H18: 17 | I18: 10.5 | J18: 17 | K18: 6 | L18: 5 | M18: 6 | N18: 5 | O18: 0 | P18: =12/8 -> 1.5 | Q18: 0 | R18: 0 | S18: 0 | T18: =32/8 -> 4 | U18: =24/8 -> 3 | V18: =44/8 -> 5.5 | X18: =68/8 -> 8.5
A19: WAFA CHAABENI | B19: 14 | C19: 14 | D19: 18 | E19: 15 | F19: 16 | G19: 0 | H19: 0 | I19: 7 | J19: 1 | K19: 11 | L19: 0 | M19: 2 | N19: 0
A20: FARAH BOUAKLINE | B20: 0 | C20: 0 | D20: 0 | E20: 8 | F20: 9 | G20: 0 | H20: 0 | I20: 0 | J20: 0 | K20: 0 | L20: 0 | M20: 0 | N20: 0 | O20: 0 | P20: 0 | Q20: 0 | R20: 0 | S20: 0 | T20: 0
A21: Syrine Dridi | B21: 0 | C21: 0 | D21: 25 | E21: 20 | F21: 20 | G21: 10 | H21: 0 | I21: 17.75 | J21: 20 | K21: 19 | L21: 20 | M21: 4.75 | N21: 0 | O21: 0 | P21: 0 | Q21: 0 | R21: 0 | S21: 0 | T21: =4/8 -> 0.5
A22: Slim AMIRI | B22: 0 | C22: 0 | D22: 0 | E22: 0 | F22: 0 | G22: 13 | H22: 0 | I22: 0 | J22: 0 | K22: 0 | L22: 0 | M22: 0 | N22: 0 | O22: 0 | P22: 0 | Q22: 0 | R22: 0 | S22: 0 | T22: 0
A23: Makram MAHFOUDH | B23: 0 | C23: 0 | D23: 0 | E23: 0 | F23: 0 | G23: 0 | H23: 0 | I23: 0 | J23: 0 | K23: 0 | L23: 0 | M23: 0 | N23: 0 | O23: 0 | P23: 0 | Q23: 0 | R23: 0 | S23: 0 | T23: 0
A24: Safouene BEN GALI | B24: 0 | C24: 0 | D24: 0 | E24: 0 | F24: 0 | G24: 0 | H24: 0 | I24: 0 | J24: 0 | K24: 3.6 | L24: 3.625 | M24: 3.75 | N24: 0 | X24: =5/8 -> 0.625
A25: Autres Frais | B25: 0 | C25: 0 | D25: 0 | E25: 0 | F25: 0 | G25: 0 | H25: 0 | I25: 0 | J25: 0 | K25: 0 | L25: 0 | M25: 0
A26: Total | B26: =SUM(B7:B24) -> 118 | C26: =SUM(C7:C24) -> 125 | D26: =SUM(D7:D24) -> 186 | E26: =SUM(E7:E24) -> 184 | F26: =SUM(F7:F24) -> 201 | G26: =SUM(G7:G24) -> 230.5 | H26: =SUM(H7:H24) -> 174.75 | I26: =SUM(I7:I24) -> 218.5625 | ... Z26: =SUM(Z7:Z24) -> 0
A27: Cumul | B27: =B26 -> 118 | C27: =C26+B27 -> 243 | D27: =D26+C27 -> 429 | E27: =E26+D27 -> 613 | F27: =F26+E27 -> 814 | G27: =G26+F27 -> 1044.5 | H27: =H26+G27 -> 1219.25 | I27: =I26+H27 -> 1437.8125 | J27: =J26+I27 -> 1625.5 | ... Z27: =Z26+Y27 -> 2199.1
A28: Coût Actuel
A29: Ahmed HAMADI | B29: 0 | C29: 0 | D29: 0 | E29: 0 | F29: =F7*TCC!$C$6 -> 2802.4242 | G29: =G7*TCC!$C$6 -> 2522.1818 | H29: =H7*TCC!$C$6 -> 2382.0606 | I29: =I7*TCC!$C$6 -> 2522.1818 | J29: =J7*TCC!$C$6 -> 1681.4545 | K29: =K7*TCC!$C$6 -> 0 | L29: =L7*TCC!$C$6 -> 0 | M29: =M7*TCC!$E$6 -> 0 | N29: =N7*TCC!$E$6 -> 0 | O29: =O7*TCC!$E$6 -> 0 | P29: =P7*TCC!$E6 -> 0 | Q29: =Q7*TCC!$E6 -> 0 | R29: =R7*TCC!$E6 -> 0 | S29: =S7*TCC!$E6 -> 0 | T29: =T7*TCC!$E6 -> 0 | U29: =U7*TCC!$E6 -> 0 | V29: =V7*TCC!$E6 -> 0 | W29: =W7*TCC!$E6 -> 0 | ... Z29: =Z7*TCC!$E6 -> 0
A30: ASMA BELGHUITH | B30: =B8*TCC!$C$7 -> 0 | C30: =C8*TCC!$C$7 -> 0 | D30: =D8*TCC!$C$7 -> 0 | E30: =E8*TCC!$C$7 -> 0 | F30: =F8*TCC!$C$7 -> 2302.5867 | G30: =G8*TCC!$C$7 -> 3198.0371 | H30: =H8*TCC!$C$7 -> 3325.9586 | I30: =I8*TCC!$C$7 -> 4013.5366 | ... L30: =L8*TCC!$C$7 -> 0 | M30: =M8*TCC!$E$6 -> 0 | N30: =N8*TCC!$E$6 -> 0 | O30: =O8*TCC!$E$6 -> 0 | P30: =P8*TCC!$E7 -> 0 | Q30: =Q8*TCC!$E7 -> 0 | R30: =R8*TCC!$E7 -> 0 | S30: =S8*TCC!$E7 -> 0 | T30: =T8*TCC!$E7 -> 0 | U30: =U8*TCC!$E7 -> 0 | V30: =V8*TCC!$E7 -> 0 | W30: =W8*TCC!$E7 -> 0 | ... Z30: =Z8*TCC!$E7 -> 0
A31: AYMEN ABID | B31: =B9*TCC!$C$8 -> 0 | C31: =C9*TCC!$C$8 -> 1394.2916 | D31: =D9*TCC!$C$8 -> 1394.2916 | E31: =E9*TCC!$C$8 -> 3718.1108 | F31: =F9*TCC!$C$8 -> 3020.965 | G31: =G9*TCC!$C$8 -> 3718.1108 | H31: =H9*TCC!$C$8 -> 4415.2566 | I31: =I9*TCC!$C$8 -> 3137.156 | J31: =J9*TCC!$C$8 -> 1742.8644 | K31: =K9*TCC!C8 -> 3485.7289 | L31: =L9*TCC!$C$8 -> 1278.1006 | M31: =M9*TCC!$E$6 -> 0 | N31: =N9*TCC!$E$6 -> 0 | O31: =O9*TCC!$E$6 -> 0 | P31: =P9*TCC!$E8 -> 144.4904 | Q31: =Q9*TCC!$E8 -> 0 | R31: =R9*TCC!$E8 -> 903.06501 | S31: =S9*TCC!$E8 -> 72.245201 | T31: =T9*TCC!$E8 -> 0 | U31: =U9*TCC!$E8 -> 0 | V31: =V9*TCC!$E8 -> 0 | W31: =W9*TCC!$E8 -> 0 | ... Z31: =Z9*TCC!$E8 -> 0
A32: DORSAF BABAY | B32: =B10*TCC!$C$9 -> 0 | C32: =C10*TCC!$C$9 -> 0 | D32: =D10*TCC!$C$9 -> 0 | E32: =E10*TCC!$C$9 -> 0 | F32: =F10*TCC!$C$9 -> 0 | G32: =G10*TCC!$C$9 -> 6673.8358 | H32: =H10*TCC!$C$9 -> 6067.1234 | I32: =I10*TCC!$C$9 -> 6067.1234 | J32: =J10*TCC!$C$9 -> 8418.1337 | K32: =K10*TCC!C9 -> 6067.1234 | L32: =L10*TCC!$C$9 -> 11527.534 | M32: =M10*TCC!$E$6 -> 1387.2 | N32: =N10*TCC!$E$6 -> 924.8 | O32: =O10*TCC!$E$6 -> 0 | P32: =P10*TCC!$E9 -> 0 | Q32: =Q10*TCC!$E9 -> 0 | R32: =R10*TCC!$E9 -> 0 | S32: =S10*TCC!$E9 -> 0 | T32: =T10*TCC!$E9 -> 0 | U32: =U10*TCC!$E9 -> 0 | V32: =V10*TCC!$E9 -> 0 | W32: =W10*TCC!$E9 -> 0 | ... Z32: =Z10*TCC!$E9 -> 0
A33: FATEN ZNAIDI | B33: =B11*TCC!$C$10 -> 8728.2898 | C33: =C11*TCC!$C$10 -> 9213.1947 | D33: =D11*TCC!$C$10 -> 9698.0997 | E33: =E11*TCC!$C$10 -> 8728.2898 | F33: =F11*TCC!$C$10 -> 7273.5748 | G33: =G11*TCC!$C$10 -> 6788.6698 | H33: =H11*TCC!$C$10 -> 7152.3485 | I33: =I11*TCC!$C$10 -> 8728.2898 | J33: =J11*TCC!$C$10 -> 7091.7354 | K33: =K11*TCC!C10 -> 9273.8079 | L33: =L11*TCC!$C$10 -> 8607.0635 | M33: =M11*TCC!$E$6 -> 2466.1333 | N33: =N11*TCC!$E$6 -> 1753.2667 | O33: =O11*TCC!$E$6 -> 693.6 | P33: =P11*TCC!$E10 -> 75.665228 | Q33: =Q11*TCC!$E10 -> 0 | R33: =R11*TCC!$E10 -> 0 | S33: =S11*TCC!$E10 -> 0 | T33: =T11*TCC!$E10 -> 151.33046 | U33: =U11*TCC!$E10 -> 0 | V33: =V11*TCC!$E10 -> 0 | W33: =W11*TCC!$E10 -> 0 | ... Z33: =Z11*TCC!$E10 -> 0
A34: HASSEN BEN HMIDA | B34: =B12*TCC!$C$11 -> 7110.7894 | C34: =C12*TCC!$C$11 -> 7110.7894 | D34: =D12*TCC!$C$11 -> 8690.9648 | E34: =E12*TCC!$C$11 -> 7110.7894 | F34: =F12*TCC!$C$11 -> 7505.8332 | G34: =G12*TCC!$C$11 -> 8690.9648 | H34: =H12*TCC!$C$11 -> 7012.0284 | I34: =I12*TCC!$C$11 -> 8098.399 | J34: =J12*TCC!$C$11 -> 7604.5942 | K34: =K12*TCC!C11 -> 7900.8771 | L34: =L12*TCC!$C$11 -> 7802.1161 | M34: =M12*TCC!$E$6 -> 1541.3333 | N34: =N12*TCC!$E$6 -> 770.66667 | O34: =O12*TCC!$E$6 -> 57.8 | P34: =P12*TCC!$E11 -> 1632.533 | Q34: =Q12*TCC!$E11 -> 0 | R34: =R12*TCC!$E11 -> 116.6095 | S34: =S12*TCC!$E11 -> 233.219 | T34: =T12*TCC!$E11 -> 1515.9235 | U34: =U12*TCC!$E11 -> 1049.4855 | V34: =V12*TCC!$E11 -> 1399.314 | W34: =W12*TCC!$E11 -> 466.43801 | ... Z34: =Z12*TCC!$E11 -> 0
A35: ISLEM BEN SAID | B35: =B13*TCC!$C$12 -> 0 | C35: =C13*TCC!$C$12 -> 0 | D35: =D13*TCC!$C$12 -> 0 | E35: =E13*TCC!$C$12 -> 1081.8182 | F35: =F13*TCC!$C$12 -> 309.09091 | G35: =G13*TCC!$C$12 -> 3400 | H35: =H13*TCC!$C$12 -> 2086.3636 | I35: =I13*TCC!$C$12 -> 3245.4545 | J35: =J13*TCC!$C$12 -> 2917.0455 | K35: =K13*TCC!C12 -> 3129.5455 | L35: =L13*TCC!$C$12 -> 2781.8182 | M35: =M13*TCC!$E$6 -> 1175.2667 | N35: =N13*TCC!$E$6 -> 231.2 | O35: =O13*TCC!$E$6 -> 404.6 | P35: =P13*TCC!$E12 -> 40.100313 | Q35: =Q13*TCC!$E12 -> 320.8025 | R35: =R13*TCC!$E12 -> 0 | S35: =S13*TCC!$E12 -> 441.10344 | T35: =T13*TCC!$E12 -> 0 | U35: =U13*TCC!$E12 -> 0 | V35: =V13*TCC!$E12 -> 40.100313 | W35: =W13*TCC!$E12 -> 401.00313 | ... Z35: =Z13*TCC!$E12 -> 0
A36: MOATEZ ZNAIDI | B36: =B14*TCC!$C$13 -> 2928.6364 | C36: =C14*TCC!$C$13 -> 2489.3409 | D36: =D14*TCC!$C$13 -> 3075.0682 | E36: =E14*TCC!$C$13 -> 2928.6364 | F36: =F14*TCC!$C$13 -> 2928.6364 | G36: =G14*TCC!$C$13 -> 3221.5 | H36: =H14*TCC!$C$13 -> 1867.0057 | I36: =I14*TCC!$C$13 -> 3020.1562 | J36: =J14*TCC!$C$13 -> 3038.4602 | K36: =K14*TCC!C13 -> 3001.8523 | L36: =L14*TCC!$C$13 -> 1098.2386 | M36: =M14*TCC!$E$6 -> 1772.5333 | N36: =N14*TCC!$E$6 -> 1618.4 | O36: =O14*TCC!$E$6 -> 655.06667 | P36: =P14*TCC!$E13 -> 148.76115 | Q36: =Q14*TCC!$E13 -> 148.76115 | R36: =R14*TCC!$E13 -> 0 | S36: =S14*TCC!$E13 -> 0 | T36: =T14*TCC!$E13 -> 0 | U36: =U14*TCC!$E13 -> 0 | V36: =V14*TCC!$E13 -> 0 | W36: =W14*TCC!$E13 -> 0 | ... Z36: =Z14*TCC!$E13 -> 0
A37: NIDHAL MAROUANI | B37: =B15*TCC!$C$14 -> 4128.303 | C37: =C15*TCC!$C$14 -> 4357.6532 | D37: =D15*TCC!$C$14 -> 5275.0539 | E37: =E15*TCC!$C$14 -> 4587.0034 | F37: =F15*TCC!$C$14 -> 4587.0034 | G37: =G15*TCC!$C$14 -> 5045.7037 | H37: =H15*TCC!$C$14 -> 4357.6532 | I37: =I15*TCC!$C$14 -> 3898.9529 | J37: =J15*TCC!$C$14 -> 4587.0034 | K37: =K15*TCC!C14 -> 4357.6532 | L37: =L15*TCC!$C$14 -> 4587.0034 | M37: =M15*TCC!$E$6 -> 1695.4667 | N37: =N15*TCC!$E$6 -> 616.53333 | O37: =O15*TCC!$E$6 -> 0 | P37: =P15*TCC!$E14 -> 0 | Q37: =Q15*TCC!$E14 -> 0 | R37: =R15*TCC!$E14 -> 0 | S37: =S15*TCC!$E14 -> 0 | T37: =T15*TCC!$E14 -> 0 | U37: =U15*TCC!$E14 -> 0 | V37: =V15*TCC!$E14 -> 0 | W37: =W15*TCC!$E14 -> 0 | ... Z37: =Z15*TCC!$E14 -> 0
A38: RAMI LOULOU | B38: =B16*TCC!$C$13 -> 0 | C38: =C16*TCC!$C$13 -> 0 | D38: =D16*TCC!$C$13 -> 0 | E38: =E16*TCC!$C$13 -> 292.86364 | F38: =F16*TCC!$C$13 -> 878.59091 | G38: =G16*TCC!$C$15 -> 11628.808 | H38: =H16*TCC!$C$15 -> 5329.8705 | I38: =I16*TCC!$C$15 -> 13082.409 | J38: =J16*TCC!$C$15 -> 10478.041 | K38: =K16*TCC!C15 -> 11871.075 | L38: =L16*TCC!$C$15 -> 14051.477 | M38: =M16*TCC!$E$6 -> 231.2 | N38: =N16*TCC!$E$6 -> 96.333333 | O38: =O16*TCC!$E$6 -> 462.4 | P38: =P16*TCC!$E15 -> 3114.8975 | Q38: =Q16*TCC!$E15 -> 239.6075 | R38: =R16*TCC!$E15 -> 1198.0375 | S38: =S16*TCC!$E15 -> 479.215 | T38: =T16*TCC!$E15 -> 0 | U38: =U16*TCC!$E15 -> 0 | V38: =V16*TCC!$E15 -> 0 | W38: =W16*TCC!$E15 -> 119.80375 | ... Z38: =Z16*TCC!$E15 -> 0
A39: WAFA BOUSETTA | B39: =B17*TCC!$C$13 -> 1610.75 | C39: =C17*TCC!$C$13 -> 2196.4773 | D39: =D17*TCC!$C$13 -> 2196.4773 | E39: =E17*TCC!$C$13 -> 1464.3182 | F39: =F17*TCC!$C$13 -> 2196.4773 | G39: =G17*TCC!$C$16 -> 2391.8189 | H39: =H17*TCC!$C$16 -> 2471.5462 | I39: =I17*TCC!$C$16 -> 2471.5462 | J39: =J17*TCC!$C$16 -> 1913.4551 | K39: =K17*TCC!C16 -> 1913.4551 | L39: =L17*TCC!$C$16 -> 2790.4553 | M39: =M17*TCC!$E$6 -> 2851.4667 | N39: =N17*TCC!$E$6 -> 770.66667 | O39: =O17*TCC!$E$6 -> 0 | P39: =P17*TCC!$E16 -> 0 | Q39: =Q17*TCC!$E16 -> 0 | R39: =R17*TCC!$E16 -> 0 | S39: =S17*TCC!$E16 -> 0 | T39: =T17*TCC!$E16 -> 0 | U39: =U17*TCC!$E16 -> 0 | V39: =V17*TCC!$E16 -> 0 | W39: =W17*TCC!$E16 -> 0 | ... Z39: =Z17*TCC!$E16 -> 0
A40: AHMED AMINE AMIRI | B40: =B18*TCC!$C$13 -> 2782.2045 | C40: =C18*TCC!$C$13 -> 2489.3409 | D40: =D18*TCC!$C$13 -> 2342.9091 | E40: =E18*TCC!$C$13 -> 1464.3182 | F40: =F18*TCC!$C$13 -> 2489.3409 | G40: =G18*TCC!$C$17 -> 15035.416 | H40: =H18*TCC!$C$17 -> 12171.527 | I40: =I18*TCC!$C$17 -> 7517.7079 | J40: =J18*TCC!$C$17 -> 12171.527 | K40: =K18*TCC!C17 -> 4295.8331 | L40: =L18*TCC!$C$17 -> 3579.8609 | M40: =M18*TCC!$E$6 -> 924.8 | N40: =N18*TCC!$E$6 -> 770.66667 | O40: =O18*TCC!$E$6 -> 0 | P40: =P18*TCC!$E17 -> 1297.6633 | Q40: =Q18*TCC!$E17 -> 0 | R40: =R18*TCC!$E17 -> 0 | S40: =S18*TCC!$E17 -> 0 | T40: =T18*TCC!$E17 -> 3460.4353 | U40: =U18*TCC!$E17 -> 2595.3265 | V40: =V18*TCC!$E17 -> 4758.0986 | W40: =W18*TCC!$E17 -> 0 | ... Z40: =Z18*TCC!$E17 -> 0
A41: WAFA CHAABENI | B41: =B19*TCC!$C$18 -> 2501.9494 | C41: =C19*TCC!$C$13 -> 2050.0455 | D41: =D19*TCC!$C$13 -> 2635.7727 | E41: =E19*TCC!$C$13 -> 2196.4773 | F41: =F19*TCC!$C$13 -> 2342.9091 | G41: =G19*TCC!$C$18 -> 0 | H41: =H19*TCC!$C$18 -> 0 | I41: =I19*TCC!$C$18 -> 1250.9747 | J41: =J19*TCC!$C$18 -> 178.71067 | K41: =K19*TCC!C18 -> 1965.8174 | L41: =L19*TCC!$C$18 -> 0 | M41: =M19*TCC!$E$6 -> 308.26667 | N41: =N19*TCC!$E$6 -> 0 | O41: =O19*TCC!$E$6 -> 0 | P41: =P19*TCC!$E18 -> 0 | Q41: =Q19*TCC!$E18 -> 0 | R41: =R19*TCC!$E18 -> 0 | S41: =S19*TCC!$E18 -> 0 | T41: =T19*TCC!$E18 -> 0 | U41: =U19*TCC!$E18 -> 0 | V41: =V19*TCC!$E18 -> 0 | W41: =W19*TCC!$E18 -> 0 | ... Z41: =Z19*TCC!$E18 -> 0
A42: FARAH BOUAKLINE | B42: =B20*TCC!$C$19 -> 0 | C42: =C20*TCC!$C$13 -> 0 | D42: =D20*TCC!$C$13 -> 0 | E42: =E20*TCC!$C$13 -> 1171.4545 | F42: =F20*TCC!$C$13 -> 1317.8864 | G42: =G20*TCC!$C$19 -> 0 | H42: =H20*TCC!$C$19 -> 0 | I42: =I20*TCC!$C$19 -> 0 | J42: =J20*TCC!$C$19 -> 0 | K42: =K20*TCC!C19 -> 0 | L42: =L20*TCC!$C$19 -> 0 | M42: =M20*TCC!$E$6 -> 0 | N42: =N20*TCC!$E$6 -> 0 | O42: =O20*TCC!$E$6 -> 0 | P42: =P20*TCC!$E19 -> 0 | Q42: =Q20*TCC!$E19 -> 0 | R42: =R20*TCC!$E19 -> 0 | S42: =S20*TCC!$E19 -> 0 | T42: =T20*TCC!$E19 -> 0 | U42: =U20*TCC!$E19 -> 0 | V42: =V20*TCC!$E19 -> 0 | W42: =W20*TCC!$E19 -> 0 | ... Z42: =Z20*TCC!$E19 -> 0
A43: Syrine Dridi | B43: =B21*TCC!$C$20 -> 0 | C43: =C21*TCC!$C$13 -> 0 | D43: =D21*TCC!$C$13 -> 3660.7955 | E43: =E21*TCC!$C$13 -> 2928.6364 | F43: =F21*TCC!$C$13 -> 2928.6364 | G43: =G21*TCC!$C$20 -> 1422.4158 | H43: =H21*TCC!$C$20 -> 0 | I43: =I21*TCC!$C$20 -> 2524.788 | J43: =J21*TCC!$C$20 -> 2844.8315 | K43: =K21*TCC!C20 -> 2702.5899 | L43: =L21*TCC!$C$20 -> 2844.8315 | M43: =M21*TCC!$E$6 -> 732.13333 | N43: =N21*TCC!$E$6 -> 0 | O43: =O21*TCC!$E$6 -> 0 | P43: =P21*TCC!$E20 -> 0 | Q43: =Q21*TCC!$E20 -> 0 | R43: =R21*TCC!$E20 -> 0 | S43: =S21*TCC!$E20 -> 0 | T43: =T21*TCC!$E20 -> 85.805375 | U43: =U21*TCC!$E20 -> 0 | V43: =V21*TCC!$E20 -> 0 | W43: =W21*TCC!$E20 -> 0 | ... Z43: =Z21*TCC!$E20 -> 0
A44: Slim AMIRI | B44: =B22*TCC!$C$21 -> 0 | C44: =C22*TCC!$C$13 -> 0 | D44: =D22*TCC!$C$13 -> 0 | E44: =E22*TCC!$C$13 -> 0 | F44: =F22*TCC!$C$13 -> 0 | G44: =G22*TCC!$C$21 -> 1938.7727 | H44: =H22*TCC!$C$21 -> 0 | I44: =I22*TCC!$C$21 -> 0 | J44: =J22*TCC!$C$21 -> 0 | K44: =K22*TCC!$C$21 -> 0 | L44: =L22*TCC!$C$21 -> 0 | M44: =M22*TCC!$E$6 -> 0 | N44: =N22*TCC!$E$6 -> 0 | O44: =O22*TCC!$E$6 -> 0 | P44: =P22*TCC!$E21 -> 0 | Q44: =Q22*TCC!$E21 -> 0 | R44: =R22*TCC!$E21 -> 0 | S44: =S22*TCC!$E21 -> 0 | T44: =T22*TCC!$E21 -> 0 | U44: =U22*TCC!$E21 -> 0 | V44: =V22*TCC!$E21 -> 0 | W44: =W22*TCC!$E21 -> 0 | ... Z44: =Z22*TCC!$E21 -> 0
A45: Makram MAHFOUDH | B45: =B23*TCC!$C$22 -> 0 | C45: =C23*TCC!$C$13 -> 0 | D45: =D23*TCC!$C$13 -> 0 | E45: =E23*TCC!$C$13 -> 0 | F45: =F23*TCC!$C$13 -> 0 | G45: =G23*TCC!$C$22 -> 0 | H45: =H23*TCC!$C$22 -> 0 | I45: =I23*TCC!$C$22 -> 0 | J45: =J23*TCC!$C$22 -> 0 | K45: =K23*TCC!$C$22 -> 0 | L45: =L23*TCC!$C$20 -> 0 | M45: =M23*TCC!$E$6 -> 0 | N45: =N23*TCC!$E$6 -> 0 | O45: =O23*TCC!$E$6 -> 0 | P45: =P23*TCC!$E22 -> 0 | Q45: =Q23*TCC!$E22 -> 0 | R45: =R23*TCC!$E22 -> 0 | S45: =S23*TCC!$E22 -> 0 | T45: =T23*TCC!$E22 -> 0 | U45: =U23*TCC!$E22 -> 0 | V45: =V23*TCC!$E22 -> 0 | W45: =W23*TCC!$E22 -> 0 | ... Z45: =Z23*TCC!$E22 -> 0
A46: Safouene BEN GALI | B46: =B15*TCC!$C$23 -> 5252.5936 | C46: =C15*TCC!$C$14 -> 4357.6532 | D46: =D15*TCC!$C$14 -> 5275.0539 | E46: =E15*TCC!$C$14 -> 4587.0034 | F46: =F15*TCC!$C$14 -> 4587.0034 | G46: =G24*TCC!$C$23 -> 0 | H46: =H24*TCC!$C$23 -> 0 | I46: =I24*TCC!$C$23 -> 0 | J46: =J24*TCC!$C$23 -> 0 | K46: =K24*TCC!C23 -> 1050.5187 | L46: =L24*TCC!$C$23 -> 1057.814 | M46: =M24*TCC!$E$6 -> 578 | N46: =N24*TCC!$E$6 -> 0 | O46: =O24*TCC!$E$6 -> 0 | P46: =P24*TCC!$E23 -> 0 | Q46: =Q24*TCC!$E23 -> 0 | R46: =R24*TCC!$E23 -> 0 | S46: =S24*TCC!$E23 -> 0 | T46: =T24*TCC!$E23 -> 0 | U46: =U24*TCC!$E23 -> 0 | V46: =V24*TCC!$E23 -> 0 | W46: =W24*TCC!$E23 -> 0 | ... Z46: =Z24*TCC!$E23 -> 0
A47: Frais de mission (Perdiem) | M47: =Missions!O3+Missions!O4 -> 11408.536
A48: Frais de mission (Billet)
A49: Autres Frais
A50: Total | B50: =SUM(B29:B49) -> 35043.516 | C50: =SUM(C29:C49) -> 35658.787 | D50: =SUM(D29:D49) -> 44244.487 | E50: =SUM(E29:E49) -> 42259.719 | F50: =SUM(F29:F49) -> 47470.959 | G50: =SUM(G29:G49) -> 75676.235 | H50: =SUM(H29:H49) -> 58638.742 | I50: =SUM(I29:I49) -> 69578.676 | ... Z50: =SUM(Z29:Z49) -> 0
A51: Cumul | B51: =B50 -> 35043.516 | C51: =C50+B51 -> 70702.303 | D51: =D50+C51 -> 114946.79 | E51: =E50+D51 -> 157206.51 | F51: =F50+E51 -> 204677.47 | G51: =G50+F51 -> 280353.7 | H51: =H50+G51 -> 338992.45 | I51: =I50+H51 -> 408571.12 | J51: =J50+I51 -> 473238.98 | ... Z51: =Z50+Y51 -> 667507.88

Sheet Recap Facturation
A2: Dashboard | H2: Total contrat HT (DT) | I2: ='Fiche identification'!B26 -> 1269861.5 | K2: Total frais: | L2: =I2-I3 -> 98420.962
H3: Totah Rémunération (HT) | I3: 1171440.5 | K3: Consommé: | L3: =Missions!J20+Missions!J21+Missions!J22 -> #REF!
A4: Mois en cours | B4: =Dashboard!C22 -> 45997 | H4: Total contrat HT (FCFA) | I4: ='Fiche identification'!B22 -> 248992444 | K4: Reste à consommer: | L4: =L2-L3 -> #REF!
B6: N° échéance | C6: Description | D6: % | E6: Devise | F6: Montant | G6: Date initiale | H6: Montant en TND | I6: Reste à facturer en TND | J6: Cumul facturation | K6: Cumul facturation % | L6: Reste à facturer % | M6: Date prévisionnelle | N6: Date réelle | O6: Statut | P6: Réglé (si facturé) O/N | Q6: Montant payé (Si réglé) | R6: Cumul payé | S6: Commentaires
A7: 45358 | B7: 1 | C7: Facture Sprint 1 | D7: 0.1 | E7: FCFA | F7: 22280339 | G7: =DATE(2024,3,6)+10 -> 45367 | H7: =F7*#REF! -> #REF! | I7: =$I$2-H7 -> #REF! | J7: =H7 -> #REF! | K7: =J7/$I$2 -> #REF! | L7: =100%-K7 -> #REF! | M7: =DATE(2024,3,6)+10 -> 45367 | N7: 45364 | O7: Facturé | P7: Oui | Q7: =22280339/#REF! -> #REF! | R7: =Q7 -> #REF! | S7: Facture n°24-02
A8: 45450 | B8: 2 | C8: Facture Sprint 2+3+4 | D8: 0.16 | E8: FCFA | F8: 35767792 | G8: =DATE(2024,6,6)+10 -> 45459 | H8: =F8*#REF! -> #REF! | I8: =I7-H8 -> #REF! | J8: =H7+H8 -> #REF! | K8: =J8/$I$2 -> #REF! | L8: =100%-K8 -> #REF! | M8: =DATE(2024,6,6)+10 -> 45459 | N8: 45496 | O8: Facturé | P8: Oui | Q8: 54655 | R8: =R7+Q8 -> #REF! | S8: Facture n°24-07
A9: 45511 | B9: 3 | C9: Facture Sprint 5+6 | D9: 0.16 | E9: FCFA | F9: 35791642 | G9: =DATE(2024,8,6)+10 -> 45520 | H9: =F9*#REF! -> #REF! | I9: =I8-H9 -> #REF! | J9: =H7+H8+H9 -> #REF! | K9: =J9/$I$2 -> #REF! | L9: =100%-K9 -> #REF! | M9: =DATE(2024,9,20)+10 -> 45565 | N9: 30/9/2024 | O9: Facturé | P9: Oui | Q9: 54346 | R9: =R8+Q9 -> #REF! | S9: Facture n°24-08
A10: 45572 | B10: 4 | C10: Facture Sprint 7+8 | D10: 0.16 | E10: FCFA | F10: 35791642 | G10: =DATE(2024,10,6)+10 -> 45581 | H10: =F10*#REF! -> #REF! | I10: =I9-H10 -> #REF! | J10: =H7+H8+H9+H10 -> #REF! | K10: =J10/$I$2 -> #REF! | L10: =100%-K10 -> #REF! | M10: =DATE(2024,10,25) -> 45590 | N10: 45593 | O10: Facturé | P10: Oui | Q10: 54286 | R10: =R9+Q10 -> #REF! | S10: Facture n°24-09
A11: 45633 | B11: 5 | C11: Facture Sprint 9+10 | D11: 0.16 | E11: FCFA | F11: 35791642 | G11: =DATE(2024,12,6)+10 -> 45642 | H11: =F11*#REF! -> #REF! | I11: =I10-H11 -> #REF! | J11: =SUM(H7:H11) -> #REF! | K11: =J11/$I$2 -> #REF! | L11: =100%-K11 -> #REF! | M11: 45657 | N11: 45657 | O11: Facturé | P11: Non | R11: =R10+Q11 -> #REF! | S11: Facture n°24-10
A12: 45695 | B12: 6 | C12: Facture Sprint 11+12 | D12: 0.16 | E12: FCFA | F12: 42692650 | G12: =DATE(2025,2,6)+10 -> 45704 | H12: =F12*#REF! -> #REF! | I12: =I11-H12 -> #REF! | J12: =SUM(H7:H12) -> #REF! | K12: =J12/$I$2 -> #REF! | L12: =100%-K12 -> #REF! | M12: 45704 | N12: 45744 | O12: Facturé | P12: Non | R12: =R11+Q12 -> #REF! | S12: Facture n°2025-05
A13: 45876 | B13: 7 | C13: MNT 18 premiers mois | D13: 0.05 | E13: FCFA | F13: 11223645 | G13: =DATE(2025,8,6)+10 -> 45885 | H13: =F13*#REF! -> #REF! | I13: =I12-H13 -> #REF! | J13: =SUM(H7:H13) -> #REF! | K13: =J13/$I$2 -> #REF! | L13: =100%-K13 -> #REF! | M13: =DATE(2025,8,6)+10 -> 45885 | N13: 45898 | O13: Facturé | P13: Non | R13: =R12+Q13 -> #REF! | S13: Facture n°2025-17
A14: 46060 | B14: 8 | C14: MNT 6 derniers mois | D14: 0.05 | E14: FCFA | G14: =DATE(2026,2,6)+10 -> 46069 | H14: =F14*#REF! -> #REF! | I14: =I13-H14 -> #REF! | J14: =SUM(H7:H14) -> #REF! | K14: =J14/$I$2 -> #REF! | L14: =100%-K14 -> #REF! | M14: =DATE(2026,2,6)+10 -> 46069 | R14: =R13+Q14 -> #REF!
F16: =D14*I3 -> 58572.025

Sheet S. Contractuelle
A2: Mois en cours | C2: Dashboard
G3: Période de développement | N3: Période de garantie
A4: Statut contractuel et financier | B4: 45323 | C4: 45352 | D4: 45383 | E4: 45413 | F4: 45444 | G4: 45474 | H4: 45505 | I4: 45536 | J4: 45566 | K4: 45597 | L4: 45627 | M4: 45658 | N4: 45689 | O4: 45717 | P4: 45748 | Q4: 45778 | R4: 45809 | S4: 45839 | T4: 45870 | U4: 45901 | V4: 45931 | W4: 45962 | X4: 45992 | Y4: 46023
A5: Devise Projet | B5: FCFA | C5: =$B$5 -> FCFA | D5: =$B$5 -> FCFA | E5: =$B$5 -> FCFA | F5: =$B$5 -> FCFA | G5: =$B$5 -> FCFA | H5: =$B$5 -> FCFA | I5: =$B$5 -> FCFA | J5: =$B$5 -> FCFA | ... Y5: =$B$5 -> FCFA
A6: Budget initial TO (incluant licences & soutraitances) | B6: 248992444 | C6: =$B$6 -> 248992444 | D6: =$B$6 -> 248992444 | E6: =$B$6 -> 248992444 | F6: =$B$6 -> 248992444 | G6: =$B$6 -> 248992444 | H6: =$B$6 -> 248992444 | I6: =$B$6 -> 248992444 | J6: =$B$6 -> 248992444 | ... Y6: =$B$6 -> 248992444
A7: Budget Licences & soutraitance (Initial) | B7: 0 | C7: =$B$7 -> 0 | D7: =$B$7 -> 0 | E7: =$B$7 -> 0 | F7: =$B$7 -> 0 | G7: =$B$7 -> 0 | H7: =$B$7 -> 0 | I7: =$B$7 -> 0 | J7: =$B$7 -> 0 | ... Y7: =$B$7 -> 0
A8: Avenant (O/N) | B8: Non | C8: =$B$8 -> Non | D8: =$B$8 -> Non | E8: =$B$8 -> Non | F8: =$B$8 -> Non | G8: =$B$8 -> Non | H8: =$B$8 -> Non | I8: =$B$8 -> Non | J8: =$B$8 -> Non | ... Y8: =$B$8 -> Non
A9: Montant Avenant | B9: 0 | C9: =$B$9 -> 0 | D9: =$B$9 -> 0 | E9: =$B$9 -> 0 | F9: =$B$9 -> 0 | G9: =$B$9 -> 0 | H9: =$B$9 -> 0 | I9: =$B$9 -> 0 | J9: =$B$9 -> 0 | ... Y9: =$B$9 -> 0
A10: Total avenants | B10: 0 | C10: =$B$10 -> 0 | D10: =$B$10 -> 0 | E10: =$B$10 -> 0 | F10: =$B$10 -> 0 | G10: =$B$10 -> 0 | H10: =$B$10 -> 0 | I10: =$B$10 -> 0 | J10: =$B$10 -> 0 | ... Y10: =$B$10 -> 0
A11: Budget total (avenants inclus) | B11: ='Fiche identification'!B22 -> 248992444 | C11: =$B$11 -> 248992444 | D11: =$B$11 -> 248992444 | E11: =$B$11 -> 248992444 | F11: =$B$11 -> 248992444 | G11: =$B$11 -> 248992444 | H11: =$B$11 -> 248992444 | I11: =$B$11 -> 248992444 | J11: =$B$11 -> 248992444 | ... Y11: =$B$11 -> 248992444
A12: Budget initial TO (incluant licences & soutraitances) en TND | B12: ='Fiche identification'!B23 -> 1269861.5 | C12: =$B$12 -> 1269861.5 | D12: =$B$12 -> 1269861.5 | E12: =$B$12 -> 1269861.5 | F12: =$B$12 -> 1269861.5 | G12: =$B$12 -> 1269861.5 | H12: =$B$12 -> 1269861.5 | I12: =$B$12 -> 1269861.5 | J12: =$B$12 -> 1269861.5 | ... P12: =$B$12 -> 1269861.5
A13: Budget Licences & soutraitance (Initial) en TND | B13: ='Fiche identification'!B18 -> 0 | C13: =$B$13 -> 0 | D13: =$B$13 -> 0 | E13: =$B$13 -> 0 | F13: =$B$13 -> 0 | G13: =$B$13 -> 0 | H13: =$B$13 -> 0 | I13: =$B$13 -> 0 | J13: =$B$13 -> 0 | ... P13: =$B$13 -> 0 | Q13: 0 | R13: 0 | S13: 0 | T13: 0 | U13: 0 | V13: 0 | W13: 0 | X13: 0 | Y13: 0
A14: Total avenants en TND | B14: 0 | C14: =$B$14 -> 0 | D14: =$B$14 -> 0 | E14: =$B$14 -> 0 | F14: =$B$14 -> 0 | G14: =$B$14 -> 0 | H14: =$B$14 -> 0 | I14: =$B$14 -> 0 | J14: =$B$14 -> 0 | ... Q14: =$B$14 -> 0 | R14: 0 | S14: 0 | T14: 0 | U14: 0 | V14: 0 | W14: 0 | X14: 0 | Y14: 0
A15: Budget total (avenants inclus) en TND | B15: 1269861.5 | C15: =B15+C14 -> 1269861.5 | D15: =C15+D14 -> 1269861.5 | E15: =D15+E14 -> 1269861.5 | F15: =E15+F14 -> 1269861.5 | G15: =F15+G14 -> 1269861.5 | H15: =G15+H14 -> 1269861.5 | I15: =H15+I14 -> 1269861.5 | J15: =I15+J14 -> 1269861.5 | ... M15: =L15+M14 -> 1269861.5 | N15: =$B$15 -> 1269861.5 | O15: =$B$15 -> 1269861.5 | P15: =$B$15 -> 1269861.5 | Q15: =$B$15 -> 1269861.5 | R15: =$B$15 -> 1269861.5 | S15: =$B$15 -> 1269861.5 | T15: =$B$15 -> 1269861.5
A16: PPR (Provision Pour Risques) en TND | B16: =B15*5% -> 63493.073 | C16: =C15*5% -> 63493.073 | D16: =D15*5% -> 63493.073 | E16: =E15*5% -> 63493.073 | F16: =F15*5% -> 63493.073 | G16: =G15*5% -> 63493.073 | H16: =H15*5% -> 63493.073 | I16: =I15*5% -> 63493.073 | ... Y16: =Y15*5% -> 0
A17: PPP(Provision Pour Pénalités) en TND | B17: 0 | C17: =$B$17 -> 0 | D17: =$B$17 -> 0 | E17: =$B$17 -> 0 | F17: =$B$17 -> 0 | G17: =$B$17 -> 0 | H17: =$B$17 -> 0 | I17: =$B$17 -> 0 | J17: =$B$17 -> 0 | ... Y17: =$B$17 -> 0
A18: Coût Total en TND (DI) | B18: 714333 | C18: =$B$18 -> 714333 | D18: =$B$18 -> 714333 | E18: =$B$18 -> 714333 | F18: =$B$18 -> 714333 | G18: =$B$18 -> 714333 | H18: =$B$18 -> 714333 | I18: =$B$18 -> 714333 | J18: =$B$18 -> 714333 | ... Y18: =$B$18 -> 714333
A19: Marge nette vendue % | B19: =B20/B15 -> 0.43747171 | C19: =C20/C15 -> 0.43747171 | D19: =D20/D15 -> 0.43747171 | E19: =E20/E15 -> 0.43747171 | F19: =F20/F15 -> 0.43747171 | G19: =G20/G15 -> 0.43747171 | H19: =H20/H15 -> 0.43747171 | I19: =I20/I15 -> 0.43747171 | ... Y19: =Y20/Y15 -> #DIV/0!
A20: Marge nette vendue en TND | B20: =B15-B18 -> 555528.46 | C20: =C15-C18 -> 555528.46 | D20: =D15-D18 -> 555528.46 | E20: =E15-E18 -> 555528.46 | F20: =F15-F18 -> 555528.46 | G20: =G15-G18 -> 555528.46 | H20: =H15-H18 -> 555528.46 | I20: =I15-I18 -> 555528.46 | ... Y20: =Y15-Y18 -> -714333
A21: Workload vendu avenants inclus en JH | B21: 1717 | C21: =$B$21 -> 1717 | D21: =$B$21 -> 1717 | E21: =$B$21 -> 1717 | F21: =$B$21 -> 1717 | G21: =$B$21 -> 1717 | H21: =$B$21 -> 1717 | I21: =$B$21 -> 1717 | J21: =$B$21 -> 1717 | ... Y21: =$B$21 -> 1717
A22: Workload initial en JH | B22: 1717 | C22: =$B$22 -> 1717 | D22: =$B$22 -> 1717 | E22: =$B$22 -> 1717 | F22: =$B$22 -> 1717 | G22: =$B$22 -> 1717 | H22: =$B$22 -> 1717 | I22: =$B$22 -> 1717 | J22: =$B$22 -> 1717 | ... Y22: =$B$22 -> 1717
A23: Workload avenants en JH | B23: 0 | C23: =$B$23 -> 0 | D23: =$B$23 -> 0 | E23: =$B$23 -> 0 | F23: =$B$23 -> 0 | G23: =$B$23 -> 0 | H23: =$B$23 -> 0 | I23: =$B$23 -> 0 | J23: =$B$23 -> 0 | ... Y23: =$B$23 -> 0
A24: Workload Garantie en JH | B24: 75 | C24: =$B$24 -> 75 | D24: =$B$24 -> 75 | E24: =$B$24 -> 75 | F24: =$B$24 -> 75 | G24: =$B$24 -> 75 | H24: =$B$24 -> 75 | I24: =$B$24 -> 75 | J24: =$B$24 -> 75 | ... Y24: =$B$24 -> 75
A25: Workload total en JH | B25: =SUM(B22:B24) -> 1792 | C25: =SUM(C22:C24) -> 1792 | D25: =SUM(D22:D24) -> 1792 | E25: =SUM(E22:E24) -> 1792 | F25: =SUM(F22:F24) -> 1792 | G25: =SUM(G22:G24) -> 1792 | H25: =SUM(H22:H24) -> 1792 | I25: =SUM(I22:I24) -> 1792 | ... Y25: =SUM(Y22:Y24) -> 1792
A26: Date Début | B26: 45323 | C26: 45323 | D26: 45323 | E26: 45323 | F26: 45323 | G26: 45323 | H26: 45323 | I26: 45323 | J26: 45323 | K26: 45323 | L26: 45323 | M26: 45323 | N26: 45323 | O26: 45689 | P26: 45689 | Q26: 45689 | R26: 45689 | S26: 45689 | T26: 45689 | U26: 45689 | V26: 45689 | W26: 45689 | X26: 45689 | Y26: 45689
A27: Date fin actualisée | B27: 46054 | C27: 46054 | D27: 46054 | E27: 46054 | F27: 46054 | G27: 46054 | H27: 46054 | I27: 46054 | J27: 46054 | K27: 46054 | L27: 46054 | M27: 46054 | N27: 46054 | O27: 46054 | P27: 46054 | Q27: 46054 | R27: 46054 | S27: 46054 | T27: 46054 | U27: 46054 | V27: 46054 | W27: 46054 | X27: 46054 | Y27: 46054
A28: Durée actualisée (j) | B28: 365 | C28: =$B$28 -> 365 | D28: =$B$28 -> 365 | E28: =$B$28 -> 365 | F28: =$B$28 -> 365 | G28: =$B$28 -> 365 | H28: =$B$28 -> 365 | I28: =$B$28 -> 365 | J28: =$B$28 -> 365 | ... Y28: =$B$28 -> 365
A29: Avancement délais | B29: =(B4-B26+30)/B28 -> 0.082191781 | C29: =(C4-C26+30)/C28 -> 0.16164384 | D29: =(D4-D26+30)/D28 -> 0.24657534 | E29: =(E4-E26+30)/E28 -> 0.32876712 | F29: =(F4-F26+30)/F28 -> 0.41369863 | G29: =(G4-G26+30)/G28 -> 0.49589041 | H29: =(H4-H26+30)/H28 -> 0.58082192 | I29: =(I4-I26+30)/I28 -> 0.66575342 | ... M29: =(M4-M26+30)/M28 -> 1

Sheet Situation actuelle
A2: Dashboard | C2: Total contrat HT (DT) | D2: ='Fiche identification'!B26 -> 1269861.5
C3: Total contrat HT (FCFA) | D3: ='Fiche identification'!B22 -> 248992444
A4: Mois en cours
B6: 45323 | C6: 45352 | D6: 45383 | E6: 45413 | F6: 45444 | G6: 45474 | H6: 45505 | I6: 45536 | J6: 45566 | K6: 45597 | L6: 45627 | M6: 45658 | N6: 45689 | O6: 45717 | P6: 45748 | Q6: 45778 | R6: 45809 | S6: 45839 | T6: 45870 | U6: 45901 | V6: 45931 | W6: 45962 | X6: 45992 | Y6: 46023 | Z6: 46054
A7: Phase actuelle | B7: Sprint 1 | C7: Sprint 2 | D7: Sprint 3 | E7: Sprint 4 | F7: Sprint 5 | G7: Sprint 6 | H7: Sprint 7 | I7: Sprint 8 | J7: Sprint 9 | K7: Sprint 10 | L7: Sprint 11 | M7: Sprint 12
A8: Earned Value % | B8: =2/12 -> 0.16666667 | C8: =3/12 -> 0.25 | D8: =4/12 -> 0.33333333 | E8: =4.5/12 -> 0.375 | F8: =5/12 -> 0.41666667 | G8: =6.5/12 -> 0.54166667 | H8: =7/12 -> 0.58333333 | I8: =8.5/12 -> 0.70833333 | J8: =9.2/12 -> 0.76666667 | K8: =10/12 -> 0.83333333
A9: Delivery % | B9: =1/12 -> 0.083333333 | C9: =2/12 -> 0.16666667 | D9: =3/12 -> 0.25 | E9: =4/12 -> 0.33333333 | F9: =5/12 -> 0.41666667 | G9: =6/12 -> 0.5 | H9: =7/12 -> 0.58333333 | I9: =8/12 -> 0.66666667 | J9: =9/12 -> 0.75 | K9: =9.5/12 -> 0.79166667
A10: Observations et faits marquants | B10: RAS | C10: RAS | D10: RAS | E10: RAS | F10: RAS | G10: RAS | H10: RAS | I10: RAS | J10: RAS | K10: RAS | L10: RAS | M10: RAS | N10: RAS | O10: RAS | P10: RAS | Q10: RAS | R10: RAS | S10: RAS | T10: RAS | U10: RAS | V10: RAS | W10: RAS | X10: RAS | Y10: RAS | Z10: RAS
A11: Charge totale consommée JH | B11: 118 | C11: 235 | D11: 430 | E11: 621 | F11: 828 | G11: 1059 | H11: ='Coût réel Actualisé'!H27 -> 1219.25 | I11: ='Coût réel Actualisé'!I27 -> 1437.8125 | J11: ='Coût réel Actualisé'!J27 -> 1625.5 | K11: ='Coût réel Actualisé'!K27 -> 1813.225
A12: RAF JH | B12: =1717-B11 -> 1599 | C12: =1717-C11 -> 1482 | D12: =1717-D11 -> 1287 | E12: =1717-E11 -> 1096 | F12: =1717-F11 -> 889 | G12: =1717-G11 -> 658 | H12: ='Coût Prévisionnel'!H24 -> 829 | I12: ='Coût Prévisionnel'!I24 -> 641 | J12: ='Coût Prévisionnel'!J24 -> 448 | K12: ='Coût Prévisionnel'!K24 -> 303 | L12: ='Coût Prévisionnel'!L24 -> 193 | M12: ='Coût Prévisionnel'!M24 -> 92 | N12: ='Coût Prévisionnel'!N24 -> 72 | O12: ='Coût Prévisionnel'!O24 -> 66 | ... Z12: ='Coût Prévisionnel'!Z24 -> 0
A13: Dérive JH | B13: =1717-B12-B11 -> 0 | C13: =1717-C12-C11 -> 0 | D13: =1717-D12-D11 -> 0 | E13: =1717-E12-E11 -> 0 | F13: =1717-F12-F11 -> 0 | G13: =1717-G12-G11 -> 0 | H13: =1717-H12-H11 -> -331.25 | I13: =1717-I12-I11 -> -361.8125 | ... Z13: =1717-Z12-Z11 -> 1717
A14: Cumul CA production TND | B14: =$D$2*B8 -> 211643.58 | C14: =$D$2*C8 -> 317465.37 | D14: =$D$2*D8 -> 423287.15 | E14: =$D$2*E8 -> 476198.05 | F14: =$D$2*F8 -> 529108.94 | G14: =$D$2*G8 -> 687841.63 | H14: =$D$2*H8 -> 740752.52 | I14: =$D$2*I8 -> 899485.2 | ... Z14: =$D$2*Z8 -> 0
A15: Total facturé TND | B15: =Avancement_Facturation!B15 -> 0 | C15: =Avancement_Facturation!C15 -> 126986.15 | D15: =Avancement_Facturation!D15 -> 126986.15 | E15: =Avancement_Facturation!E15 -> 126986.15 | F15: =Avancement_Facturation!F15 -> 330163.98 | G15: =Avancement_Facturation!G15 -> 330163.98 | H15: =Avancement_Facturation!H15 -> 533341.82 | I15: =Avancement_Facturation!I15 -> 533341.82 | ... U15: =Avancement_Facturation!U15 -> 1003190.6 | V15: =Avancement_Facturation!AH15 -> 0 | W15: =Avancement_Facturation!AI15 -> 0 | X15: =Avancement_Facturation!AJ15 -> 0 | Y15: =Avancement_Facturation!AK15 -> 0 | Z15: =Avancement_Facturation!AL15 -> 0
A16: FAE/Stock TND | B16: =B14-B15 -> 211643.58 | C16: =C14-C15 -> 190479.22 | D16: =D14-D15 -> 296301.01 | E16: =E14-E15 -> 349211.9 | F16: =F14-F15 -> 198944.96 | G16: =G14-G15 -> 357677.65 | H16: =H14-H15 -> 207410.71 | I16: =I14-I15 -> 366143.39 | ... Z16: =Z14-Z15 -> 0
A17: Coût actuel TND (cumul) | B17: ='Coût réel Actualisé'!B51 -> 35043.516 | C17: ='Coût réel Actualisé'!C51 -> 70702.303 | D17: ='Coût réel Actualisé'!D51 -> 114946.79 | E17: ='Coût réel Actualisé'!E51 -> 157206.51 | F17: ='Coût réel Actualisé'!F51 -> 204677.47 | G17: ='Coût réel Actualisé'!G51 -> 280353.7 | H17: ='Coût réel Actualisé'!H51 -> 338992.45 | I17: ='Coût réel Actualisé'!I51 -> 408571.12 | ... N17: ='Coût réel Actualisé'!N51 -> 630886.04 | O17: ='Coût réel Actualisé'!#REF! -> #REF! | P17: ='Coût réel Actualisé'!#REF! -> #REF! | Q17: ='Coût réel Actualisé'!#REF! -> #REF! | R17: ='Coût réel Actualisé'!O51 -> 633159.51 | S17: ='Coût réel Actualisé'!P51 -> 639613.62 | T17: ='Coût réel Actualisé'!Q51 -> 640322.79 | U17: ='Coût réel Actualisé'!R51 -> 642540.5 | V17: ='Coût réel Actualisé'!S51 -> 643766.28 | W17: ='Coût réel Actualisé'!T51 -> 648979.78 | X17: ='Coût réel Actualisé'!U51 -> 652624.59 | Y17: ='Coût réel Actualisé'!V51 -> 658822.1 | Z17: ='Coût réel Actualisé'!W51 -> 659809.35
A18: Marge % | B18: =B19/B14 -> 0.83442202 | C18: =C19/C14 -> 0.77729129 | D18: =D19/D14 -> 0.72844253 | E18: =E19/E14 -> 0.66987158 | F18: =F19/F14 -> 0.61316574 | G18: =G19/G14 -> 0.59241533 | H18: =H19/H14 -> 0.54236748 | I18: =I19/I14 -> 0.54577227 | ... Z18: =Z19/Z14 -> #DIV/0!
A19: Marge Net TND | B19: =B14-B17 -> 176600.06 | C19: =C14-C17 -> 246763.06 | D19: =D14-D17 -> 308340.37 | E19: =E14-E17 -> 318991.54 | F19: =F14-F17 -> 324431.48 | G19: =G14-G17 -> 407487.92 | H19: =H14-H17 -> 401760.08 | I19: =I14-I17 -> 490914.08 | ... Z19: =Z14-Z17 -> -659809.35
A22: Situation prévisionnelle à l'atterrissage (EAC) | B22: 45323 | C22: 45352 | D22: 45383 | E22: 45413 | F22: 45444 | G22: 45474 | H22: 45505 | I22: 45536 | J22: 45566 | K22: 45597 | L22: 45627 | M22: 45658 | N22: 45689 | O22: 45717 | P22: 45748 | Q22: 45778 | R22: 45809 | S22: 45839 | T22: 45870 | U22: 45901 | V22: 45931 | W22: 45962 | X22: 45992 | Y22: 46023 | Z22: 46054
A23: Coûts prévisionnels pour finaliser le projet TND | B23: =710000-B17 -> 674956.48 | C23: =710000-C17 -> 639297.7 | D23: =710000-D17 -> 595053.21 | E23: =710000-E17 -> 552793.49 | F23: =710000-F17 -> 505322.53 | G23: ='Coût Prévisionnel'!G43 -> #REF! | H23: ='Coût Prévisionnel'!H43 -> #REF! | I23: ='Coût Prévisionnel'!I43 -> #REF! | J23: ='Coût Prévisionnel'!J43 -> #REF! | K23: ='Coût Prévisionnel'!K43 -> #REF! | L23: ='Coût Prévisionnel'!L43 -> #REF! | M23: ='Coût Prévisionnel'!M43 -> #REF! | N23: ='Coût Prévisionnel'!N43 -> #REF! | ... W23: ='Coût Prévisionnel'!W43 -> #REF! | X23: ='Coût Prévisionnel'!X42 -> #REF! | Y23: ='Coût Prévisionnel'!Y42 -> #REF! | Z23: ='Coût Prévisionnel'!Z42 -> #REF!
A24: EAC Marge % | B24: =B25/'S. Contractuelle'!B15 -> 0.44088389 | C24: =C25/'S. Contractuelle'!C15 -> 0.44088389 | D24: =D25/'S. Contractuelle'!D15 -> 0.44088389 | E24: =E25/'S. Contractuelle'!E15 -> 0.44088389 | F24: =F25/'S. Contractuelle'!F15 -> 0.44088389 | G24: =G25/'S. Contractuelle'!G15 -> #REF! | H24: =H25/'S. Contractuelle'!H15 -> #REF! | I24: =I25/'S. Contractuelle'!I15 -> #REF! | J24: =J25/'S. Contractuelle'!B15 -> #REF! | K24: =K25/'S. Contractuelle'!C15 -> #REF! | L24: =L25/'S. Contractuelle'!D15 -> #REF! | M24: =M25/'S. Contractuelle'!E15 -> #REF! | N24: =N25/'S. Contractuelle'!F15 -> #REF! | O24: =O25/'S. Contractuelle'!G15 -> #REF! | P24: =P25/'S. Contractuelle'!H15 -> #REF! | Q24: =Q25/'S. Contractuelle'!I15 -> #REF! | ... Z24: =Z25/'S. Contractuelle'!R15 -> #REF!
A25: EAC Marge TND | B25: ='S. Contractuelle'!B15-(B17+B23) -> 559861.46 | C25: ='S. Contractuelle'!C15-(C17+C23) -> 559861.46 | D25: ='S. Contractuelle'!D15-(D17+D23) -> 559861.46 | E25: ='S. Contractuelle'!E15-(E17+E23) -> 559861.46 | F25: ='S. Contractuelle'!F15-(F17+F23) -> 559861.46 | G25: ='S. Contractuelle'!G15-(G17+G23) -> #REF! | H25: ='S. Contractuelle'!H15-(H17+H23) -> #REF! | I25: ='S. Contractuelle'!I15-(I17+I23) -> #REF! | J25: ='S. Contractuelle'!J15-(J17+J23) -> #REF! | K25: ='S. Contractuelle'!C15-(K17+K23) -> #REF! | L25: ='S. Contractuelle'!D15-(L17+L23) -> #REF! | M25: ='S. Contractuelle'!E15-(M17+M23) -> #REF! | N25: ='S. Contractuelle'!F15-(N17+N23) -> #REF! | O25: ='S. Contractuelle'!G15-(O17+O23) -> #REF! | P25: ='S. Contractuelle'!H15-(P17+P23) -> #REF! | Q25: ='S. Contractuelle'!I15-(Q17+Q23) -> #REF! | R25: ='S. Contractuelle'!J15-(R17+R23) -> #REF! | ... Z25: ='S. Contractuelle'!R15-(Z17+Z23) -> #REF!
A26: Date fin prévisionnelle (estimation chef du projet) | B26: 45693 | C26: 45693 | D26: 45693 | E26: 45693 | F26: 45693 | G26: 45693 | H26: 45693 | I26: 45693 | J26: 45693 | K26: 45693 | L26: 45693 | M26: 45693
A27: TND EAC ASP | I27: ='S. Contractuelle'!#REF!-(I18+I24) -> #REF!
A28: TND EAC ASP VAR | H28: 0.41151005 | I28: ='S. Contractuelle'!#REF!-(I19+I25) -> #REF!
A29: TND EAC ADW | H29: 511428 | I29: ='S. Contractuelle'!#REF!-(I20+I27) -> #REF!
A30: TND EAC ADW VAR | I30: ='S. Contractuelle'!#REF!-(I21+I28) -> #REF!

Sheet Parties Prenantes
A1: Staffing / Equipe projet
A2: Profils projets | B2: Collaborateurs | C2: Date de début | D2: Date de fin | E2: Taux de staffing %
A17: Client
A18: Identification | B18: Exigences | D18: Impact
A23: Partenaires
A24: Identification | B24: Exigences | D24: Impact
A28: Bailleur de fond
A29: Identification | B29: Exigences | D29: Impact

Sheet Livrables projet
C1: Dashboard
A2: Phase | B2: N° | C2: Désignation du livrable | D2: Date de livraison prévue | E2: Livré? | F2: Date de livraison | G2: Delivery (%) | H2: 45323 | I2: 45352 | J2: 45383 | K2: 45413 | L2: 45444 | M2: 45474 | N2: 45505 | O2: 45536 | P2: 45566 | Q2: 45597 | R2: 45627 | S2: 45658 | T2: 45689 | U2: 45717 | V2: 45748 | W2: 45778 | X2: 45809 | Y2: 45839 | Z2: 45870 | AA2: 45901 | AB2: 45931 | AC2: 45962 | AD2: 45992 | AE2: 46023 | AF2: 46054
A3: Sprint 1 | B3: 1 | C3: L10 Plan d’assurance qualité (PAQ) de l’étape 1 | D3: 45348 | E3: Oui | F3: 45348 | G3: 1 | H3: 1 | I3: 1 | J3: 1 | K3: 1 | L3: 1 | M3: 1 | N3: 1 | O3: 1 | P3: 1 | Q3: 1 | R3: 1 | S3: 1 | T3: 1 | U3: 1 | V3: 1 | W3: 1 | X3: 1 | Y3: 1 | Z3: 1 | AA3: 1 | AB3: 1 | AC3: 1 | AD3: 1 | AE3: 1 | AF3: 1
B4: 2 | C4: L11 Spécifications fonctionnelles détaillées de l’étape 1 | D4: 45348 | E4: Oui | F4: 45348 | G4: 1 | H4: 1 | I4: 1 | J4: 1 | K4: 1 | L4: 1 | M4: 1 | N4: 1 | O4: 1 | P4: 1 | Q4: 1 | R4: 1 | S4: 1 | T4: 1 | U4: 1 | V4: 1 | W4: 1 | X4: 1 | Y4: 1 | Z4: 1 | AA4: 1 | AB4: 1 | AC4: 1 | AD4: 1 | AE4: 1 | AF4: 1
B5: 3 | C5: L12 Spécifications techniques détaillées de l’étape 1 | D5: 45348 | E5: Oui | F5: 45348 | G5: 1 | H5: 1 | I5: 1 | J5: 1 | K5: 1 | L5: 1 | M5: 1 | N5: 1 | O5: 1 | P5: 1 | Q5: 1 | R5: 1 | S5: 1 | T5: 1 | U5: 1 | V5: 1 | W5: 1 | X5: 1 | Y5: 1 | Z5: 1 | AA5: 1 | AB5: 1 | AC5: 1 | AD5: 1 | AE5: 1 | AF5: 1
B6: 4 | C6: L13 Manuel d’utilisation version 1 | D6: 45357 | E6: Oui | F6: 45357 | G6: 1 | H6: 0 | I6: 1 | J6: 1 | K6: 1 | L6: 1 | M6: 1 | N6: 1 | O6: 1 | P6: 1 | Q6: 1 | R6: 1 | S6: 1 | T6: 1 | U6: 1 | V6: 1 | W6: 1 | X6: 1 | Y6: 1 | Z6: 1 | AA6: 1 | AB6: 1 | AC6: 1 | AD6: 1 | AE6: 1 | AF6: 1
B7: 5 | C7: L14 Manuel d’installation et d’administration version 1 | D7: 45357 | E7: Oui | F7: 45357 | G7: 1 | H7: 0 | I7: 1 | J7: 1 | K7: 1 | L7: 1 | M7: 1 | N7: 1 | O7: 1 | P7: 1 | Q7: 1 | R7: 1 | S7: 1 | T7: 1 | U7: 1 | V7: 1 | W7: 1 | X7: 1 | Y7: 1 | Z7: 1 | AA7: 1 | AB7: 1 | AC7: 1 | AD7: 1 | AE7: 1 | AF7: 1
B8: 6 | C8: L15 Version 1 du Système | D8: 45357 | E8: Oui | F8: 45357 | G8: 1 | H8: 0 | I8: 1 | J8: 1 | K8: 1 | L8: 1 | M8: 1 | N8: 1 | O8: 1 | P8: 1 | Q8: 1 | R8: 1 | S8: 1 | T8: 1 | U8: 1 | V8: 1 | W8: 1 | X8: 1 | Y8: 1 | Z8: 1 | AA8: 1 | AB8: 1 | AC8: 1 | AD8: 1 | AE8: 1 | AF8: 1
B9: 7 | C9: L16 SIG-I amélioré | D9: 45357 | E9: Oui | F9: 45357 | G9: 1 | H9: 0 | I9: 1 | J9: 1 | K9: 1 | L9: 1 | M9: 1 | N9: 1 | O9: 1 | P9: 1 | Q9: 1 | R9: 1 | S9: 1 | T9: 1 | U9: 1 | V9: 1 | W9: 1 | X9: 1 | Y9: 1 | Z9: 1 | AA9: 1 | AB9: 1 | AC9: 1 | AD9: 1 | AE9: 1 | AF9: 1
B10: 8 | C10: L17 Manuels de formation technique sur Angular et SpringBoot | D10: 45342 | E10: Oui | F10: 45342 | G10: 1 | H10: 1 | I10: 1 | J10: 1 | K10: 1 | L10: 1 | M10: 1 | N10: 1 | O10: 1 | P10: 1 | Q10: 1 | R10: 1 | S10: 1 | T10: 1 | U10: 1 | V10: 1 | W10: 1 | X10: 1 | Y10: 1 | Z10: 1 | AA10: 1 | AB10: 1 | AC10: 1 | AD10: 1 | AE10: 1 | AF10: 1
B11: 9 | C11: L18 Rapport de formation | D11: 45357 | E11: Oui | F11: 45357 | G11: 1 | H11: 0 | I11: 1 | J11: 1 | K11: 1 | L11: 1 | M11: 1 | N11: 1 | O11: 1 | P11: 1 | Q11: 1 | R11: 1 | S11: 1 | T11: 1 | U11: 1 | V11: 1 | W11: 1 | X11: 1 | Y11: 1 | Z11: 1 | AA11: 1 | AB11: 1 | AC11: 1 | AD11: 1 | AE11: 1 | AF11: 1
A12: Sprint 2 | B12: 10 | C12: L20 Plan d’assurance qualité (PAQ) de l’étape 2 | D12: 45366 | E12: Oui | F12: 45366 | G12: 1 | H12: 0 | I12: 1 | J12: 1 | K12: 1 | L12: 1 | M12: 1 | N12: 1 | O12: 1 | P12: 1 | Q12: 1 | R12: 1 | S12: 1 | T12: 1 | U12: 1 | V12: 1 | W12: 1 | X12: 1 | Y12: 1 | Z12: 1 | AA12: 1 | AB12: 1 | AC12: 1 | AD12: 1 | AE12: 1 | AF12: 1
B13: 11 | C13: L21 Spécifications fonctionnelles détaillées de l’étape 2 | D13: 45366 | E13: Oui | F13: 45366 | G13: 1 | H13: 0 | I13: 1 | J13: 1 | K13: 1 | L13: 1 | M13: 1 | N13: 1 | O13: 1 | P13: 1 | Q13: 1 | R13: 1 | S13: 1 | T13: 1 | U13: 1 | V13: 1 | W13: 1 | X13: 1 | Y13: 1 | Z13: 1 | AA13: 1 | AB13: 1 | AC13: 1 | AD13: 1 | AE13: 1 | AF13: 1
B14: 12 | C14: L22 Spécifications techniques détaillées de l’étape 2 | D14: 45366 | E14: Oui | F14: 45366 | G14: 1 | H14: 0 | I14: 1 | J14: 1 | K14: 1 | L14: 1 | M14: 1 | N14: 1 | O14: 1 | P14: 1 | Q14: 1 | R14: 1 | S14: 1 | T14: 1 | U14: 1 | V14: 1 | W14: 1 | X14: 1 | Y14: 1 | Z14: 1 | AA14: 1 | AB14: 1 | AC14: 1 | AD14: 1 | AE14: 1 | AF14: 1
B15: 13 | C15: L23 Manuel d’utilisation version 2 | D15: 45388 | E15: Oui | F15: 45388 | G15: 1 | H15: 0 | I15: 0 | J15: 1 | K15: 1 | L15: 1 | M15: 1 | N15: 1 | O15: 1 | P15: 1 | Q15: 1 | R15: 1 | S15: 1 | T15: 1 | U15: 1 | V15: 1 | W15: 1 | X15: 1 | Y15: 1 | Z15: 1 | AA15: 1 | AB15: 1 | AC15: 1 | AD15: 1 | AE15: 1 | AF15: 1
B16: 14 | C16: L24 Manuel d’installation et d’administration version 2 | D16: 45388 | E16: Oui | F16: 45388 | G16: 1 | H16: 0 | I16: 0 | J16: 1 | K16: 1 | L16: 1 | M16: 1 | N16: 1 | O16: 1 | P16: 1 | Q16: 1 | R16: 1 | S16: 1 | T16: 1 | U16: 1 | V16: 1 | W16: 1 | X16: 1 | Y16: 1 | Z16: 1 | AA16: 1 | AB16: 1 | AC16: 1 | AD16: 1 | AE16: 1 | AF16: 1
B17: 15 | C17: L25 Version 2 du Système | D17: 45388 | E17: Oui | F17: 45388 | G17: 1 | H17: 0 | I17: 0 | J17: 1 | K17: 1 | L17: 1 | M17: 1 | N17: 1 | O17: 1 | P17: 1 | Q17: 1 | R17: 1 | S17: 1 | T17: 1 | U17: 1 | V17: 1 | W17: 1 | X17: 1 | Y17: 1 | Z17: 1 | AA17: 1 | AB17: 1 | AC17: 1 | AD17: 1 | AE17: 1 | AF17: 1
A18: Sprint 3 | B18: 16 | C18: L30 Plan d’assurance qualité (PAQ) de l’étape 3 | D18: 45398 | E18: Oui | F18: 45398 | G18: 1 | H18: 0 | I18: 0 | J18: 1 | K18: 1 | L18: 1 | M18: 1 | N18: 1 | O18: 1 | P18: 1 | Q18: 1 | R18: 1 | S18: 1 | T18: 1 | U18: 1 | V18: 1 | W18: 1 | X18: 1 | Y18: 1 | Z18: 1 | AA18: 1 | AB18: 1 | AC18: 1 | AD18: 1 | AE18: 1 | AF18: 1
B19: 17 | C19: L31 Spécifications fonctionnelles détaillées de l’étape 3 | D19: 45398 | E19: Oui | F19: 45398 | G19: 1 | H19: 0 | I19: 0 | J19: 1 | K19: 1 | L19: 1 | M19: 1 | N19: 1 | O19: 1 | P19: 1 | Q19: 1 | R19: 1 | S19: 1 | T19: 1 | U19: 1 | V19: 1 | W19: 1 | X19: 1 | Y19: 1 | Z19: 1 | AA19: 1 | AB19: 1 | AC19: 1 | AD19: 1 | AE19: 1 | AF19: 1
B20: 18 | C20: L32 Spécifications techniques détaillées de l’étape 3 | D20: 45398 | E20: Oui | F20: 45398 | G20: 1 | H20: 0 | I20: 0 | J20: 1 | K20: 1 | L20: 1 | M20: 1 | N20: 1 | O20: 1 | P20: 1 | Q20: 1 | R20: 1 | S20: 1 | T20: 1 | U20: 1 | V20: 1 | W20: 1 | X20: 1 | Y20: 1 | Z20: 1 | AA20: 1 | AB20: 1 | AC20: 1 | AD20: 1 | AE20: 1 | AF20: 1
B21: 19 | C21: L33 Manuel d’utilisation version 3 | D21: 45418 | E21: Oui | F21: 45418 | G21: 1 | H21: 0 | I21: 0 | J21: 0 | K21: 1 | L21: 1 | M21: 1 | N21: 1 | O21: 1 | P21: 1 | Q21: 1 | R21: 1 | S21: 1 | T21: 1 | U21: 1 | V21: 1 | W21: 1 | X21: 1 | Y21: 1 | Z21: 1 | AA21: 1 | AB21: 1 | AC21: 1 | AD21: 1 | AE21: 1 | AF21: 1
B22: 20 | C22: L34 Manuel d’installation et d’administration version 3 | D22: 45418 | E22: Oui | F22: 45418 | G22: 1 | H22: 0 | I22: 0 | J22: 0 | K22: 1 | L22: 1 | M22: 1 | N22: 1 | O22: 1 | P22: 1 | Q22: 1 | R22: 1 | S22: 1 | T22: 1 | U22: 1 | V22: 1 | W22: 1 | X22: 1 | Y22: 1 | Z22: 1 | AA22: 1 | AB22: 1 | AC22: 1 | AD22: 1 | AE22: 1 | AF22: 1
B23: 21 | C23: L35 Version 3 du Système | D23: 45418 | E23: Oui | F23: 45418 | G23: 1 | H23: 0 | I23: 0 | J23: 0 | K23: 1 | L23: 1 | M23: 1 | N23: 1 | O23: 1 | P23: 1 | Q23: 1 | R23: 1 | S23: 1 | T23: 1 | U23: 1 | V23: 1 | W23: 1 | X23: 1 | Y23: 1 | Z23: 1 | AA23: 1 | AB23: 1 | AC23: 1 | AD23: 1 | AE23: 1 | AF23: 1
A24: Sprint 4 | B24: 22 | C24: L40 Plan d’assurance qualité (PAQ) de l’étape 4 | D24: 45429 | E24: Oui | F24: 45429 | G24: 1 | H24: 0 | I24: 0 | J24: 0 | K24: 1 | L24: 1 | M24: 1 | N24: 1 | O24: 1 | P24: 1 | Q24: 1 | R24: 1 | S24: 1 | T24: 1 | U24: 1 | V24: 1 | W24: 1 | X24: 1 | Y24: 1 | Z24: 1 | AA24: 1 | AB24: 1 | AC24: 1 | AD24: 1 | AE24: 1 | AF24: 1
B25: 23 | C25: L41 Spécifications fonctionnelles détaillées de l’étape 4 | D25: 45429 | E25: Oui | F25: 45429 | G25: 1 | H25: 0 | I25: 0 | J25: 0 | K25: 1 | L25: 1 | M25: 1 | N25: 1 | O25: 1 | P25: 1 | Q25: 1 | R25: 1 | S25: 1 | T25: 1 | U25: 1 | V25: 1 | W25: 1 | X25: 1 | Y25: 1 | Z25: 1 | AA25: 1 | AB25: 1 | AC25: 1 | AD25: 1 | AE25: 1 | AF25: 1
B26: 24 | C26: L42 Spécifications techniques détaillées de l’étape 4 | D26: 45429 | E26: Oui | F26: 45429 | G26: 1 | H26: 0 | I26: 0 | J26: 0 | K26: 1 | L26: 1 | M26: 1 | N26: 1 | O26: 1 | P26: 1 | Q26: 1 | R26: 1 | S26: 1 | T26: 1 | U26: 1 | V26: 1 | W26: 1 | X26: 1 | Y26: 1 | Z26: 1 | AA26: 1 | AB26: 1 | AC26: 1 | AD26: 1 | AE26: 1 | AF26: 1
B27: 25 | C27: L43 Manuel d’utilisation version 4 | D27: 45449 | E27: Oui | F27: 45449 | G27: 1 | H27: 0 | I27: 0 | J27: 0 | K27: 0 | L27: 1 | M27: 1 | N27: 1 | O27: 1 | P27: 1 | Q27: 1 | R27: 1 | S27: 1 | T27: 1 | U27: 1 | V27: 1 | W27: 1 | X27: 1 | Y27: 1 | Z27: 1 | AA27: 1 | AB27: 1 | AC27: 1 | AD27: 1 | AE27: 1 | AF27: 1
B28: 26 | C28: L44 Manuel d’installation et d’administration version 4 | D28: 45449 | E28: Oui | F28: 45449 | G28: 1 | H28: 0 | I28: 0 | J28: 0 | K28: 0 | L28: 1 | M28: 1 | N28: 1 | O28: 1 | P28: 1 | Q28: 1 | R28: 1 | S28: 1 | T28: 1 | U28: 1 | V28: 1 | W28: 1 | X28: 1 | Y28: 1 | Z28: 1 | AA28: 1 | AB28: 1 | AC28: 1 | AD28: 1 | AE28: 1 | AF28: 1
B29: 27 | C29: L45 Version 4 du Système | D29: 45449 | E29: Oui | F29: 45449 | G29: 1 | H29: 0 | I29: 0 | J29: 0 | K29: 0 | L29: 1 | M29: 1 | N29: 1 | O29: 1 | P29: 1 | Q29: 1 | R29: 1 | S29: 1 | T29: 1 | U29: 1 | V29: 1 | W29: 1 | X29: 1 | Y29: 1 | Z29: 1 | AA29: 1 | AB29: 1 | AC29: 1 | AD29: 1 | AE29: 1 | AF29: 1
A30: Sprint 5 | B30: 28 | C30: L50 Plan d’assurance qualité (PAQ) de l’étape 5 | D30: 45470 | E30: Oui | F30: 45470 | G30: 1 | H30: 0 | I30: 0 | J30: 0 | K30: 0 | L30: 1 | M30: 1 | N30: 1 | O30: 1 | P30: 1 | Q30: 1 | R30: 1 | S30: 1 | T30: 1 | U30: 1 | V30: 1 | W30: 1 | X30: 1 | Y30: 1 | Z30: 1 | AA30: 1 | AB30: 1 | AC30: 1 | AD30: 1 | AE30: 1 | AF30: 1
B31: 29 | C31: L51 Spécifications fonctionnelles détaillées de l’étape 5 | D31: 45470 | E31: Oui | F31: 45470 | G31: 1 | H31: 0 | I31: 0 | J31: 0 | K31: 0 | L31: 1 | M31: 1 | N31: 1 | O31: 1 | P31: 1 | Q31: 1 | R31: 1 | S31: 1 | T31: 1 | U31: 1 | V31: 1 | W31: 1 | X31: 1 | Y31: 1 | Z31: 1 | AA31: 1 | AB31: 1 | AC31: 1 | AD31: 1 | AE31: 1 | AF31: 1
B32: 30 | C32: L52 Spécifications techniques détaillées de l’étape 5 | D32: 45470 | E32: Oui | F32: 45470 | G32: 1 | H32: 0 | I32: 0 | J32: 0 | K32: 0 | L32: 1 | M32: 1 | N32: 1 | O32: 1 | P32: 1 | Q32: 1 | R32: 1 | S32: 1 | T32: 1 | U32: 1 | V32: 1 | W32: 1 | X32: 1 | Y32: 1 | Z32: 1 | AA32: 1 | AB32: 1 | AC32: 1 | AD32: 1 | AE32: 1 | AF32: 1
B33: 31 | C33: L53 Manuel d’utilisation version 5 | D33: 45481 | E33: Oui | F33: 45481 | G33: 1 | H33: 0 | I33: 0 | J33: 0 | K33: 0 | L33: 0 | M33: 1 | N33: 1 | O33: 1 | P33: 1 | Q33: 1 | R33: 1 | S33: 1 | T33: 1 | U33: 1 | V33: 1 | W33: 1 | X33: 1 | Y33: 1 | Z33: 1 | AA33: 1 | AB33: 1 | AC33: 1 | AD33: 1 | AE33: 1 | AF33: 1
B34: 32 | C34: L54 Manuel d’installation et d’administration version 5 | D34: 45481 | E34: Oui | F34: 45481 | G34: 1 | H34: 0 | I34: 0 | J34: 0 | K34: 0 | L34: 0 | M34: 1 | N34: 1 | O34: 1 | P34: 1 | Q34: 1 | R34: 1 | S34: 1 | T34: 1 | U34: 1 | V34: 1 | W34: 1 | X34: 1 | Y34: 1 | Z34: 1 | AA34: 1 | AB34: 1 | AC34: 1 | AD34: 1 | AE34: 1 | AF34: 1
B35: 33 | C35: L55 Version 5 du Système | D35: 45481 | E35: Oui | F35: 45481 | G35: 1 | H35: 0 | I35: 0 | J35: 0 | K35: 0 | L35: 0 | M35: 1 | N35: 1 | O35: 1 | P35: 1 | Q35: 1 | R35: 1 | S35: 1 | T35: 1 | U35: 1 | V35: 1 | W35: 1 | X35: 1 | Y35: 1 | Z35: 1 | AA35: 1 | AB35: 1 | AC35: 1 | AD35: 1 | AE35: 1 | AF35: 1
A36: Sprint 6 | B36: 34 | C36: L60 Plan d’assurance qualité (PAQ) de l’étape 6 | D36: 45506 | E36: Oui | F36: 45506 | G36: 1 | H36: 0 | I36: 0 | J36: 0 | K36: 0 | L36: 0 | M36: 0 | N36: 1 | O36: 1 | P36: 1 | Q36: 1 | R36: 1 | S36: 1 | T36: 1 | U36: 1 | V36: 1 | W36: 1 | X36: 1 | Y36: 1 | Z36: 1 | AA36: 1 | AB36: 1 | AC36: 1 | AD36: 1 | AE36: 1 | AF36: 1
B37: 35 | C37: L61 Spécifications fonctionnelles détaillées de l’étape 6 | D37: 45506 | E37: Oui | F37: 45506 | G37: 1 | H37: 0 | I37: 0 | J37: 0 | K37: 0 | L37: 0 | M37: 0 | N37: 1 | O37: 1 | P37: 1 | Q37: 1 | R37: 1 | S37: 1 | T37: 1 | U37: 1 | V37: 1 | W37: 1 | X37: 1 | Y37: 1 | Z37: 1 | AA37: 1 | AB37: 1 | AC37: 1 | AD37: 1 | AE37: 1 | AF37: 1
B38: 36 | C38: L62 Spécifications techniques détaillées de l’étape 6 | D38: 45506 | E38: Oui | F38: 45506 | G38: 1 | H38: 0 | I38: 0 | J38: 0 | K38: 0 | L38: 0 | M38: 0 | N38: 1 | O38: 1 | P38: 1 | Q38: 1 | R38: 1 | S38: 1 | T38: 1 | U38: 1 | V38: 1 | W38: 1 | X38: 1 | Y38: 1 | Z38: 1 | AA38: 1 | AB38: 1 | AC38: 1 | AD38: 1 | AE38: 1 | AF38: 1
B39: 37 | C39: L63 Manuel d’utilisation version 6 | D39: 45513 | E39: Oui | F39: 45513 | G39: 1 | H39: 0 | I39: 0 | J39: 0 | K39: 0 | L39: 0 | M39: 0 | N39: 1 | O39: 1 | P39: 1 | Q39: 1 | R39: 1 | S39: 1 | T39: 1 | U39: 1 | V39: 1 | W39: 1 | X39: 1 | Y39: 1 | Z39: 1 | AA39: 1 | AB39: 1 | AC39: 1 | AD39: 1 | AE39: 1 | AF39: 1
B40: 38 | C40: L64 Manuel d’installation et d’administration version 6 | D40: 45513 | E40: Oui | F40: 45513 | G40: 1 | H40: 0 | I40: 0 | J40: 0 | K40: 0 | L40: 0 | M40: 0 | N40: 1 | O40: 1 | P40: 1 | Q40: 1 | R40: 1 | S40: 1 | T40: 1 | U40: 1 | V40: 1 | W40: 1 | X40: 1 | Y40: 1 | Z40: 1 | AA40: 1 | AB40: 1 | AC40: 1 | AD40: 1 | AE40: 1 | AF40: 1
B41: 39 | C41: L65 Version 6 du Système | D41: 45513 | E41: Oui | F41: 45513 | G41: 1 | H41: 0 | I41: 0 | J41: 0 | K41: 0 | L41: 0 | M41: 0 | N41: 1 | O41: 1 | P41: 1 | Q41: 1 | R41: 1 | S41: 1 | T41: 1 | U41: 1 | V41: 1 | W41: 1 | X41: 1 | Y41: 1 | Z41: 1 | AA41: 1 | AB41: 1 | AC41: 1 | AD41: 1 | AE41: 1 | AF41: 1
A42: Sprint 7 | B42: 40 | C42: L70 Plan d’assurance qualité (PAQ) de l’étape 7 | D42: 45540 | E42: Oui | F42: 45540 | G42: 1 | H42: 0 | I42: 0 | J42: 0 | K42: 0 | L42: 0 | M42: 0 | N42: 0 | O42: 1 | P42: 1 | Q42: 1 | R42: 1 | S42: 1 | T42: 1 | U42: 1 | V42: 1 | W42: 1 | X42: 1 | Y42: 1 | Z42: 1 | AA42: 1 | AB42: 1 | AC42: 1 | AD42: 1 | AE42: 1 | AF42: 1
B43: 41 | C43: L71 Spécifications fonctionnelles détaillées de l’étape 7 | D43: 45540 | E43: Oui | F43: 45540 | G43: 1 | H43: 0 | I43: 0 | J43: 0 | K43: 0 | L43: 0 | M43: 0 | N43: 0 | O43: 1 | P43: 1 | Q43: 1 | R43: 1 | S43: 1 | T43: 1 | U43: 1 | V43: 1 | W43: 1 | X43: 1 | Y43: 1 | Z43: 1 | AA43: 1 | AB43: 1 | AC43: 1 | AD43: 1 | AE43: 1 | AF43: 1
B44: 42 | C44: L72 Spécifications techniques détaillées de l’étape 7 | D44: 45540 | E44: Oui | F44: 45540 | G44: 1 | H44: 0 | I44: 0 | J44: 0 | K44: 0 | L44: 0 | M44: 0 | N44: 0 | O44: 1 | P44: 1 | Q44: 1 | R44: 1 | S44: 1 | T44: 1 | U44: 1 | V44: 1 | W44: 1 | X44: 1 | Y44: 1 | Z44: 1 | AA44: 1 | AB44: 1 | AC44: 1 | AD44: 1 | AE44: 1 | AF44: 1
B45: 43 | C45: L73 Manuel d’utilisation version 7 | D45: 45545 | E45: Oui | F45: 45545 | G45: 1 | H45: 0 | I45: 0 | J45: 0 | K45: 0 | L45: 0 | M45: 0 | N45: 0 | O45: 1 | P45: 1 | Q45: 1 | R45: 1 | S45: 1 | T45: 1 | U45: 1 | V45: 1 | W45: 1 | X45: 1 | Y45: 1 | Z45: 1 | AA45: 1 | AB45: 1 | AC45: 1 | AD45: 1 | AE45: 1 | AF45: 1
B46: 44 | C46: L74 Manuel d’installation et d’administration version 7 | D46: 45545 | E46: Oui | F46: 45545 | G46: 1 | H46: 0 | I46: 0 | J46: 0 | K46: 0 | L46: 0 | M46: 0 | N46: 0 | O46: 1 | P46: 1 | Q46: 1 | R46: 1 | S46: 1 | T46: 1 | U46: 1 | V46: 1 | W46: 1 | X46: 1 | Y46: 1 | Z46: 1 | AA46: 1 | AB46: 1 | AC46: 1 | AD46: 1 | AE46: 1 | AF46: 1
B47: 45 | C47: L75 Version 7 du Système | D47: 45545 | E47: Oui | F47: 45545 | G47: 1 | H47: 0 | I47: 0 | J47: 0 | K47: 0 | L47: 0 | M47: 0 | N47: 0 | O47: 1 | P47: 1 | Q47: 1 | R47: 1 | S47: 1 | T47: 1 | U47: 1 | V47: 1 | W47: 1 | X47: 1 | Y47: 1 | Z47: 1 | AA47: 1 | AB47: 1 | AC47: 1 | AD47: 1 | AE47: 1 | AF47: 1
A48: Sprint 8 | B48: 46 | C48: L80 Plan d’assurance qualité (PAQ) de l’étape 8 | D48: 45555 | E48: Oui | F48: 45555 | G48: 1 | H48: 0 | I48: 0 | J48: 0 | K48: 0 | L48: 0 | M48: 0 | N48: 0 | O48: 1 | P48: 1 | Q48: 1 | R48: 1 | S48: 1 | T48: 1 | U48: 1 | V48: 1 | W48: 1 | X48: 1 | Y48: 1 | Z48: 1 | AA48: 1 | AB48: 1 | AC48: 1 | AD48: 1 | AE48: 1 | AF48: 1
B49: 47 | C49: L81 Spécifications fonctionnelles détaillées de l’étape 8 | D49: 45555 | E49: Oui | F49: 45555 | G49: 1 | H49: 0 | I49: 0 | J49: 0 | K49: 0 | L49: 0 | M49: 0 | N49: 0 | O49: 1 | P49: 1 | Q49: 1 | R49: 1 | S49: 1 | T49: 1 | U49: 1 | V49: 1 | W49: 1 | X49: 1 | Y49: 1 | Z49: 1 | AA49: 1 | AB49: 1 | AC49: 1 | AD49: 1 | AE49: 1 | AF49: 1
B50: 48 | C50: L82 Spécifications techniques détaillées de l’étape 8 | D50: 45555 | E50: Oui | F50: 45555 | G50: 1 | H50: 0 | I50: 0 | J50: 0 | K50: 0 | L50: 0 | M50: 0 | N50: 0 | O50: 1 | P50: 1 | Q50: 1 | R50: 1 | S50: 1 | T50: 1 | U50: 1 | V50: 1 | W50: 1 | X50: 1 | Y50: 1 | Z50: 1 | AA50: 1 | AB50: 1 | AC50: 1 | AD50: 1 | AE50: 1 | AF50: 1
B51: 49 | C51: L83 Manuel d’utilisation version 8 | D51: 45573 | E51: Oui | F51: 45582 | G51: 1 | H51: 0 | I51: 0 | J51: 0 | K51: 0 | L51: 0 | M51: 0 | N51: 0 | O51: 0 | P51: 0 | Q51: 1 | R51: 1 | S51: 1 | T51: 1 | U51: 1 | V51: 1 | W51: 1 | X51: 1 | Y51: 1 | Z51: 1 | AA51: 1 | AB51: 1 | AC51: 1 | AD51: 1 | AE51: 1 | AF51: 1
B52: 50 | C52: L84 Manuel d’installation et d’administration version 8 | D52: 45573 | E52: Oui | F52: 45582 | G52: 1 | H52: 0 | I52: 0 | J52: 0 | K52: 0 | L52: 0 | M52: 0 | N52: 0 | O52: 0 | P52: 0 | Q52: 1 | R52: 1 | S52: 1 | T52: 1 | U52: 1 | V52: 1 | W52: 1 | X52: 1 | Y52: 1 | Z52: 1 | AA52: 1 | AB52: 1 | AC52: 1 | AD52: 1 | AE52: 1 | AF52: 1
B53: 51 | C53: L85 Version 8 du Système | D53: 45573 | E53: Oui | F53: 45582 | G53: 1 | H53: 0 | I53: 0 | J53: 0 | K53: 0 | L53: 0 | M53: 0 | N53: 0 | O53: 0 | P53: 0 | Q53: 1 | R53: 1 | S53: 1 | T53: 1 | U53: 1 | V53: 1 | W53: 1 | X53: 1 | Y53: 1 | Z53: 1 | AA53: 1 | AB53: 1 | AC53: 1 | AD53: 1 | AE53: 1 | AF53: 1
A54: Sprint 9 | B54: 52 | C54: L90 Plan d’assurance qualité (PAQ) de l’étape 9 | D54: 45611 | E54: Oui | F54: 45611 | G54: 1 | H54: 0 | I54: 0 | J54: 0 | K54: 0 | L54: 0 | M54: 0 | N54: 0 | O54: 0 | P54: 0 | Q54: 1 | R54: 1 | S54: 1 | T54: 1 | U54: 1 | V54: 1 | W54: 1 | X54: 1 | Y54: 1 | Z54: 1 | AA54: 1 | AB54: 1 | AC54: 1 | AD54: 1 | AE54: 1 | AF54: 1
B55: 53 | C55: L91 Spécifications fonctionnelles détaillées de l’étape 9 | D55: 45611 | E55: Oui | F55: 45611 | G55: 1 | H55: 0 | I55: 0 | J55: 0 | K55: 0 | L55: 0 | M55: 0 | N55: 0 | O55: 0 | P55: 0 | Q55: 1 | R55: 1 | S55: 1 | T55: 1 | U55: 1 | V55: 1 | W55: 1 | X55: 1 | Y55: 1 | Z55: 1 | AA55: 1 | AB55: 1 | AC55: 1 | AD55: 1 | AE55: 1 | AF55: 1
B56: 54 | C56: L92 Spécifications techniques détaillées de l’étape 9 | D56: 45611 | E56: Oui | F56: 45611 | G56: 1 | H56: 0 | I56: 0 | J56: 0 | K56: 0 | L56: 0 | M56: 0 | N56: 0 | O56: 0 | P56: 0 | Q56: 1 | R56: 1 | S56: 1 | T56: 1 | U56: 1 | V56: 1 | W56: 1 | X56: 1 | Y56: 1 | Z56: 1 | AA56: 1 | AB56: 1 | AC56: 1 | AD56: 1 | AE56: 1 | AF56: 1
B57: 55 | C57: L93 Manuel d’utilisation version 9 | D57: 45618 | E57: Oui | F57: 45618 | G57: 1 | H57: 0 | I57: 0 | J57: 0 | K57: 0 | L57: 0 | M57: 0 | N57: 0 | O57: 0 | P57: 0 | Q57: 1 | R57: 1 | S57: 1 | T57: 1 | U57: 1 | V57: 1 | W57: 1 | X57: 1 | Y57: 1 | Z57: 1 | AA57: 1 | AB57: 1 | AC57: 1 | AD57: 1 | AE57: 1 | AF57: 1
B58: 56 | C58: L94 Manuel d’installation et d’administration version 9 | D58: 45618 | E58: Oui | F58: 45618 | G58: 1 | H58: 0 | I58: 0 | J58: 0 | K58: 0 | L58: 0 | M58: 0 | N58: 0 | O58: 0 | P58: 0 | Q58: 1 | R58: 1 | S58: 1 | T58: 1 | U58: 1 | V58: 1 | W58: 1 | X58: 1 | Y58: 1 | Z58: 1 | AA58: 1 | AB58: 1 | AC58: 1 | AD58: 1 | AE58: 1 | AF58: 1
B59: 57 | C59: L95 Version 9 du Système | D59: 45618 | E59: Oui | F59: 45618 | G59: 1 | H59: 0 | I59: 0 | J59: 0 | K59: 0 | L59: 0 | M59: 0 | N59: 0 | O59: 0 | P59: 0 | Q59: 1 | R59: 1 | S59: 1 | T59: 1 | U59: 1 | V59: 1 | W59: 1 | X59: 1 | Y59: 1 | Z59: 1 | AA59: 1 | AB59: 1 | AC59: 1 | AD59: 1 | AE59: 1 | AF59: 1
A60: Sprint 10 | B60: 58 | C60: L100 Plan d’assurance qualité (PAQ) de l’étape 10 | D60: 45622 | E60: Oui | F60: 45629 | G60: 1 | H60: 0 | I60: 0 | J60: 0 | K60: 0 | L60: 0 | M60: 0 | N60: 0 | O60: 0 | P60: 0 | Q60: 0 | R60: 1 | S60: 1 | T60: 1 | U60: 1 | V60: 1 | W60: 1 | X60: 1 | Y60: 1 | Z60: 1 | AA60: 1 | AB60: 1 | AC60: 1 | AD60: 1 | AE60: 1 | AF60: 1
B61: 59 | C61: L101 Spécifications fonctionnelles détaillées de l’étape 10 | D61: 45622 | E61: Oui | F61: 45629 | G61: 1 | H61: 0 | I61: 0 | J61: 0 | K61: 0 | L61: 0 | M61: 0 | N61: 0 | O61: 0 | P61: 0 | Q61: 0 | R61: 1 | S61: 1 | T61: 1 | U61: 1 | V61: 1 | W61: 1 | X61: 1 | Y61: 1 | Z61: 1 | AA61: 1 | AB61: 1 | AC61: 1 | AD61: 1 | AE61: 1 | AF61: 1
B62: 60 | C62: L102 Spécifications techniques détaillées de l’étape 10 | D62: 45622 | E62: Oui | F62: 45629 | G62: 1 | H62: 0 | I62: 0 | J62: 0 | K62: 0 | L62: 0 | M62: 0 | N62: 0 | O62: 0 | P62: 0 | Q62: 0 | R62: 1 | S62: 1 | T62: 1 | U62: 1 | V62: 1 | W62: 1 | X62: 1 | Y62: 1 | Z62: 1 | AA62: 1 | AB62: 1 | AC62: 1 | AD62: 1 | AE62: 1 | AF62: 1
B63: 61 | C63: L103 Manuel d’utilisation version 10 | D63: 45635 | E63: Oui | F63: 45639 | G63: 1 | H63: 0 | I63: 0 | J63: 0 | K63: 0 | L63: 0 | M63: 0 | N63: 0 | O63: 0 | P63: 0 | Q63: 0 | R63: 1 | S63: 1 | T63: 1 | U63: 1 | V63: 1 | W63: 1 | X63: 1 | Y63: 1 | Z63: 1 | AA63: 1 | AB63: 1 | AC63: 1 | AD63: 1 | AE63: 1 | AF63: 1
B64: 62 | C64: L104 Manuel d’installation et d’administration version 10 | D64: 45635 | E64: Oui | F64: 45639 | G64: 1 | H64: 0 | I64: 0 | J64: 0 | K64: 0 | L64: 0 | M64: 0 | N64: 0 | O64: 0 | P64: 0 | Q64: 0 | R64: 1 | S64: 1 | T64: 1 | U64: 1 | V64: 1 | W64: 1 | X64: 1 | Y64: 1 | Z64: 1 | AA64: 1 | AB64: 1 | AC64: 1 | AD64: 1 | AE64: 1 | AF64: 1
B65: 63 | C65: L105 Version 10 du Système | D65: 45635 | E65: Oui | F65: 45639 | G65: 1 | H65: 0 | I65: 0 | J65: 0 | K65: 0 | L65: 0 | M65: 0 | N65: 0 | O65: 0 | P65: 0 | Q65: 0 | R65: 1 | S65: 1 | T65: 1 | U65: 1 | V65: 1 | W65: 1 | X65: 1 | Y65: 1 | Z65: 1 | AA65: 1 | AB65: 1 | AC65: 1 | AD65: 1 | AE65: 1 | AF65: 1
A66: Sprint 11 | B66: 64 | C66: L110 Plan d’assurance qualité (PAQ) de l’étape 11 | D66: 45652 | E66: Oui | F66: 45652 | G66: 1 | H66: 0 | I66: 0 | J66: 0 | K66: 0 | L66: 0 | M66: 0 | N66: 0 | O66: 0 | P66: 0 | Q66: 0 | R66: 1 | S66: 1 | T66: 1 | U66: 1 | V66: 1 | W66: 1 | X66: 1 | Y66: 1 | Z66: 1 | AA66: 1 | AB66: 1 | AC66: 1 | AD66: 1 | AE66: 1 | AF66: 1
B67: 65 | C67: L111 Spécifications fonctionnelles détaillées de l’étape 11 | D67: 45652 | E67: Oui | F67: 45652 | G67: 1 | H67: 0 | I67: 0 | J67: 0 | K67: 0 | L67: 0 | M67: 0 | N67: 0 | O67: 0 | P67: 0 | Q67: 0 | R67: 1 | S67: 1 | T67: 1 | U67: 1 | V67: 1 | W67: 1 | X67: 1 | Y67: 1 | Z67: 1 | AA67: 1 | AB67: 1 | AC67: 1 | AD67: 1 | AE67: 1 | AF67: 1
B68: 66 | C68: L112 Spécifications techniques détaillées de l’étape 11 | D68: 45652 | E68: Oui | F68: 45652 | G68: 1 | H68: 0 | I68: 0 | J68: 0 | K68: 0 | L68: 0 | M68: 0 | N68: 0 | O68: 0 | P68: 0 | Q68: 0 | R68: 1 | S68: 1 | T68: 1 | U68: 1 | V68: 1 | W68: 1 | X68: 1 | Y68: 1 | Z68: 1 | AA68: 1 | AB68: 1 | AC68: 1 | AD68: 1 | AE68: 1 | AF68: 1
B69: 67 | C69: L113 Manuel d’utilisation version 11 | D69: 45665 | E69: Oui | F69: 45666 | G69: 1 | H69: 0 | I69: 0 | J69: 0 | K69: 0 | L69: 0 | M69: 0 | N69: 0 | O69: 0 | P69: 0 | Q69: 0 | R69: 0 | S69: 1 | T69: 1 | U69: 1 | V69: 1 | W69: 1 | X69: 1 | Y69: 1 | Z69: 1 | AA69: 1 | AB69: 1 | AC69: 1 | AD69: 1 | AE69: 1 | AF69: 1
B70: 68 | C70: L114 Manuel d’installation et d’administration version 11 | D70: 45665 | E70: Oui | F70: 45666 | G70: 1 | H70: 0 | I70: 0 | J70: 0 | K70: 0 | L70: 0 | M70: 0 | N70: 0 | O70: 0 | P70: 0 | Q70: 0 | R70: 0 | S70: 1 | T70: 1 | U70: 1 | V70: 1 | W70: 1 | X70: 1 | Y70: 1 | Z70: 1 | AA70: 1 | AB70: 1 | AC70: 1 | AD70: 1 | AE70: 1 | AF70: 1
B71: 69 | C71: L115 Version 11 du Système | D71: 45665 | E71: Oui | F71: 45666 | G71: 1 | H71: 0 | I71: 0 | J71: 0 | K71: 0 | L71: 0 | M71: 0 | N71: 0 | O71: 0 | P71: 0 | Q71: 0 | R71: 0 | S71: 1 | T71: 1 | U71: 1 | V71: 1 | W71: 1 | X71: 1 | Y71: 1 | Z71: 1 | AA71: 1 | AB71: 1 | AC71: 1 | AD71: 1 | AE71: 1 | AF71: 1
A72: Sprint 12 | B72: 70 | C72: L120 Plan d’assurance qualité (PAQ) de l’étape 12 | D72: 45685 | E72: Oui | F72: 45685 | G72: 1 | H72: 0 | I72: 0 | J72: 0 | K72: 0 | L72: 0 | M72: 0 | N72: 0 | O72: 0 | P72: 0 | Q72: 0 | R72: 0 | S72: 1 | T72: 1 | U72: 1 | V72: 1 | W72: 1 | X72: 1 | Y72: 1 | Z72: 1 | AA72: 1 | AB72: 1 | AC72: 1 | AD72: 1 | AE72: 1 | AF72: 1
B73: 71 | C73: L121 Spécifications fonctionnelles détaillées de l’étape 12 | D73: 45685 | E73: Oui | F73: 45685 | G73: 1 | H73: 0 | I73: 0 | J73: 0 | K73: 0 | L73: 0 | M73: 0 | N73: 0 | O73: 0 | P73: 0 | Q73: 0 | R73: 0 | S73: 1 | T73: 1 | U73: 1 | V73: 1 | W73: 1 | X73: 1 | Y73: 1 | Z73: 1 | AA73: 1 | AB73: 1 | AC73: 1 | AD73: 1 | AE73: 1 | AF73: 1
B74: 72 | C74: L122 Spécifications techniques détaillées de l’étape 12 | D74: 45685 | E74: Oui | F74: 45685 | G74: 1 | H74: 0 | I74: 0 | J74: 0 | K74: 0 | L74: 0 | M74: 0 | N74: 0 | O74: 0 | P74: 0 | Q74: 0 | R74: 0 | S74: 1 | T74: 1 | U74: 1 | V74: 1 | W74: 1 | X74: 1 | Y74: 1 | Z74: 1 | AA74: 1 | AB74: 1 | AC74: 1 | AD74: 1 | AE74: 1 | AF74: 1
B75: 73 | C75: L123 Manuel d’utilisation version 12 | D75: 45694 | E75: Oui | F75: 45694 | G75: 1 | H75: 0 | I75: 0 | J75: 0 | K75: 0 | L75: 0 | M75: 0 | N75: 0 | O75: 0 | P75: 0 | Q75: 0 | R75: 0 | S75: 0 | T75: 1 | U75: 1 | V75: 1 | W75: 1 | X75: 1 | Y75: 1 | Z75: 1 | AA75: 1 | AB75: 1 | AC75: 1 | AD75: 1 | AE75: 1 | AF75: 1
B76: 74 | C76: L124 Manuel d’installation et d’administration version 12 | D76: 45694 | E76: Oui | F76: 45694 | G76: 1 | H76: 0 | I76: 0 | J76: 0 | K76: 0 | L76: 0 | M76: 0 | N76: 0 | O76: 0 | P76: 0 | Q76: 0 | R76: 0 | S76: 0 | T76: 1 | U76: 1 | V76: 1 | W76: 1 | X76: 1 | Y76: 1 | Z76: 1 | AA76: 1 | AB76: 1 | AC76: 1 | AD76: 1 | AE76: 1 | AF76: 1
B77: 75 | C77: L125 Version 12 du Système | D77: 45694 | E77: Oui | F77: 45694 | G77: 1 | H77: 0 | I77: 0 | J77: 0 | K77: 0 | L77: 0 | M77: 0 | N77: 0 | O77: 0 | P77: 0 | Q77: 0 | R77: 0 | S77: 0 | T77: 1 | U77: 1 | V77: 1 | W77: 1 | X77: 1 | Y77: 1 | Z77: 1 | AA77: 1 | AB77: 1 | AC77: 1 | AD77: 1 | AE77: 1 | AF77: 1
A78: Maintenance 12 mois | B78: Après 6 mois de maintenance à partir de la fin du mois 12
B79: 76 | C79: Rapport de maintenance curative | D79: 45900 | E79: Oui | F79: 45894 | G79: =MAX(H79:AF79) -> 1 | H79: 0 | I79: 0 | J79: 0 | K79: 0 | L79: 0 | M79: 0 | N79: 0 | O79: 0 | P79: 0 | Q79: 0 | R79: 0 | S79: 0 | T79: 0 | U79: 0 | V79: 0 | W79: 0 | X79: 0 | Y79: 0 | Z79: 1 | AA79: 1 | AB79: 1 | AC79: 1 | AD79: 1 | AE79: 1 | AF79: 1
B80: 77 | C80: Rapport de maintenance évolutive (Facultatif) | D80: 45900 | E80: Oui | F80: =F79 -> 45894 | G80: =MAX(H80:AF80) -> 1 | H80: 0 | I80: 0 | J80: 0 | K80: 0 | L80: 0 | M80: 0 | N80: 0 | O80: 0 | P80: 0 | Q80: 0 | R80: 0 | S80: 0 | T80: 0 | U80: 0 | V80: 0 | W80: 0 | X80: 0 | Y80: 0 | Z80: 1 | AA80: 1 | AB80: 1 | AC80: 1 | AD80: 1 | AE80: 1 | AF80: 1
B81: 78 | C81: Rapport de maintenance préventive (Facultatif) | D81: 45900 | E81: Oui | F81: =F80 -> 45894 | G81: =MAX(H81:AF81) -> 1 | H81: 0 | I81: 0 | J81: 0 | K81: 0 | L81: 0 | M81: 0 | N81: 0 | O81: 0 | P81: 0 | Q81: 0 | R81: 0 | S81: 0 | T81: 0 | U81: 0 | V81: 0 | W81: 0 | X81: 0 | Y81: 0 | Z81: 1 | AA81: 1 | AB81: 1 | AC81: 1 | AD81: 1 | AE81: 1 | AF81: 1
B82: Après 6 mois de maintenance à partir de la fin du mois 18
B83: 79 | C83: Rapport de maintenance curative | D83: =EDATE(D81,6) -> 46081 | E83: Non | G83: =MAX(H83:AF83) -> 0 | H83: 0 | I83: 0 | J83: 0 | K83: 0 | L83: 0 | M83: 0 | N83: 0 | O83: 0 | P83: 0 | Q83: 0 | R83: 0 | S83: 0 | T83: 0 | U83: 0 | V83: 0 | W83: 0 | X83: 0 | Y83: 0 | Z83: 0 | AA83: 0 | AB83: 0 | AC83: 0 | AD83: 0 | AE83: 0 | AF83: 0
B84: 80 | C84: Rapport de maintenance évolutive (Facultatif) | D84: =D83 -> 46081 | E84: Non | G84: =MAX(H84:AF84) -> 0 | H84: 0 | I84: 0 | J84: 0 | K84: 0 | L84: 0 | M84: 0 | N84: 0 | O84: 0 | P84: 0 | Q84: 0 | R84: 0 | S84: 0 | T84: 0 | U84: 0 | V84: 0 | W84: 0 | X84: 0 | Y84: 0 | Z84: 0 | AA84: 0 | AB84: 0 | AC84: 0 | AD84: 0 | AE84: 0 | AF84: 0
B85: 81 | C85: Rapport de maintenance préventive (Facultatif) | D85: =D84 -> 46081 | E85: Non | G85: =MAX(H85:AF85) -> 0 | H85: 0 | I85: 0 | J85: 0 | K85: 0 | L85: 0 | M85: 0 | N85: 0 | O85: 0 | P85: 0 | Q85: 0 | R85: 0 | S85: 0 | T85: 0 | U85: 0 | V85: 0 | W85: 0 | X85: 0 | Y85: 0 | Z85: 0 | AA85: 0 | AB85: 0 | AC85: 0 | AD85: 0 | AE85: 0 | AF85: 0
C86: Delivery % | G86: =AVERAGE(G3:G85) -> 0.96296296 | H86: =AVERAGE(H3:H85) -> 0.049382716 | I86: =AVERAGE(I3:I85) -> 0.14814815 | J86: =AVERAGE(J3:J85) -> 0.22222222 | K86: =AVERAGE(K3:K85) -> 0.2962963 | L86: =AVERAGE(L3:L85) -> 0.37037037 | M86: =AVERAGE(M3:M85) -> 0.40740741 | N86: =AVERAGE(N3:N85) -> 0.48148148 | ... AF86: =AVERAGE(AF3:AF85) -> 0.96296296

Sheet Base des Risques
A1: Risques Projet
A3: Id | B3: Actif | C3: Libellé | D3: Description de l'impact (qu'est ce qui peut arriver ?) | E3: Type de risque | F3: Sévérité, Gravité | G3: Probabilité | H3: Risques ou pénalités | I3: Impact (coût en TND pour ST2i) | J3: Impact pondéré (Prob. X Imp.) | K3: Traitement | L3: Id Mesure | M3: Mesure : action préventive ou corrective (diminuant la probabilité ou l'impact) | N3: Coût estimé (en TND pour ST2i) | O3: Action réalisée? | P3: Date de clôture | Q3: Efficience | R3: Provision pondérée initiale | S3: Commentaires
A4: 1 | J4: =G4*I4 -> 0
A5: 2 | J5: =G5*I5 -> 0
A6: 3 | J6: =G6*I6 -> 0
A7: 4 | J7: =G7*I7 -> 0
A8: 5 | J8: =G8*I8 -> 0
A9: 6 | J9: =G9*I9 -> 0
A10: 7 | J10: =G10*I10 -> 0
A11: 8 | J11: =G11*I11 -> 0
A12: 9 | J12: =G12*I12 -> 0
A13: 10 | J13: =G13*I13 -> 0
J15: =SUM(J4:J13) -> 0 | N15: =SUM(N4:N13) -> 0

Sheet Liste des actions
A1: Liste des actions du projet | G1: Dashboard
A3: N° | B3: Code | C3: Constat/ Action | D3: Partie Prenante | E3: Origine | F3: Plan d'action | I3: Resp | J3: Date réalisation prévu | K3: % de réalisation | L3: Date réalisation Réelle | M3: Suivi de l'efficacité | O3: Commentaires | P3: Clôture
M4: Date | N4: Efficace O/N
F5: Analyse des causes | G5: Type d'action | H5: Sous action | P5: Date | Q5: O/N
A6: 1
A7: 2
A8: 3
A9: 4
A10: 5
A11: 6
A12: 7
A13: 12
A14: 13
A15: 14
A16: 15
A17: 16
... A51: 50
A52: Total | C52: =COUNTA(C6:C51) -> 0
G53: =SUM(G52:G52) -> 0 | K53: =K52 -> 0

Sheet Registre Changement
A1: Changements Projet
A3: Demande de changement | C3: Demandeur | D3: Impact du changement | E3: Changement validé? | F3: Responsable | G3: Date limite de réalisation | H3: Réalisé O/N | I3: Date de réalisation | J3: Efficace O/N | K3: Date de suivi d'efficacité | L3: Date de clôture

Sheet Avenants
A1: Date avenant | B1: JH | C1: Garantie JH | D1: Montant | E1: Devise | F1: Montant TND | G1: PPR TND | H1: PPP TND | I1: Coûts TND | J1: Marge nette TND | K1: Marge nette %
D2: 0 | G2: 0 | H2: 0 | I2: 0 | J2: 0 | K2: =IFERROR((I2-J2)/B2,"") | M2: Dashboard
K3: =IFERROR((I3-J3)/B3,"")
K4: =IFERROR((I4-J4)/B4,"")
K5: =IFERROR((I5-J5)/B5,"")
K6: =IFERROR((I6-J6)/B6,"")
K7: =IFERROR((I7-J7)/B7,"")
K8: =IFERROR((I8-J8)/B8,"")
K9: =IFERROR((I9-J9)/B9,"")
K10: =IFERROR((I10-J10)/B10,"")
K11: =IFERROR((I11-J11)/B11,"")

Sheet Statistiques
A1: MOIS SELECTIONNÉ | C1: =Dashboard!C22 -> 45997
A2: Projet | C2: =Dashboard!C7 -> A24001 - PFS_AIE
A3: Date début | C3: ='Fiche identification'!B11 -> 45328
A4: Durée du projet (J) | C4: ='Fiche identification'!B13 -> 731
A6: BUDGET ET DATES | B6: Mois selectionné | C6: =C3 -> 45328 | D6: =DATE(YEAR(C6), MONTH(C6)+1, DAY(C6)) -> 45357 | E6: =DATE(YEAR(D6), MONTH(D6)+1, DAY(D6)) -> 45388 | F6: =DATE(YEAR(E6), MONTH(E6)+1, DAY(E6)) -> 45418 | G6: =DATE(YEAR(F6), MONTH(F6)+1, DAY(F6)) -> 45449 | H6: =DATE(YEAR(G6), MONTH(G6)+1, DAY(G6)) -> 45479 | I6: =DATE(YEAR(H6), MONTH(H6)+1, DAY(H6)) -> 45510 | J6: =DATE(YEAR(I6), MONTH(I6)+1, DAY(I6)) -> 45541 | K6: =DATE(YEAR(J6), MONTH(J6)+1, DAY(J6)) -> 45571 | ... AA6: =DATE(YEAR(Z6), MONTH(Z6)+1, DAY(Z6)) -> 46059
A7: Montant affaire | B7: =HLOOKUP($C$1,$C$6:$AA$9,2,0) -> 1269861.5 | C7: ='Fiche identification'!$B$23 -> 1269861.5 | D7: ='Fiche identification'!$B$23 -> 1269861.5 | E7: ='Fiche identification'!$B$23 -> 1269861.5 | F7: ='Fiche identification'!$B$23 -> 1269861.5 | G7: ='Fiche identification'!$B$23 -> 1269861.5 | H7: ='Fiche identification'!$B$23 -> 1269861.5 | I7: ='Fiche identification'!$B$23 -> 1269861.5 | J7: ='Fiche identification'!$B$23 -> 1269861.5 | ... AA7: ='Fiche identification'!$B$23 -> 1269861.5
A8: Date de fin prévue | B8: =HLOOKUP($C$1,$C$6:$AA$9,3,0) -> 46058 | C8: ='Fiche identification'!$B12 -> 46058 | D8: ='Fiche identification'!$B12 -> 46058 | E8: ='Fiche identification'!$B12 -> 46058 | F8: ='Fiche identification'!$B12 -> 46058 | G8: ='Fiche identification'!$B12 -> 46058 | H8: ='Fiche identification'!$B12 -> 46058 | I8: ='Fiche identification'!$B12 -> 46058 | J8: ='Fiche identification'!$B12 -> 46058 | ... AA8: ='Fiche identification'!$B12 -> 46058
A9: Date fin prévisionnelle (estimation chef de projet) | B9: =HLOOKUP($C$1,$C$6:$AA$9,4,0) -> 46058 | C9: 46058 | D9: 46058 | E9: 46058 | F9: 46058 | G9: 46058 | H9: 46058 | I9: 46058 | J9: 46058 | K9: 46058 | L9: 46058 | M9: 46058 | N9: 46058 | O9: 46058 | P9: 46058 | Q9: 46058 | R9: 46058 | S9: 46058 | T9: 46058 | U9: 46058 | V9: 46058 | W9: 46058 | X9: 46058 | Y9: 46058 | Z9: 46058 | AA9: 46058
A10: Montant honoraires | B10: =HLOOKUP($C$1,$C$6:$AA$10,5,0) -> #REF! | C10: ='Fiche identification'!$B$24 -> #REF! | D10: ='Fiche identification'!$B$24 -> #REF! | E10: ='Fiche identification'!$B$24 -> #REF! | F10: ='Fiche identification'!$B$24 -> #REF! | G10: ='Fiche identification'!$B$24 -> #REF! | H10: ='Fiche identification'!$B$24 -> #REF! | I10: ='Fiche identification'!$B$24 -> #REF! | J10: ='Fiche identification'!$B$24 -> #REF! | ... AA10: ='Fiche identification'!$B$24 -> #REF!
A12: TAUX D'AVANCEMENT GLOBAL | B12: Mois selectionné | C12: =C3 -> 45328 | D12: =DATE(YEAR(C12), MONTH(C12)+1, DAY(C12)) -> 45357 | E12: =DATE(YEAR(D12), MONTH(D12)+1, DAY(D12)) -> 45388 | F12: =DATE(YEAR(E12), MONTH(E12)+1, DAY(E12)) -> 45418 | G12: =DATE(YEAR(F12), MONTH(F12)+1, DAY(F12)) -> 45449 | H12: =DATE(YEAR(G12), MONTH(G12)+1, DAY(G12)) -> 45479 | I12: =DATE(YEAR(H12), MONTH(H12)+1, DAY(H12)) -> 45510 | J12: =DATE(YEAR(I12), MONTH(I12)+1, DAY(I12)) -> 45541 | K12: =DATE(YEAR(J12), MONTH(J12)+1, DAY(J12)) -> 45571 | ... AA12: =DATE(YEAR(Z12), MONTH(Z12)+1, DAY(Z12)) -> 46059
A13: Consommation des délais | B13: =HLOOKUP($C$1,$C$12:$AA$16,2,0) -> 0.95622435 | C13: =(C12-$C3+30)/$C4 -> 0.041039672 | D13: =(D12-$C3+30)/$C4 -> 0.080711354 | E13: =(E12-$C3+30)/$C4 -> 0.12311902 | F13: =(F12-$C3+30)/$C4 -> 0.16415869 | G13: =(G12-$C3+30)/$C4 -> 0.20656635 | H13: =(H12-$C3+30)/$C4 -> 0.24760602 | I13: =(I12-$C3+30)/$C4 -> 0.29001368 | J13: =(J12-$C3+30)/$C4 -> 0.33242134 | ... AA13: =(AA12-$C3+30)/$C4 -> 1.0410397
A14: Earned Value | B14: =HLOOKUP($C$1,$C$12:$AA$16,3,0) -> 0.99 | C14: =1/14 -> 0.071428571 | D14: =2/14 -> 0.14285714 | E14: =3/14 -> 0.21428571 | F14: =4/14 -> 0.28571429 | G14: =5/14 -> 0.35714286 | H14: =6/14 -> 0.42857143 | I14: =7/14 -> 0.5 | J14: =8/14 -> 0.57142857 | K14: =9/14 -> 0.64285714 | L14: =10/14 -> 0.71428571 | M14: =11/14 -> 0.78571429 | N14: 0.81 | O14: 0.85 | P14: 0.85 | Q14: 0.85 | R14: 0.85 | S14: 0.85 | T14: 0.85 | U14: 0.95 | V14: 0.96 | W14: 0.97 | X14: 0.98 | Y14: 0.99 | Z14: 0.99 | AA14: 1
A15: Delivery | B15: =HLOOKUP($C$1,$C$12:$AA$16,4,0) -> 0.96296296 | C15: ='Livrables projet'!H86 -> 0.049382716 | D15: ='Livrables projet'!I86 -> 0.14814815 | E15: ='Livrables projet'!J86 -> 0.22222222 | F15: ='Livrables projet'!K86 -> 0.2962963 | G15: ='Livrables projet'!L86 -> 0.37037037 | H15: ='Livrables projet'!M86 -> 0.40740741 | I15: ='Livrables projet'!N86 -> 0.48148148 | J15: ='Livrables projet'!O86 -> 0.59259259 | ... AA15: ='Livrables projet'!AF86 -> 0.96296296
A16: Facturation | B16: =HLOOKUP($C$1,$C$12:$AA$16,5,0) -> #REF! | C16: =IF((C22/C10)=0,B16,C22/C7) -> #REF! | D16: =IF((D22/D10)=0,C16,D22/D7) -> #REF! | E16: =IF((E22/E10)=0,D16,E22/E7) -> #REF! | F16: =IF((F22/F10)=0,E16,F22/F7) -> #REF! | G16: =IF((G22/G10)=0,F16,G22/G7) -> #REF! | H16: =IF((H22/H10)=0,G16,H22/H7) -> #REF! | I16: =IF((I22/I10)=0,H16,I22/I7) -> #REF! | J16: =IF((J22/J10)=0,I16,J22/J7) -> #REF! | ... V16: =IF((V22/V10)=0,U16,V22/V7) -> #REF! | W16: =IF((W22/W7)=0,V16,W22/W7) -> #REF! | X16: =IF((X22/X7)=0,W16,X22/X7) -> #REF! | Y16: =IF((Y22/Y7)=0,X16,Y22/Y7) -> #REF! | Z16: =IF((Z22/Z7)=0,Y16,Z22/Z7) -> #REF! | AA16: =IF((AA22/AA7)=0,Z16,AA22/AA7) -> #REF!
A19: CHIFFRE D'AFFAIRES | B19: Mois selectionné | C19: =C3 -> 45328 | D19: =DATE(YEAR(C19), MONTH(C19)+1, DAY(C19)) -> 45357 | E19: =DATE(YEAR(D19), MONTH(D19)+1, DAY(D19)) -> 45388 | F19: =DATE(YEAR(E19), MONTH(E19)+1, DAY(E19)) -> 45418 | G19: =DATE(YEAR(F19), MONTH(F19)+1, DAY(F19)) -> 45449 | H19: =DATE(YEAR(G19), MONTH(G19)+1, DAY(G19)) -> 45479 | I19: =DATE(YEAR(H19), MONTH(H19)+1, DAY(H19)) -> 45510 | J19: =DATE(YEAR(I19), MONTH(I19)+1, DAY(I19)) -> 45541 | K19: =DATE(YEAR(J19), MONTH(J19)+1, DAY(J19)) -> 45571 | ... AA19: =DATE(YEAR(Z19), MONTH(Z19)+1, DAY(Z19)) -> 46059
A20: CA Production TND | B20: =HLOOKUP($C$1,$C$19:$AA$23,2,0) -> #REF! | C20: =IF(C14*C10+C21=0,B20,C14*C10+C21) -> #REF! | D20: =IF(D14*D10+D21=0,C20,D14*D10+D21) -> #REF! | E20: =IF(E14*E10+E21=0,D20,E14*E10+E21) -> #REF! | F20: =IF(F14*F10+F21=0,E20,F14*F10+F21) -> #REF! | G20: =IF(G14*G10+G21=0,F20,G14*G10+G21) -> #REF! | H20: =IF(H14*H10+H21=0,G20,H14*H10+H21) -> #REF! | I20: =IF(I14*I10+I21=0,H20,I14*I10+I21) -> #REF! | J20: =IF(J14*J10+J21=0,I20,J14*J10+J21) -> #REF! | ... Z20: =IF(Z14*Z10+Z21=0,Y20,Z14*Z10+Z21) -> #REF! | AA20: =IF(AA14*AA7+AA21=0,Z20,AA14*AA7+AA21) -> 1269861.5
A21: Autres frais facturés | B21: =HLOOKUP($C$1,$C$19:$AA$23,3,0) -> 0 | C21: 0 | D21: 0 | E21: 0 | F21: 0 | G21: 0 | H21: 0 | I21: 0 | J21: 0 | K21: 0 | L21: 0 | M21: 0 | N21: =15*#REF!*#REF! -> #REF! | O21: 0 | P21: 0 | Q21: 0 | R21: 0 | S21: 0 | T21: 0 | U21: 0 | V21: 0 | W21: 0
A22: CA Facturé TND | B22: =HLOOKUP($C$1,$C$19:$AA$23,4,0) -> #REF! | C22: 0 | D22: ='Recap Facturation'!J7 -> #REF! | E22: ='Recap Facturation'!J7 -> #REF! | F22: ='Recap Facturation'!J7 -> #REF! | G22: ='Recap Facturation'!J8 -> #REF! | H22: ='Recap Facturation'!J8 -> #REF! | I22: ='Recap Facturation'!J8 -> #REF! | J22: ='Recap Facturation'!J9 -> #REF! | K22: ='Recap Facturation'!J10 -> #REF! | L22: ='Recap Facturation'!J10 -> #REF! | M22: ='Recap Facturation'!J11 -> #REF! | N22: ='Recap Facturation'!J11 -> #REF! | O22: ='Recap Facturation'!J11 -> #REF! | P22: ='Recap Facturation'!J12 -> #REF! | Q22: ='Recap Facturation'!J12 -> #REF! | R22: =Q22 -> #REF! | S22: =R22 -> #REF! | T22: =S22 -> #REF! | U22: ='Recap Facturation'!J13 -> #REF! | V22: ='Recap Facturation'!J13 -> #REF! | W22: =V22 -> #REF! | X22: =W22 -> #REF! | Y22: =X22 -> #REF! | Z22: =Y22 -> #REF! | AA22: =Z22 -> #REF!
A23: Stock | B23: =HLOOKUP($C$1,$C$19:$AA$23,5,0) -> #REF! | C23: =C20-C22 -> #REF! | D23: =D20-D22 -> #REF! | E23: =E20-E22 -> #REF! | F23: =F20-F22 -> #REF! | G23: =G20-G22 -> #REF! | H23: =H20-H22 -> #REF! | I23: =I20-I22 -> #REF! | J23: =J20-J22 -> #REF! | ... AA23: =AA20-AA22 -> #REF!
A26: COÛTS | B26: Mois selectionné | C26: =C3 -> 45328 | D26: =DATE(YEAR(C26), MONTH(C26)+1, DAY(C26)) -> 45357 | E26: =DATE(YEAR(D26), MONTH(D26)+1, DAY(D26)) -> 45388 | F26: =DATE(YEAR(E26), MONTH(E26)+1, DAY(E26)) -> 45418 | G26: =DATE(YEAR(F26), MONTH(F26)+1, DAY(F26)) -> 45449 | H26: =DATE(YEAR(G26), MONTH(G26)+1, DAY(G26)) -> 45479 | I26: =DATE(YEAR(H26), MONTH(H26)+1, DAY(H26)) -> 45510 | J26: =DATE(YEAR(I26), MONTH(I26)+1, DAY(I26)) -> 45541 | K26: =DATE(YEAR(J26), MONTH(J26)+1, DAY(J26)) -> 45571 | ... AA26: =DATE(YEAR(Z26), MONTH(Z26)+1, DAY(Z26)) -> 46059
A27: Coût initial | B27: =HLOOKUP($C$1,$C$26:$AA$32,2,0) -> #REF! | C27: =#REF! -> #REF! | D27: =#REF! -> #REF! | E27: =#REF! -> #REF! | F27: =#REF! -> #REF! | G27: =#REF! -> #REF! | H27: =#REF! -> #REF! | I27: =#REF! -> #REF! | J27: =#REF! -> #REF! | ... AA27: =#REF! -> #REF!
A28: Coût réel (mois) | B28: =HLOOKUP($C$1,$C$26:$AA$32,3,0) -> 7698.5354 | C28: ='Coût réel Actualisé'!B50 -> 35043.516 | D28: ='Coût réel Actualisé'!C50 -> 35658.787 | E28: ='Coût réel Actualisé'!D50 -> 44244.487 | F28: ='Coût réel Actualisé'!E50 -> 42259.719 | G28: ='Coût réel Actualisé'!F50 -> 47470.959 | H28: ='Coût réel Actualisé'!G50 -> 75676.235 | I28: ='Coût réel Actualisé'!H50 -> 58638.742 | J28: ='Coût réel Actualisé'!I50 -> 69578.676 | ... AA28: ='Coût réel Actualisé'!Z50 -> 0
A29: Autres coûts | B29: =HLOOKUP($C$1,$C$26:$AA$32,4,0) -> 0 | C29: ='Coût réel Actualisé'!B47+'Coût réel Actualisé'!B48+'Coût réel Actualisé'!B49 -> 0 | D29: ='Coût réel Actualisé'!C47+'Coût réel Actualisé'!C48+'Coût réel Actualisé'!C49 -> 0 | E29: ='Coût réel Actualisé'!D47+'Coût réel Actualisé'!D48+'Coût réel Actualisé'!D49 -> 0 | F29: ='Coût réel Actualisé'!E47+'Coût réel Actualisé'!E48+'Coût réel Actualisé'!E49 -> 0 | G29: ='Coût réel Actualisé'!F47+'Coût réel Actualisé'!F48+'Coût réel Actualisé'!F49 -> 0 | H29: ='Coût réel Actualisé'!G47+'Coût réel Actualisé'!G48+'Coût réel Actualisé'!G49 -> 0 | I29: ='Coût réel Actualisé'!H47+'Coût réel Actualisé'!H48+'Coût réel Actualisé'!H49 -> 0 | J29: ='Coût réel Actualisé'!I47+'Coût réel Actualisé'!I48+'Coût réel Actualisé'!I49 -> 0 | ... M29: ='Coût réel Actualisé'!L47+'Coût réel Actualisé'!L48+'Coût réel Actualisé'!L49 -> 0 | N29: ='Coût réel Actualisé'!M47 -> 11408.536 | O29: ='Coût réel Actualisé'!N47 -> 0 | P29: ='Coût réel Actualisé'!O47 -> 0 | Q29: ='Coût réel Actualisé'!P47 -> 0 | R29: ='Coût réel Actualisé'!Q47 -> 0 | S29: ='Coût réel Actualisé'!R47 -> 0 | T29: ='Coût réel Actualisé'!S47 -> 0 | U29: ='Coût réel Actualisé'!T47 -> 0 | ... AA29: ='Coût réel Actualisé'!Z47 -> 0
A30: Coût réel cumul | B30: =HLOOKUP($C$1,$C$26:$AA$32,5,0) -> 667507.88 | C30: =C28 -> 35043.516 | D30: =D28+C30 -> 70702.303 | E30: =E28+D30 -> 114946.79 | F30: =F28+E30 -> 157206.51 | G30: =G28+F30 -> 204677.47 | H30: =H28+G30 -> 280353.7 | I30: =I28+H30 -> 338992.45 | J30: =J28+I30 -> 408571.12 | K30: =K28+J30 -> 473238.98 | ... AA30: =AA28+Z30 -> 667507.88
A31: Coût prévisionnel RAF ETC | B31: =HLOOKUP($C$1,$C$26:$AA$32,6,0) -> #REF! | C31: ='Coût Prévisionnel'!B43 -> #REF! | D31: ='Coût Prévisionnel'!C43 -> #REF! | E31: ='Coût Prévisionnel'!D43 -> #REF! | F31: ='Coût Prévisionnel'!E43 -> #REF! | G31: ='Coût Prévisionnel'!F43 -> #REF! | H31: ='Coût Prévisionnel'!G43 -> #REF! | I31: ='Coût Prévisionnel'!H43 -> #REF! | J31: ='Coût Prévisionnel'!I43 -> #REF! | ... AA31: ='Coût Prévisionnel'!Z43 -> #REF!
A32: Coût prévisionnel EAC | B32: =HLOOKUP($C$1,$C$26:$AA$32,7,0) -> #REF! | C32: =C31+C30 -> #REF! | D32: =D31+D30 -> #REF! | E32: =E31+E30 -> #REF! | F32: =F31+F30 -> #REF! | G32: =G31+G30 -> #REF! | H32: =H31+H30 -> #REF! | I32: =I31+I30 -> #REF! | J32: =J31+J30 -> #REF! | ... AA32: =AA31+AA30 -> #REF!
A35: MARGE NETTE | B35: Mois selectionné | C35: =C3 -> 45328 | D35: =DATE(YEAR(C35), MONTH(C35)+1, DAY(C35)) -> 45357 | E35: =DATE(YEAR(D35), MONTH(D35)+1, DAY(D35)) -> 45388 | F35: =DATE(YEAR(E35), MONTH(E35)+1, DAY(E35)) -> 45418 | G35: =DATE(YEAR(F35), MONTH(F35)+1, DAY(F35)) -> 45449 | H35: =DATE(YEAR(G35), MONTH(G35)+1, DAY(G35)) -> 45479 | I35: =DATE(YEAR(H35), MONTH(H35)+1, DAY(H35)) -> 45510 | J35: =DATE(YEAR(I35), MONTH(I35)+1, DAY(I35)) -> 45541 | K35: =DATE(YEAR(J35), MONTH(J35)+1, DAY(J35)) -> 45571 | ... AA35: =DATE(YEAR(Z35), MONTH(Z35)+1, DAY(Z35)) -> 46059
A36: Marge nette vendue TND | B36: =HLOOKUP($C$1,$C$35:$AA$41,2,0) -> #REF! | C36: =#REF! -> #REF! | D36: =#REF! -> #REF! | E36: =#REF! -> #REF! | F36: =#REF! -> #REF! | G36: =#REF! -> #REF! | H36: =#REF! -> #REF! | I36: =#REF! -> #REF! | J36: =#REF! -> #REF! | ... AA36: =#REF! -> #REF!
A37: Marge nette actuelle TND | B37: =HLOOKUP($C$1,$C$35:$AA$41,3,0) -> #REF! | C37: =C20-C30 -> #REF! | D37: =D20-D30 -> #REF! | E37: =E20-E30 -> #REF! | F37: =F20-F30 -> #REF! | G37: =G20-G30 -> #REF! | H37: =H20-H30 -> #REF! | I37: =I20-I30 -> #REF! | J37: =J20-J30 -> #REF! | ... AA37: =AA20-AA30 -> 602353.58
A38: Marge nette EAC TND | B38: =HLOOKUP($C$1,$C$35:$AA$41,4,0) -> #REF! | C38: =C7-(C30+C31) -> #REF! | D38: =D7-(D30+D31) -> #REF! | E38: =E7-(E30+E31) -> #REF! | F38: =F7-(F30+F31) -> #REF! | G38: =G7-(G30+G31) -> #REF! | H38: =H7-(H30+H31) -> #REF! | I38: =I7-(I30+I31) -> #REF! | J38: =J7-(J30+J31) -> #REF! | ... AA38: =AA7-(AA30+AA31) -> #REF!
A39: Marge nette vendue % | B39: =HLOOKUP($C$1,$C$35:$AA$41,5,0) -> #REF! | C39: =#REF! -> #REF! | D39: =#REF! -> #REF! | E39: =#REF! -> #REF! | F39: =#REF! -> #REF! | G39: =#REF! -> #REF! | H39: =#REF! -> #REF! | I39: =#REF! -> #REF! | J39: =#REF! -> #REF! | ... AA39: =#REF! -> #REF!
A40: Marge nette actuelle % | B40: =HLOOKUP($C$1,$C$35:$AA$41,6,0) -> #REF! | C40: =C37/C20 -> #REF! | D40: =D37/D20 -> #REF! | E40: =E37/E20 -> #REF! | F40: =F37/F20 -> #REF! | G40: =G37/G20 -> #REF! | H40: =H37/H20 -> #REF! | I40: =I37/I20 -> #REF! | J40: =J37/J20 -> #REF! | ... AA40: =AA37/AA20 -> 0.4743459
A41: Marge nette EAC % | B41: =HLOOKUP($C$1,$C$35:$AA$41,7,0) -> #REF! | C41: =C38/C7 -> #REF! | D41: =D38/D7 -> #REF! | E41: =E38/E7 -> #REF! | F41: =F38/F7 -> #REF! | G41: =G38/G7 -> #REF! | H41: =H38/H7 -> #REF! | I41: =I38/I7 -> #REF! | J41: =J38/J7 -> #REF! | ... AA41: =AA38/AA7 -> #REF!
A44: CHARGE HOMME-JOUR | B44: Mois selectionné | C44: =C3 -> 45328 | D44: =DATE(YEAR(C44), MONTH(C44)+1, DAY(C44)) -> 45357 | E44: =DATE(YEAR(D44), MONTH(D44)+1, DAY(D44)) -> 45388 | F44: =DATE(YEAR(E44), MONTH(E44)+1, DAY(E44)) -> 45418 | G44: =DATE(YEAR(F44), MONTH(F44)+1, DAY(F44)) -> 45449 | H44: =DATE(YEAR(G44), MONTH(G44)+1, DAY(G44)) -> 45479 | I44: =DATE(YEAR(H44), MONTH(H44)+1, DAY(H44)) -> 45510 | J44: =DATE(YEAR(I44), MONTH(I44)+1, DAY(I44)) -> 45541 | K44: =DATE(YEAR(J44), MONTH(J44)+1, DAY(J44)) -> 45571 | ... AA44: =DATE(YEAR(Z44), MONTH(Z44)+1, DAY(Z44)) -> 46059
A45: Charge prevue globale | B45: =HLOOKUP($C$1,$C$44:$AA$50,2,0) -> #REF! | C45: =#REF! -> #REF! | D45: =#REF! -> #REF! | E45: =#REF! -> #REF! | F45: =#REF! -> #REF! | G45: =#REF! -> #REF! | H45: =#REF! -> #REF! | I45: =#REF! -> #REF! | J45: =#REF! -> #REF! | ... AA45: =#REF! -> #REF!
A46: Consommés mois en cours (HJ) | B46: =HLOOKUP($C$1,$C$44:$AA$50,3,0) -> 9.625 | C46: ='Coût réel Actualisé'!B26 -> 118 | D46: ='Coût réel Actualisé'!C26 -> 125 | E46: ='Coût réel Actualisé'!D26 -> 186 | F46: ='Coût réel Actualisé'!E26 -> 184 | G46: ='Coût réel Actualisé'!F26 -> 201 | H46: ='Coût réel Actualisé'!G26 -> 230.5 | I46: ='Coût réel Actualisé'!H26 -> 174.75 | J46: ='Coût réel Actualisé'!I26 -> 218.5625 | ... AA46: ='Coût réel Actualisé'!Z26 -> 0
A47: Consommés cumul (HJ) | B47: =HLOOKUP($C$1,$C$44:$AA$50,4,0) -> 2199.1 | C47: ='Coût réel Actualisé'!B27 -> 118 | D47: ='Coût réel Actualisé'!C27 -> 243 | E47: ='Coût réel Actualisé'!D27 -> 429 | F47: ='Coût réel Actualisé'!E27 -> 613 | G47: ='Coût réel Actualisé'!F27 -> 814 | H47: ='Coût réel Actualisé'!G27 -> 1044.5 | I47: ='Coût réel Actualisé'!H27 -> 1219.25 | J47: ='Coût réel Actualisé'!I27 -> 1437.8125 | ... AA47: ='Coût réel Actualisé'!Z27 -> 2199.1
A48: Reste à faire global (HJ) ETC | B48: =HLOOKUP($C$1,$C$44:$AA$50,5,0) -> 12 | C48: ='Coût Prévisionnel'!B24 -> 1769 | D48: ='Coût Prévisionnel'!C24 -> 1654 | E48: ='Coût Prévisionnel'!D24 -> 1529 | F48: ='Coût Prévisionnel'!E24 -> 1394 | G48: ='Coût Prévisionnel'!F24 -> 1229 | H48: ='Coût Prévisionnel'!G24 -> 1009 | I48: ='Coût Prévisionnel'!H24 -> 829 | J48: ='Coût Prévisionnel'!I24 -> 641 | ... AA48: ='Coût Prévisionnel'!Z24 -> 0
A49: Reste à faire global (HJ) EAC | B49: =HLOOKUP($C$1,$C$44:$AA$50,6,0) -> 2211.1 | C49: =C48+C47 -> 1887 | D49: =D48+D47 -> 1897 | E49: =E48+E47 -> 1958 | F49: =F48+F47 -> 2007 | G49: =G48+G47 -> 2043 | H49: =H48+H47 -> 2053.5 | I49: =I48+I47 -> 2048.25 | J49: =J48+J47 -> 2078.8125 | ... AA49: =AA48+AA47 -> 2199.1
A50: Dérive | B50: =HLOOKUP($C$1,$C$44:$AA$50,7,0) -> #REF! | C50: =C49-C45 -> #REF! | D50: =D49-D45 -> #REF! | E50: =E49-E45 -> #REF! | F50: =F49-F45 -> #REF! | G50: =G49-G45 -> #REF! | H50: =H49-H45 -> #REF! | I50: =I49-I45 -> #REF! | J50: =J49-J45 -> #REF! | ... AA50: =AA49-AA45 -> #REF!
A53: FAITS MARQUANTS | B53: Mois selectionné | C53: =C3 -> 45328 | D53: =DATE(YEAR(C53), MONTH(C53)+1, DAY(C53)) -> 45357 | E53: =DATE(YEAR(D53), MONTH(D53)+1, DAY(D53)) -> 45388 | F53: =DATE(YEAR(E53), MONTH(E53)+1, DAY(E53)) -> 45418 | G53: =DATE(YEAR(F53), MONTH(F53)+1, DAY(F53)) -> 45449 | H53: =DATE(YEAR(G53), MONTH(G53)+1, DAY(G53)) -> 45479 | I53: =DATE(YEAR(H53), MONTH(H53)+1, DAY(H53)) -> 45510 | J53: =DATE(YEAR(I53), MONTH(I53)+1, DAY(I53)) -> 45541 | K53: =DATE(YEAR(J53), MONTH(J53)+1, DAY(J53)) -> 45571 | ... AA53: =DATE(YEAR(Z53), MONTH(Z53)+1, DAY(Z53)) -> 46059
A54: Observations et faits marquants | B54: =HLOOKUP($C$1,$C$53:$AA$54,2,0) -> à prévoir les frais de déplacement de AHB (à facturer) | C54: RAS | D54: ='Situation actuelle'!B10 -> RAS | E54: ='Situation actuelle'!C10 -> RAS | F54: ='Situation actuelle'!D10 -> RAS | G54: ='Situation actuelle'!E10 -> RAS | H54: ='Situation actuelle'!F10 -> RAS | I54: ='Situation actuelle'!G10 -> RAS | J54: ='Situation actuelle'!H10 -> RAS | K54: ='Situation actuelle'!I10 -> RAS | ... X54: ='Situation actuelle'!V10 -> RAS | Y54: à prévoir les frais de déplacement de AHB (à facturer) | Z54: à prévoir les frais de déplacement de AHB (à facturer) | AA54: à prévoir les frais de déplacement de AHB (à facturer)

Sheet Dashboard
B4: TABLEAU DE BORD | C4: =C22 -> 45997 | U4: KPIs Projet
C6: Affaire | R6: Evolution KPIs
C7: ='Fiche identification'!B2 -> A24001 - PFS_AIE | AE7: Retour
C9: Intitulé
C10: ='Fiche identification'!B5 -> Mise à jour technologique et mise à niveau du SIG-I pour integrer les besoins du projet Filets Sociaux adaptatifs et d'Inclusion Economique | E10: Montant Affaire | G10: Date debut | I10: Date fin revue | K10: Jours-hommes | O10: Marge nette vendue
E11: =Statistiques!B7 -> 1269861.5 | G11: =Statistiques!C3 -> 45328 | I11: =Statistiques!B8 -> 46058 | O11: =Statistiques!B39 -> #REF!
C12: Client | K12: Prévus global | L12: =Statistiques!B45 -> #REF! | O12: =Statistiques!B36 -> #REF!
C13: ='Fiche identification'!B4 -> Projet Filets Sociaux Adaptatifs et Inclusion Economique | E13: DELAIS | F13: =Statistiques!B13 -> 0.95622435 | R13: Mise à jour contrat
H14: Reste (en mois) y compris période de garantie | I14: =(I11-C22+1-30)/30 -> 1.0666667
C15: Durée cont. (jours) | K15: Consommés | L15: =Statistiques!B47 -> 2199.1
C16: =Statistiques!B8-Statistiques!C3+1 -> 731 | E16: EARNED VALUE | F16: =Statistiques!B14 -> 0.99 | R16: Mise à jour avancement
O17: Marge nette actuelle
C18: Chef de Projet | K18: Reste à Faire | L18: =Statistiques!B48 -> 12 | O18: =Statistiques!B40 -> #REF!
C19: ='Fiche identification'!B10 -> Ahmed Amine Amiri | E19: DELIVERY | F19: =Statistiques!B15 -> 0.96296296 | O19: =Statistiques!B37 -> #REF! | R19: Mise à jour facturation
K20: Dérive | L20: =Statistiques!B50 -> #REF!
C21: Mois
C22: 45997 | E22: FACTURATION | F22: =Statistiques!B16 -> #REF!
E24: Date fin prév. | F24: =Statistiques!B9 -> 46058 | K24: Chiffre d'affaires
C25: Faits marquants | H25: Derive (en mois) | I25: =(F24-I11)/30 -> 0 | O25: Marge nette EAC
O26: =Statistiques!B41 -> #REF!
C27: =Statistiques!B54 -> à prévoir les frais de déplacement de AHB (à facturer) | H27: Coût initial | I27: =Statistiques!B27 -> #REF! | K27: CA. Production | L27: =Statistiques!B20 -> #REF! | O27: =Statistiques!B38 -> #REF!
H29: Coût réel cumulé | I29: =Statistiques!B30 -> 667507.88 | K29: Facturé | L29: =Statistiques!B22 -> #REF!
H31: Coût ETC | I31: =Statistiques!B31 -> #REF! | K31: Stock | L31: =Statistiques!B23 -> #REF!
U33: N° de facture | V33: Objet | W33: % | X33: Montant | Y33: Reste à facturer en TND | Z33: Emise (Oui/Non) | AA33: Date initiale | AB33: Date prévisonnelle actualisée | AC33: Date réelle | AD33: Dérive | AE33: Commentaires
U34: Facture 1 | V34: Facture Sprint 1 | W34: 0.1 | X34: 118438 | Y34: ='Recap Facturation'!I2-Tableau1[[#This Row],[Montant]] -> 1151423.5 | Z34: Oui | AA34: 45367 | AB34: 45367 | AC34: 45365 | AD34: =IF(ISBLANK(Tableau1[[#This Row],[Date réelle]]),IF(TODAY()>AA34,AA34-TODAY()+1,0),Tableau1[[#This Row],[Date initiale]]-Tableau1[[#This Row],[Date réelle]]+1) -> 3
U35: Facture 2 | V35: Facture Sprint 2+3+4 | W35: 0.16 | X35: 188981 | Y35: =Y34-Tableau1[[#This Row],[Montant]] -> 962442.46 | Z35: Oui | AA35: 45459 | AB35: 45459 | AC35: 45496 | AD35: =IF(ISBLANK(Tableau1[[#This Row],[Date réelle]]),IF(TODAY()>AA35,AA35-TODAY()+1,0),Tableau1[[#This Row],[Date initiale]]-Tableau1[[#This Row],[Date réelle]]+1) -> -36
U36: Facture 3 | V36: Facture Sprint 5+6 | W36: 0.16 | X36: 190080 | Y36: =Y35-Tableau1[[#This Row],[Montant]] -> 772362.46 | Z36: Oui | AA36: 45520 | AB36: 45565 | AC36: 45565 | AD36: =IF(ISBLANK(Tableau1[[#This Row],[Date réelle]]),IF(TODAY()>AA36,AA36-TODAY()+1,0),Tableau1[[#This Row],[Date initiale]]-Tableau1[[#This Row],[Date réelle]]+1) -> -44
U37: Facture 4 | V37: Facture Sprint 7+8 | W37: 0.16 | X37: 187791.35 | Y37: =Y36-Tableau1[[#This Row],[Montant]] -> 584571.12 | Z37: Oui | AA37: 45581 | AB37: 45590 | AC37: 45593 | AD37: =IF(ISBLANK(Tableau1[[#This Row],[Date réelle]]),IF(TODAY()>AA37,AA37-TODAY()+1,0),Tableau1[[#This Row],[Date initiale]]-Tableau1[[#This Row],[Date réelle]]+1) -> -11
U38: Facture 5 | V38: Facture Sprint 9+10 | W38: 0.16 | X38: 187430.48 | Y38: =Y37-Tableau1[[#This Row],[Montant]] -> 397140.64 | Z38: Oui | AA38: 45642 | AB38: 45646 | AC38: 45657 | AD38: =IF(ISBLANK(Tableau1[[#This Row],[Date réelle]]),IF(TODAY()>AA38,AA38-TODAY()+1,0),Tableau1[[#This Row],[Date initiale]]-Tableau1[[#This Row],[Date réelle]]+1) -> -14
U39: Facture 6 | V39: Facture Sprint 11+12 | W39: 0.16 | X39: 187430.48 | Y39: =Y38-Tableau1[[#This Row],[Montant]] -> 209710.15 | AA39: 45704 | AB39: 45763 | AD39: =IF(ISBLANK(Tableau1[[#This Row],[Date réelle]]),IF(TODAY()>AA39,AA39-TODAY()+1,0),Tableau1[[#This Row],[Date initiale]]-Tableau1[[#This Row],[Date réelle]]+1) -> -481
U40: Facture 7 | V40: MNT 18 premiers mois | W40: 0.05 | X40: 58572.025 | Y40: =Y39-Tableau1[[#This Row],[Montant]] -> 151138.13 | AA40: 45885 | AB40: 45885 | AD40: =IF(ISBLANK(Tableau1[[#This Row],[Date réelle]]),IF(TODAY()>AA40,AA40-TODAY()+1,0),Tableau1[[#This Row],[Date initiale]]-Tableau1[[#This Row],[Date réelle]]+1) -> -300
U41: Facture 8 | V41: MNT 6 derniers mois | W41: 0.05 | X41: 58572.025 | Y41: =Y40-Tableau1[[#This Row],[Montant]] -> 92566.105 | AA41: 46069 | AB41: 46069 | AD41: =IF(ISBLANK(Tableau1[[#This Row],[Date réelle]]),IF(TODAY()>AA41,AA41-TODAY()+1,0),Tableau1[[#This Row],[Date initiale]]-Tableau1[[#This Row],[Date réelle]]+1) -> -116
U45: N° de facture | V45: Date prévisonnelle actualisée | W45: Montant prévu | X45: Montant facturé
U46: Facture 1 | V46: 45367 | W46: ='Recap Facturation'!$I$3*W34 -> 117144.05 | X46: 118438
U47: Facture 2 | V47: 45459 | W47: ='Recap Facturation'!$I$3*W35 -> 187430.48 | X47: 188981
U48: Facture 3 | V48: 45565 | W48: ='Recap Facturation'!$I$3*W36 -> 187430.48 | X48: 190080
U49: Facture 4 | V49: 45590 | W49: ='Recap Facturation'!$I$3*W37 -> 187430.48 | X49: 187791.35
U50: Facture 5 | V50: 45646 | W50: ='Recap Facturation'!$I$3*W38 -> 187430.48 | X50: 187430.48
U51: Facture 6 | V51: 45704 | W51: ='Recap Facturation'!$I$3*W39 -> 187430.48 | X51: 187430.48
U52: Facture 7 | V52: 45885 | W52: ='Recap Facturation'!$I$3*W40 -> 58572.025 | X52: 58572.025
U53: Facture 8 | V53: 46069 | W53: ='Recap Facturation'!$I$3*W41 -> 58572.025 | X53: 58572.025

Sheet Glossaire
A2: GLOSSAIRE DES INDICATEURS DE MANAGEMENT DES PROJETS
A4: Indicateur | B4: Unité | C4: Signification | D4: Méthode de calcul/estimation
A5: Earned Value | B5: % | C5: Taux d'avancement réel du projet | D5: A déduire depuis l’avancement des tâches élémentaires du projet (à extraire depuis l'avancement du planning du projet) ou à estimer par le chef du projet (méthode d'estimation à l'appui)
A6: Delivrery | B6: % | C6: Taux de livraison qui mesure la part des éléments livrés par rapport à ce qui était planifié Selon le projet, un livrable peut être un rapport, un module, une mise à disposition de ressources, une dépense prévue ou toute prestation ou partie de prestation prévue dans le cadre du contrat | D6: Delivery= (Nombre de livrables réalisés/ Nombre de livrables planifiés) ×100
A7: Charge totale consommée | B7: JH | C7: Total des imputations de l’équipe projet en homme-jour à date | D7: A extraire depuis KIMAI et remplir la feuille du coût actualisé
A8: RAF (Reste à Faire) | B8: JH | C8: Selon les tâches restantes du projet, estimer la charge en homme-jour encore nécessaire pour achever toutes les tâches restantes du projetl. Il n’est pas forcément lié aux estimations initiales du projet | D8: RAF= Charge restante en HJ (A extraire depuis le plan de charges actualisé) -Charges totales consommées
A9: Dérive | B9: JH | C9: Correspond au dépassement des charges en homme-jours par rapport aux prévisions initiales qui est mentionné dans le DI | D9: Dérives= Charges vendues (mentionnés dans le DI) -Charges totales consommées -RAF
A10: Cumul CA Production | B10: Devise | C10: Budget correspondant au travail effectué, indépendamment du budget réellement dépensé | D10: Cumul CA Production= Total contrat X Taux d'avancement du projet (EV%)
A11: FAE/Stock TND | B11: Devise | C11: CA correspondant au travail fourni mais non encore facturé | D11: FAE= CA Production - Total Facturé
A12: Marge nette vendue | B12: % | C12: Marge nette prévue dans le devis interne | D12: A extraire depuis le Devis Interne Marge Nette vendue = (Prix de vente-Côut total projet)/Prix de vente
A13: Marge nette actuelle | B13: Devise | C13: Marge nette à date en DT, elle mesure la rentabilité du projet après avoir déduit toutes les dépenses, y compris les autres charges (frais remboursables, autres frais). | D13: Marge Nette Actuelle = Cumul CA production-Côut actuel à date
A14: Marge actuelle | B14: % | C14: Mesure la rentabilité du projet à date (taux en %) | D14: % Marge actuelle= Marge nette actuelle / Cumul CA production à date
A15: Marge nette EAC | B15: Devise | C15: Marge estimée à la finalisation du projet (EAC:Estimate at Completion) | D15: Marge Nette EAC=Budget total- (Coût actuel + coût prévisionnel)
... A20: TCC | B20: Devise | C20: Toutes Charges Comprises: c'est le coût total du collaborateur y compris le coût salarial, achats et fournitures pour le projet et les autres coûts indirects de l'entreprise (frais administratifs, moyer, électricité et eau, entretien, utilitaires…) | D20: TCC= Coût salarial + Autres coûts (généralement estimés à 70% des coûts salariales)

Sheet Paramètres
C2: Description probabilité | D2: Valeur | F2: Affichage client
C3: Risque éteint | D3: 0 | F3: Oui
C4: Très peu probable | D4: 0.2 | F4: Non
C5: Peu probable | D5: 0.4
C6: Probable | D6: 0.6
C7: Très probable | D7: 0.8
C8: Avéré | D8: 1
C10: Description sévérité | D10: Valeur sévérité | E10: Exemples client | F10: Exemples ST2i | G10: Max % | H10: Max TND | I10: =D10 -> Valeur sévérité
C11: Mineur | D11: 1 | E11: Ressenti marginal, cosmétique | F11: Coûts/délais/qualité inchangés | G11: 0.025 | H11: 25000 | I11: =D11 -> 1
C12: Modéré | D12: 2 | E12: Le problème a un impact, sensible mais acceptable pour le client | F12: Coûts/délais/qualité restent dans les hypothèses basses | G12: 0.05 | H12: 50000 | I12: =D12 -> 2
C13: Majeur | D13: 3 | E13: Le business du client est impacté, fonctionne avec difficulté | F13: Coûts/délais/qualité impactés | G13: 0.1 | H13: 100000 | I13: =D13 -> 3
C14: Critique | D14: 4 | E14: Le cœur de métier du client est fortement impacté, la chaine ne fonctionne plus | F14: Arrêt du projet | G14: 10,0% et + | H14: 100 kTND et + | I14: =D14 -> 4
C16: Traitement | D16: Valeur | E16: Description traitement | G16: Statut | I16: Classes d'actifs
C17: Réduction | D17: 1 | E17: Le risque est en cours de traitement, on tente de le réduire (actions) | G17: Tous | I17: Client
C18: Acceptation | D18: 2 | E18: On accepte le risque en totalité ou résiduel, après réduction | G18: =C17 -> Réduction | I18: Collaborateurs ST2i
C19: Evitement | D19: 3 | E19: Le risque n'est plus là, suite par exemple à une action de fond | I19: Contrat
C20: Transfert | D20: 4 | E20: On externalise la responsabilité du risque à un sous-traitant par contrat | I20: Organisation ST2i
I21: Réputation / image de marque
I22: Services généraux
C23: VigiReport | D23: Types de risques | F23: Description efficience | G23: Valeur | I23: SI à réaliser ou exploiter
C24: 0 | D24: (Aucun) | F24: Très satisfaisant | G24: 1 | I24: SI ST2i
C25: 1 | D25: Juridique | F25: Satisfaisant | G25: 2 | I25: SI du client
C26: 1 | D26: Financier | F26: Insuffisant | G26: 3 | I26: Partenaire
C27: 3 | D27: Stabilité des exigences client | F27: Très insuffisant | G27: 4 | I27: Autre actif
C28: 4 | D28: Faisabilité technique
C29: 5 | D29: Sécurité prestation | F29: Mois du projet
C30: 6 | D30: Tenue des conventions de service | F30: 45297
C31: 7 | D31: Délai | F31: 45328
C32: 8 | D32: Recette | F32: 45357
C33: 2 | D33: Organisation humaine | F33: 45388
C34: 9 | D34: Satisf. client | F34: 45418
F35: 45449
F36: 45479
F37: 45510
F38: 45541
F39: 45571
F40: 45602
F41: 45632
F42: 45663
F43: 45694
F44: 45722
F45: 45753
F46: 45783
... F55: 46059
